Workbook
Name Slicer_Cost_type: #N/A
Name Slicer_Resource_Provider: #N/A
Name Slicer_Resource_Provider1: #N/A
Name Slicer_Resource_provider21: #N/A
Name Slicer_Status: #N/A
Name Slicer_Status2: #N/A
Name Slicer_Workstream: #N/A
Name Slicer_Workstream2: #N/A
Name Slicer_Workstream3: #N/A

Sheet Read me
A1: Page Level Info
A2: Pages | B2: Information | C2: Connected to the Dashboard | D2: DO NOT EDIT,DELETE ANY FORMULAS. IF IT IS NEEDED PLEASE INFORM THE DEVELOPER
A3: Resource Static | B3: Static Page to Capture Manpower LE details | C3: No
A4: $Dashboard | B4: Overview of Planned vs Actual monthly and Total views Data is fetched from IT Manpower LE and Other LE tabs - Update these tabs to view the correct information | C4: No
A5: Business Manpower LE | B5: Manpower LE details captured and maintained by business | C5: No
A6: IT Manpower LE | B6: Manpower LE details connected to the Power BI dashboard | C6: Yes
A7: Other LE | B7: Non-Resource details connected to the Power BI dashboard | C7: Yes
A8: Tables | B8: Contains the columns connected to the dropdowns used in the following columns: 1. Workstream - All pages 2. Cost Type - Other LE 3. Rate Concat - Resource Static, Business & IT Manpower LE 4. Variance Reasons - Resource Static, Business & IT Manpower LE | C8: Yes
A12: Updating dropdowns example
A13: As shown in the image below: To find out the source of the dropdowns - Click on the cell > Click on Data > Click on Data Validation, this will navigate to the source column where any editing, addition, deletion needed in the dropdown should be done in the destinaion as shown in image 2 only then it will reflect in the column dropdown

Sheet $ Dashboard
C1: Category | D1: Program LE 2026 | E1: Program YTD Actual 2026 | G1: 46023 | I1: 46054 | K1: 46082 | M1: 46113 | O1: 46143 | Q1: 46174 | S1: 46204 | U1: 46235 | W1: 46266 | Y1: 46296 | AA1: 46327 | AC1: 46357
G2: Plan | H2: Actual | I2: Plan | J2: Actual | K2: Plan | L2: Actual | M2: Plan | N2: Actual | O2: Plan | P2: Actual | Q2: Plan | R2: Actual | S2: Plan | T2: Actual | U2: Plan | V2: Actual | W2: Plan | X2: Actual | Y2: Plan | Z2: Actual | AA2: Plan | AB2: Actual | AC2: Plan | AD2: Actual
C3: Business Resource | D3: =SUMIF($G$2:$AF$2,"Plan",G3:AF3) | E3: =SUMIF($G$2:$AF$2,"Actual",G3:AF3) | G3: =I48 | H3: =J48 | I3: =K48 | J3: =L48 | K3: =M48 | L3: =N48 | M3: =O48 | N3: =P48 | ... AD3: =AF48
C4: IT Resource | D4: =SUMIF($G$2:$AF$2,"Plan",G4:AF4) | E4: =SUMIF($G$2:$AF$2,"Actual",G4:AF4) | G4: =I30 | H4: =J30 | I4: =K30 | J4: =L30 | K4: =M30 | L4: =N30 | M4: =O30 | N4: =P30 | ... AD4: =AF30
C5: Resource Total | D5: =SUMIF($G$2:$AF$2,"Plan",G5:AF5) | E5: =SUMIF($G$2:$AF$2,"Actual",G5:AF5) | G5: =SUM(G3:G4) | H5: =SUM(H3:H4) | I5: =SUM(I3:I4) | J5: =SUM(J3:J4) | K5: =SUM(K3:K4) | L5: =SUM(L3:L4) | M5: =SUM(M3:M4) | N5: =SUM(N3:N4) | ... AD5: =SUM(AD3:AD4) | BO5: 10,95 - it | BP5: 5,87-business | BQ5: =10.95+5.87
C6: Non-Resource | D6: =SUMIF($G$2:$AF$2,"Plan",G6:AF6) | E6: =SUMIF($G$2:$AF$2,"Actual",G6:AF6)/1000000 | G6: =I77 | H6: =J77 | I6: =M77 | J6: =L77 | K6: =M77 | L6: =N77 | M6: =Q77 | N6: =P77 | O6: =Q77 | P6: =R77 | Q6: =U77 | R6: =T77 | S6: =U77 | T6: =V77 | U6: =Y77 | V6: =X77 | W6: =Y77 | X6: =Z77 | Y6: =AC77 | Z6: =AB77 | AA6: =AC77 | AB6: =AD77 | AC6: =AG77 | AD6: =AF77
C7: Total | D7: =D6+D5 | E7: =E6+E5 | G7: =SUM(G3:G6) | H7: =SUM(H3:H6) | I7: =SUM(I3:I6) | J7: =SUM(J3:J6) | K7: =SUM(K3:K6) | L7: =SUM(L3:L6) | M7: =SUM(M3:M6) | N7: =SUM(N3:N6) | ... AD7: =SUM(AD3:AD6)
D10: [2026 - 2027] | G10: [2026] | AH10: [2027]
B11: IT Resource cost by WS/PH | C11: Business/IT | D11: Program LE | E11: Program YTD Actual | G11: LE | H11: Actual | I11: 46023 | K11: 46054 | M11: 46082 | O11: 46113 | Q11: 46143 | S11: 46174 | U11: 46204 | W11: 46235 | Y11: 46266 | AA11: 46296 | AC11: 46327 | AE11: 46357 | AH11: LE | AI11: Actual | AJ11: 46388 | AL11: 46419 | AN11: 46447 | AP11: 46478 | AR11: 46508 | AT11: 46539 | AV11: 46569 | AX11: 46600 | AZ11: 46631 | BB11: 46661 | BD11: 46692 | BF11: 46722 | CD11: GIP | CE11: 46023 | CF11: 46054 | CG11: 46082 | CH11: 46113 | CI11: 46143 | CJ11: 46174 | CK11: 46204 | CL11: 46235 | CM11: 46266 | CN11: 46296 | CO11: 46327 | CP11: 46357 | CQ11: 46388 | CR11: 46419 | CS11: 46447 | CT11: 46478 | CU11: 46508 | CV11: 46539 | CW11: 46569 | CX11: 46600 | CY11: 46631 | CZ11: 46661 | DA11: 46692 | DB11: 46722
I12: Plan | J12: Actual | K12: Plan | L12: Actual | M12: Plan | N12: Actual | O12: Plan | P12: Actual | Q12: Plan | R12: Actual | S12: Plan | T12: Actual | U12: Plan | V12: Actual | W12: Plan | X12: Actual | Y12: Plan | Z12: Actual | AA12: Plan | AB12: Actual | AC12: Plan | AD12: Actual | AE12: Plan | AF12: Actual | AJ12: Plan | AK12: =IF(AJ11<=$B$5,"Actual","") | AL12: Plan | AM12: =IF(AL11<=$B$5,"Actual","") | AN12: Plan | AO12: =IF(AN11<=$B$5,"Actual","") | AP12: Plan | AQ12: =IF(AP11<=$B$5,"Actual","") | AR12: Plan | AS12: =IF(AR11<=$B$5,"Actual","") | AT12: Plan | AU12: =IF(AT11<=$B$5,"Actual","") | AV12: Plan | AW12: =IF(AV11<=$B$5,"Actual","") | AX12: Plan | AY12: =IF(AX11<=$B$5,"Actual","") | AZ12: Plan | BA12: =IF(AZ11<=$B$5,"Actual","") | BB12: Plan | BC12: =IF(BB11<=$B$5,"Actual","") | BD12: Plan | BE12: =IF(BD11<=$B$5,"Actual","") | BF12: Plan | BG12: =IF(BF11<=$B$5,"Actual","")
B13: Program Management | C13: IT | D13: =SUM(G13,AH13) | E13: =SUM(H13,AI13) | G13: =SUMIF($I$12:$AF$12,"Plan",I13:AF13)/1000000 | H13: =SUMIF($I$12:$AF$12,"Actual",I13:AF13)/1000000 | I13: =SUMIF(Table4[Workstream],'$ Dashboard'!B13,Table4[Jan_2026_F]) | J13: =SUMIF(Table4[Workstream],'$ Dashboard'!B13,Table4[Jan_2026_A]) | K13: =SUMIF(Table4[Workstream],'$ Dashboard'!B13,Table4[Feb_2026_F]) | L13: =SUMIF(Table4[Workstream],'$ Dashboard'!B13,Table4[Feb_2026_A]) | M13: =SUMIF(Table4[Workstream],'$ Dashboard'!B13,Table4[Mar_2026_F]) | N13: =SUMIF(Table4[Workstream],'$ Dashboard'!B13,Table4[Mar_2026_A]) | O13: =SUMIF(Table4[Workstream],'$ Dashboard'!B13,Table4[Apr_2026_F]) | P13: =SUMIF(Table4[Workstream],'$ Dashboard'!B13,Table4[Apr_2026_A]) | Q13: =SUMIF(Table4[Workstream],'$ Dashboard'!B13,Table4[May_2026_F]) | R13: =SUMIF(Table4[Workstream],'$ Dashboard'!B13,Table4[May_2026_A]) | S13: =SUMIF(Table4[Workstream],'$ Dashboard'!B13,Table4[Jun_2026_F]) | T13: =SUMIF(Table4[Workstream],'$ Dashboard'!B13,Table4[Jun_2026_A]) | U13: =SUMIF(Table4[Workstream],'$ Dashboard'!B13,Table4[Jul_2026_F]) | V13: =SUMIF(Table4[Workstream],'$ Dashboard'!B13,Table4[Jul_2026_A]) | W13: =SUMIF(Table4[Workstream],'$ Dashboard'!B13,Table4[Aug_2026_F]) | X13: =SUMIF(Table4[Workstream],'$ Dashboard'!B13,Table4[Aug_2026_A]) | Y13: =SUMIF(Table4[Workstream],'$ Dashboard'!B13,Table4[Sep_2026_F]) | Z13: =SUMIF(Table4[Workstream],'$ Dashboard'!B13,Table4[Sep_2026_A]) | AA13: =SUMIF(Table4[Workstream],'$ Dashboard'!B13,Table4[Oct_2026_F]) | AB13: =SUMIF(Table4[Workstream],'$ Dashboard'!B13,Table4[Oct_2026_A]) | AC13: =SUMIF(Table4[Workstream],'$ Dashboard'!B13,Table4[Nov_2026_F]) | AD13: =SUMIF(Table4[Workstream],'$ Dashboard'!B13,Table4[Nov_2026_A]) | AE13: =SUMIF(Table4[Workstream],'$ Dashboard'!B13,Table4[Dec_2026_F]) | AF13: =SUMIF(Table4[Workstream],'$ Dashboard'!B13,Table4[Dec_2026_A])+SUMIF(Table46[Workstream],'$ Dashboard'!B13,Table46[Dec_26_A]) | AH13: =SUM(AW13:BG13)/1000000 | AI13: =SUMIF($AJ$12:$BG$12,"Actual",AJ13:BG13)/1000000 | CD13: =SUM(CE13:DB13)/1000000
B14: Prosmar Crude | C14: IT | D14: =SUM(G14,AH14) | E14: =SUM(H14,AI14) | G14: =SUMIF($I$12:$AF$12,"Plan",I14:AF14)/1000000 | H14: =SUMIF($I$12:$AF$12,"Actual",I14:AF14)/1000000 | I14: =SUMIF(Table4[Workstream],'$ Dashboard'!B14,Table4[Jan_2026_F]) | J14: =SUMIF(Table4[Workstream],'$ Dashboard'!B14,Table4[Jan_2026_A]) | K14: =SUMIF(Table4[Workstream],'$ Dashboard'!B14,Table4[Feb_2026_F]) | L14: =SUMIF(Table4[Workstream],'$ Dashboard'!B14,Table4[Feb_2026_A]) | M14: =SUMIF(Table4[Workstream],'$ Dashboard'!B14,Table4[Mar_2026_F]) | N14: =SUMIF(Table4[Workstream],'$ Dashboard'!B14,Table4[Mar_2026_A]) | O14: =SUMIF(Table4[Workstream],'$ Dashboard'!B14,Table4[Apr_2026_F]) | P14: =SUMIF(Table4[Workstream],'$ Dashboard'!B14,Table4[Apr_2026_A]) | Q14: =SUMIF(Table4[Workstream],'$ Dashboard'!B14,Table4[May_2026_F]) | R14: =SUMIF(Table4[Workstream],'$ Dashboard'!B14,Table4[May_2026_A]) | S14: =SUMIF(Table4[Workstream],'$ Dashboard'!B14,Table4[Jun_2026_F]) | T14: =SUMIF(Table4[Workstream],'$ Dashboard'!B14,Table4[Jun_2026_A]) | U14: =SUMIF(Table4[Workstream],'$ Dashboard'!B14,Table4[Jul_2026_F]) | V14: =SUMIF(Table4[Workstream],'$ Dashboard'!B14,Table4[Jul_2026_A]) | W14: =SUMIF(Table4[Workstream],'$ Dashboard'!B14,Table4[Aug_2026_F]) | X14: =SUMIF(Table4[Workstream],'$ Dashboard'!B14,Table4[Aug_2026_A]) | Y14: =SUMIF(Table4[Workstream],'$ Dashboard'!B14,Table4[Sep_2026_F]) | Z14: =SUMIF(Table4[Workstream],'$ Dashboard'!B14,Table4[Sep_2026_A]) | AA14: =SUMIF(Table4[Workstream],'$ Dashboard'!B14,Table4[Oct_2026_F]) | AB14: =SUMIF(Table4[Workstream],'$ Dashboard'!B14,Table4[Oct_2026_A]) | AC14: =SUMIF(Table4[Workstream],'$ Dashboard'!B14,Table4[Nov_2026_F]) | AD14: =SUMIF(Table4[Workstream],'$ Dashboard'!B14,Table4[Nov_2026_A]) | AE14: =SUMIF(Table4[Workstream],'$ Dashboard'!B14,Table4[Dec_2026_F]) | AF14: =SUMIF(Table4[Workstream],'$ Dashboard'!B14,Table4[Dec_2026_A])+SUMIF(Table46[Workstream],'$ Dashboard'!B14,Table46[Dec_26_A]) | AH14: =SUM(AW14:BG14)/1000000 | AI14: =SUMIF($AJ$12:$BG$12,"Actual",AJ14:BG14)/1000000 | CD14: =SUM(CE14:DB14)/1000000
B15: Prosmar Products | C15: IT | D15: =SUM(G15,AH15) | E15: =SUM(H15,AI15) | G15: =SUMIF($I$12:$AF$12,"Plan",I15:AF15)/1000000 | H15: =SUMIF($I$12:$AF$12,"Actual",I15:AF15)/1000000 | I15: =SUMIF(Table4[Workstream],'$ Dashboard'!B15,Table4[Jan_2026_F]) | J15: =SUMIF(Table4[Workstream],'$ Dashboard'!B15,Table4[Jan_2026_A]) | K15: =SUMIF(Table4[Workstream],'$ Dashboard'!B15,Table4[Feb_2026_F]) | L15: =SUMIF(Table4[Workstream],'$ Dashboard'!B15,Table4[Feb_2026_A]) | M15: =SUMIF(Table4[Workstream],'$ Dashboard'!B15,Table4[Mar_2026_F]) | N15: =SUMIF(Table4[Workstream],'$ Dashboard'!B15,Table4[Mar_2026_A]) | O15: =SUMIF(Table4[Workstream],'$ Dashboard'!B15,Table4[Apr_2026_F]) | P15: =SUMIF(Table4[Workstream],'$ Dashboard'!B15,Table4[Apr_2026_A]) | Q15: =SUMIF(Table4[Workstream],'$ Dashboard'!B15,Table4[May_2026_F]) | R15: =SUMIF(Table4[Workstream],'$ Dashboard'!B15,Table4[May_2026_A]) | S15: =SUMIF(Table4[Workstream],'$ Dashboard'!B15,Table4[Jun_2026_F]) | T15: =SUMIF(Table4[Workstream],'$ Dashboard'!B15,Table4[Jun_2026_A]) | U15: =SUMIF(Table4[Workstream],'$ Dashboard'!B15,Table4[Jul_2026_F]) | V15: =SUMIF(Table4[Workstream],'$ Dashboard'!B15,Table4[Jul_2026_A]) | W15: =SUMIF(Table4[Workstream],'$ Dashboard'!B15,Table4[Aug_2026_F]) | X15: =SUMIF(Table4[Workstream],'$ Dashboard'!B15,Table4[Aug_2026_A]) | Y15: =SUMIF(Table4[Workstream],'$ Dashboard'!B15,Table4[Sep_2026_F]) | Z15: =SUMIF(Table4[Workstream],'$ Dashboard'!B15,Table4[Sep_2026_A]) | AA15: =SUMIF(Table4[Workstream],'$ Dashboard'!B15,Table4[Oct_2026_F]) | AB15: =SUMIF(Table4[Workstream],'$ Dashboard'!B15,Table4[Oct_2026_A]) | AC15: =SUMIF(Table4[Workstream],'$ Dashboard'!B15,Table4[Nov_2026_F]) | AD15: =SUMIF(Table4[Workstream],'$ Dashboard'!B15,Table4[Nov_2026_A]) | AE15: =SUMIF(Table4[Workstream],'$ Dashboard'!B15,Table4[Dec_2026_F]) | AF15: =SUMIF(Table4[Workstream],'$ Dashboard'!B15,Table4[Dec_2026_A])+SUMIF(Table46[Workstream],'$ Dashboard'!B15,Table46[Dec_26_A]) | AH15: =SUM(AW15:BG15)/1000000 | AI15: =SUMIF($AJ$12:$BG$12,"Actual",AJ15:BG15)/1000000 | CD15: =SUM(CE15:DB15)/1000000
B16: VPD | C16: IT | D16: =SUM(G16,AH16) | E16: =SUM(H16,AI16) | G16: =SUMIF($I$12:$AF$12,"Plan",I16:AF16)/1000000 | H16: =SUMIF($I$12:$AF$12,"Actual",I16:AF16)/1000000 | I16: =SUMIF(Table4[Workstream],'$ Dashboard'!B16,Table4[Jan_2026_F]) | J16: =SUMIF(Table4[Workstream],'$ Dashboard'!B16,Table4[Jan_2026_A]) | K16: =SUMIF(Table4[Workstream],'$ Dashboard'!B16,Table4[Feb_2026_F]) | L16: =SUMIF(Table4[Workstream],'$ Dashboard'!B16,Table4[Feb_2026_A]) | M16: =SUMIF(Table4[Workstream],'$ Dashboard'!B16,Table4[Mar_2026_F]) | N16: =SUMIF(Table4[Workstream],'$ Dashboard'!B16,Table4[Mar_2026_A]) | O16: =SUMIF(Table4[Workstream],'$ Dashboard'!B16,Table4[Apr_2026_F]) | P16: =SUMIF(Table4[Workstream],'$ Dashboard'!B16,Table4[Apr_2026_A]) | Q16: =SUMIF(Table4[Workstream],'$ Dashboard'!B16,Table4[May_2026_F]) | R16: =SUMIF(Table4[Workstream],'$ Dashboard'!B16,Table4[May_2026_A]) | S16: =SUMIF(Table4[Workstream],'$ Dashboard'!B16,Table4[Jun_2026_F]) | T16: =SUMIF(Table4[Workstream],'$ Dashboard'!B16,Table4[Jun_2026_A]) | U16: =SUMIF(Table4[Workstream],'$ Dashboard'!B16,Table4[Jul_2026_F]) | V16: =SUMIF(Table4[Workstream],'$ Dashboard'!B16,Table4[Jul_2026_A]) | W16: =SUMIF(Table4[Workstream],'$ Dashboard'!B16,Table4[Aug_2026_F]) | X16: =SUMIF(Table4[Workstream],'$ Dashboard'!B16,Table4[Aug_2026_A]) | Y16: =SUMIF(Table4[Workstream],'$ Dashboard'!B16,Table4[Sep_2026_F]) | Z16: =SUMIF(Table4[Workstream],'$ Dashboard'!B16,Table4[Sep_2026_A]) | AA16: =SUMIF(Table4[Workstream],'$ Dashboard'!B16,Table4[Oct_2026_F]) | AB16: =SUMIF(Table4[Workstream],'$ Dashboard'!B16,Table4[Oct_2026_A]) | AC16: =SUMIF(Table4[Workstream],'$ Dashboard'!B16,Table4[Nov_2026_F]) | AD16: =SUMIF(Table4[Workstream],'$ Dashboard'!B16,Table4[Nov_2026_A]) | AE16: =SUMIF(Table4[Workstream],'$ Dashboard'!B16,Table4[Dec_2026_F]) | AF16: =SUMIF(Table4[Workstream],'$ Dashboard'!B16,Table4[Dec_2026_A])+SUMIF(Table46[Workstream],'$ Dashboard'!B16,Table46[Dec_26_A]) | AH16: =SUM(AW16:BG16)/1000000 | AI16: =SUMIF($AJ$12:$BG$12,"Actual",AJ16:BG16)/1000000 | CD16: =SUM(CE16:DB16)/1000000
B17: GATOR | C17: IT | D17: =SUM(G17,AH17) | E17: =SUM(H17,AI17) | G17: =SUMIF($I$12:$AF$12,"Plan",I17:AF17)/1000000 | H17: =SUMIF($I$12:$AF$12,"Actual",I17:AF17)/1000000 | I17: =SUMIF(Table4[Workstream],'$ Dashboard'!B17,Table4[Jan_2026_F]) | J17: =SUMIF(Table4[Workstream],'$ Dashboard'!B17,Table4[Jan_2026_A]) | K17: =SUMIF(Table4[Workstream],'$ Dashboard'!B17,Table4[Feb_2026_F]) | L17: =SUMIF(Table4[Workstream],'$ Dashboard'!B17,Table4[Feb_2026_A]) | M17: =SUMIF(Table4[Workstream],'$ Dashboard'!B17,Table4[Mar_2026_F]) | N17: =SUMIF(Table4[Workstream],'$ Dashboard'!B17,Table4[Mar_2026_A]) | O17: =SUMIF(Table4[Workstream],'$ Dashboard'!B17,Table4[Apr_2026_F]) | P17: =SUMIF(Table4[Workstream],'$ Dashboard'!B17,Table4[Apr_2026_A]) | Q17: =SUMIF(Table4[Workstream],'$ Dashboard'!B17,Table4[May_2026_F]) | R17: =SUMIF(Table4[Workstream],'$ Dashboard'!B17,Table4[May_2026_A]) | S17: =SUMIF(Table4[Workstream],'$ Dashboard'!B17,Table4[Jun_2026_F]) | T17: =SUMIF(Table4[Workstream],'$ Dashboard'!B17,Table4[Jun_2026_A]) | U17: =SUMIF(Table4[Workstream],'$ Dashboard'!B17,Table4[Jul_2026_F]) | V17: =SUMIF(Table4[Workstream],'$ Dashboard'!B17,Table4[Jul_2026_A]) | W17: =SUMIF(Table4[Workstream],'$ Dashboard'!B17,Table4[Aug_2026_F]) | X17: =SUMIF(Table4[Workstream],'$ Dashboard'!B17,Table4[Aug_2026_A]) | Y17: =SUMIF(Table4[Workstream],'$ Dashboard'!B17,Table4[Sep_2026_F]) | Z17: =SUMIF(Table4[Workstream],'$ Dashboard'!B17,Table4[Sep_2026_A]) | AA17: =SUMIF(Table4[Workstream],'$ Dashboard'!B17,Table4[Oct_2026_F]) | AB17: =SUMIF(Table4[Workstream],'$ Dashboard'!B17,Table4[Oct_2026_A]) | AC17: =SUMIF(Table4[Workstream],'$ Dashboard'!B17,Table4[Nov_2026_F]) | AD17: =SUMIF(Table4[Workstream],'$ Dashboard'!B17,Table4[Nov_2026_A]) | AE17: =SUMIF(Table4[Workstream],'$ Dashboard'!B17,Table4[Dec_2026_F]) | AF17: =SUMIF(Table4[Workstream],'$ Dashboard'!B17,Table4[Dec_2026_A])+SUMIF(Table46[Workstream],'$ Dashboard'!B17,Table46[Dec_26_A]) | AH17: =SUM(AW17:BG17)/1000000 | AI17: =SUMIF($AJ$12:$BG$12,"Actual",AJ17:BG17)/1000000 | CD17: =SUM(CE17:DB17)/1000000
B18: USDF | C18: IT | D18: =SUM(G18,AH18) | E18: =SUM(H18,AI18) | G18: =SUMIF($I$12:$AF$12,"Plan",I18:AF18)/1000000 | H18: =SUMIF($I$12:$AF$12,"Actual",I18:AF18)/1000000 | I18: =SUMIF(Table4[Workstream],'$ Dashboard'!B18,Table4[Jan_2026_F]) | J18: =SUMIF(Table4[Workstream],'$ Dashboard'!B18,Table4[Jan_2026_A]) | K18: =SUMIF(Table4[Workstream],'$ Dashboard'!B18,Table4[Feb_2026_F]) | L18: =SUMIF(Table4[Workstream],'$ Dashboard'!B18,Table4[Feb_2026_A]) | M18: =SUMIF(Table4[Workstream],'$ Dashboard'!B18,Table4[Mar_2026_F]) | N18: =SUMIF(Table4[Workstream],'$ Dashboard'!B18,Table4[Mar_2026_A]) | O18: =SUMIF(Table4[Workstream],'$ Dashboard'!B18,Table4[Apr_2026_F]) | P18: =SUMIF(Table4[Workstream],'$ Dashboard'!B18,Table4[Apr_2026_A]) | Q18: =SUMIF(Table4[Workstream],'$ Dashboard'!B18,Table4[May_2026_F]) | R18: =SUMIF(Table4[Workstream],'$ Dashboard'!B18,Table4[May_2026_A]) | S18: =SUMIF(Table4[Workstream],'$ Dashboard'!B18,Table4[Jun_2026_F]) | T18: =SUMIF(Table4[Workstream],'$ Dashboard'!B18,Table4[Jun_2026_A]) | U18: =SUMIF(Table4[Workstream],'$ Dashboard'!B18,Table4[Jul_2026_F]) | V18: =SUMIF(Table4[Workstream],'$ Dashboard'!B18,Table4[Jul_2026_A]) | W18: =SUMIF(Table4[Workstream],'$ Dashboard'!B18,Table4[Aug_2026_F]) | X18: =SUMIF(Table4[Workstream],'$ Dashboard'!B18,Table4[Aug_2026_A]) | Y18: =SUMIF(Table4[Workstream],'$ Dashboard'!B18,Table4[Sep_2026_F]) | Z18: =SUMIF(Table4[Workstream],'$ Dashboard'!B18,Table4[Sep_2026_A]) | AA18: =SUMIF(Table4[Workstream],'$ Dashboard'!B18,Table4[Oct_2026_F]) | AB18: =SUMIF(Table4[Workstream],'$ Dashboard'!B18,Table4[Oct_2026_A]) | AC18: =SUMIF(Table4[Workstream],'$ Dashboard'!B18,Table4[Nov_2026_F]) | AD18: =SUMIF(Table4[Workstream],'$ Dashboard'!B18,Table4[Nov_2026_A]) | AE18: =SUMIF(Table4[Workstream],'$ Dashboard'!B18,Table4[Dec_2026_F]) | AF18: =SUMIF(Table4[Workstream],'$ Dashboard'!B18,Table4[Dec_2026_A])+SUMIF(Table46[Workstream],'$ Dashboard'!B18,Table46[Dec_26_A]) | AH18: =SUM(AW18:BG18)/1000000 | AI18: =SUMIF($AJ$12:$BG$12,"Actual",AJ18:BG18)/1000000 | CD18: =SUM(CE18:DB18)/1000000
B19: JIGSAW & PDS Process work | C19: IT | D19: =SUM(G19,AH19) | E19: =SUM(H19,AI19) | G19: =SUMIF($I$12:$AF$12,"Plan",I19:AF19)/1000000 | H19: =SUMIF($I$12:$AF$12,"Actual",I19:AF19)/1000000 | I19: =SUMIF(Table4[Workstream],'$ Dashboard'!B19,Table4[Jan_2026_F]) | J19: =SUMIF(Table4[Workstream],'$ Dashboard'!B19,Table4[Jan_2026_A]) | K19: =SUMIF(Table4[Workstream],'$ Dashboard'!B19,Table4[Feb_2026_F]) | L19: =SUMIF(Table4[Workstream],'$ Dashboard'!B19,Table4[Feb_2026_A]) | M19: =SUMIF(Table4[Workstream],'$ Dashboard'!B19,Table4[Mar_2026_F]) | N19: =SUMIF(Table4[Workstream],'$ Dashboard'!B19,Table4[Mar_2026_A]) | O19: =SUMIF(Table4[Workstream],'$ Dashboard'!B19,Table4[Apr_2026_F]) | P19: =SUMIF(Table4[Workstream],'$ Dashboard'!B19,Table4[Apr_2026_A]) | Q19: =SUMIF(Table4[Workstream],'$ Dashboard'!B19,Table4[May_2026_F]) | R19: =SUMIF(Table4[Workstream],'$ Dashboard'!B19,Table4[May_2026_A]) | S19: =SUMIF(Table4[Workstream],'$ Dashboard'!B19,Table4[Jun_2026_F]) | T19: =SUMIF(Table4[Workstream],'$ Dashboard'!B19,Table4[Jun_2026_A]) | U19: =SUMIF(Table4[Workstream],'$ Dashboard'!B19,Table4[Jul_2026_F]) | V19: =SUMIF(Table4[Workstream],'$ Dashboard'!B19,Table4[Jul_2026_A]) | W19: =SUMIF(Table4[Workstream],'$ Dashboard'!B19,Table4[Aug_2026_F]) | X19: =SUMIF(Table4[Workstream],'$ Dashboard'!B19,Table4[Aug_2026_A]) | Y19: =SUMIF(Table4[Workstream],'$ Dashboard'!B19,Table4[Sep_2026_F]) | Z19: =SUMIF(Table4[Workstream],'$ Dashboard'!B19,Table4[Sep_2026_A]) | AA19: =SUMIF(Table4[Workstream],'$ Dashboard'!B19,Table4[Oct_2026_F]) | AB19: =SUMIF(Table4[Workstream],'$ Dashboard'!B19,Table4[Oct_2026_A]) | AC19: =SUMIF(Table4[Workstream],'$ Dashboard'!B19,Table4[Nov_2026_F]) | AD19: =SUMIF(Table4[Workstream],'$ Dashboard'!B19,Table4[Nov_2026_A]) | AE19: =SUMIF(Table4[Workstream],'$ Dashboard'!B19,Table4[Dec_2026_F]) | AF19: =SUMIF(Table4[Workstream],'$ Dashboard'!B19,Table4[Dec_2026_A])+SUMIF(Table46[Workstream],'$ Dashboard'!B19,Table46[Dec_26_A]) | AH19: =SUM(AW19:BG19)/1000000 | AI19: =SUMIF($AJ$12:$BG$12,"Actual",AJ19:BG19)/1000000 | CD19: =SUM(CE19:DB19)/1000000
B20: DA Desk | C20: IT | D20: =SUM(G20,AH20) | E20: =SUM(H20,AI20) | G20: =SUMIF($I$12:$AF$12,"Plan",I20:AF20)/1000000 | H20: =SUMIF($I$12:$AF$12,"Actual",I20:AF20)/1000000 | I20: =SUMIF(Table4[Workstream],'$ Dashboard'!B20,Table4[Jan_2026_F]) | J20: =SUMIF(Table4[Workstream],'$ Dashboard'!B20,Table4[Jan_2026_A]) | K20: =SUMIF(Table4[Workstream],'$ Dashboard'!B20,Table4[Feb_2026_F]) | L20: =SUMIF(Table4[Workstream],'$ Dashboard'!B20,Table4[Feb_2026_A]) | M20: =SUMIF(Table4[Workstream],'$ Dashboard'!B20,Table4[Mar_2026_F]) | N20: =SUMIF(Table4[Workstream],'$ Dashboard'!B20,Table4[Mar_2026_A]) | O20: =SUMIF(Table4[Workstream],'$ Dashboard'!B20,Table4[Apr_2026_F]) | P20: =SUMIF(Table4[Workstream],'$ Dashboard'!B20,Table4[Apr_2026_A]) | Q20: =SUMIF(Table4[Workstream],'$ Dashboard'!B20,Table4[May_2026_F]) | R20: =SUMIF(Table4[Workstream],'$ Dashboard'!B20,Table4[May_2026_A]) | S20: =SUMIF(Table4[Workstream],'$ Dashboard'!B20,Table4[Jun_2026_F]) | T20: =SUMIF(Table4[Workstream],'$ Dashboard'!B20,Table4[Jun_2026_A]) | U20: =SUMIF(Table4[Workstream],'$ Dashboard'!B20,Table4[Jul_2026_F]) | V20: =SUMIF(Table4[Workstream],'$ Dashboard'!B20,Table4[Jul_2026_A]) | W20: =SUMIF(Table4[Workstream],'$ Dashboard'!B20,Table4[Aug_2026_F]) | X20: =SUMIF(Table4[Workstream],'$ Dashboard'!B20,Table4[Aug_2026_A]) | Y20: =SUMIF(Table4[Workstream],'$ Dashboard'!B20,Table4[Sep_2026_F]) | Z20: =SUMIF(Table4[Workstream],'$ Dashboard'!B20,Table4[Sep_2026_A]) | AA20: =SUMIF(Table4[Workstream],'$ Dashboard'!B20,Table4[Oct_2026_F]) | AB20: =SUMIF(Table4[Workstream],'$ Dashboard'!B20,Table4[Oct_2026_A]) | AC20: =SUMIF(Table4[Workstream],'$ Dashboard'!B20,Table4[Nov_2026_F]) | AD20: =SUMIF(Table4[Workstream],'$ Dashboard'!B20,Table4[Nov_2026_A]) | AE20: =SUMIF(Table4[Workstream],'$ Dashboard'!B20,Table4[Dec_2026_F]) | AF20: =SUMIF(Table4[Workstream],'$ Dashboard'!B20,Table4[Dec_2026_A])+SUMIF(Table46[Workstream],'$ Dashboard'!B20,Table46[Dec_26_A]) | AH20: =SUM(AW20:BG20)/1000000 | AI20: =SUMIF($AJ$12:$BG$12,"Actual",AJ20:BG20)/1000000 | CD20: =SUM(CE20:DB20)/1000000
B21: IDT | C21: IT | D21: =SUM(G21,AH21) | E21: =SUM(H21,AI21) | G21: =SUMIF($I$12:$AF$12,"Plan",I21:AF21)/1000000 | H21: =SUMIF($I$12:$AF$12,"Actual",I21:AF21)/1000000 | I21: =SUMIF(Table4[Workstream],'$ Dashboard'!B21,Table4[Jan_2026_F]) | J21: =SUMIF(Table4[Workstream],'$ Dashboard'!B21,Table4[Jan_2026_A]) | K21: =SUMIF(Table4[Workstream],'$ Dashboard'!B21,Table4[Feb_2026_F]) | L21: =SUMIF(Table4[Workstream],'$ Dashboard'!B21,Table4[Feb_2026_A]) | M21: =SUMIF(Table4[Workstream],'$ Dashboard'!B21,Table4[Mar_2026_F]) | N21: =SUMIF(Table4[Workstream],'$ Dashboard'!B21,Table4[Mar_2026_A]) | O21: =SUMIF(Table4[Workstream],'$ Dashboard'!B21,Table4[Apr_2026_F]) | P21: =SUMIF(Table4[Workstream],'$ Dashboard'!B21,Table4[Apr_2026_A]) | Q21: =SUMIF(Table4[Workstream],'$ Dashboard'!B21,Table4[May_2026_F]) | R21: =SUMIF(Table4[Workstream],'$ Dashboard'!B21,Table4[May_2026_A]) | S21: =SUMIF(Table4[Workstream],'$ Dashboard'!B21,Table4[Jun_2026_F]) | T21: =SUMIF(Table4[Workstream],'$ Dashboard'!B21,Table4[Jun_2026_A]) | U21: =SUMIF(Table4[Workstream],'$ Dashboard'!B21,Table4[Jul_2026_F]) | V21: =SUMIF(Table4[Workstream],'$ Dashboard'!B21,Table4[Jul_2026_A]) | W21: =SUMIF(Table4[Workstream],'$ Dashboard'!B21,Table4[Aug_2026_F]) | X21: =SUMIF(Table4[Workstream],'$ Dashboard'!B21,Table4[Aug_2026_A]) | Y21: =SUMIF(Table4[Workstream],'$ Dashboard'!B21,Table4[Sep_2026_F]) | Z21: =SUMIF(Table4[Workstream],'$ Dashboard'!B21,Table4[Sep_2026_A]) | AA21: =SUMIF(Table4[Workstream],'$ Dashboard'!B21,Table4[Oct_2026_F]) | AB21: =SUMIF(Table4[Workstream],'$ Dashboard'!B21,Table4[Oct_2026_A]) | AC21: =SUMIF(Table4[Workstream],'$ Dashboard'!B21,Table4[Nov_2026_F]) | AD21: =SUMIF(Table4[Workstream],'$ Dashboard'!B21,Table4[Nov_2026_A]) | AE21: =SUMIF(Table4[Workstream],'$ Dashboard'!B21,Table4[Dec_2026_F]) | AF21: =SUMIF(Table4[Workstream],'$ Dashboard'!B21,Table4[Dec_2026_A])+SUMIF(Table46[Workstream],'$ Dashboard'!B21,Table46[Dec_26_A]) | AH21: =SUM(AW21:BG21)/1000000 | AI21: =SUMIF($AJ$12:$BG$12,"Actual",AJ21:BG21)/1000000 | CD21: =SUM(CE21:DB21)/1000000
D22: =SUM(G22,AH22) | E22: =SUM(H22,AI22) | G22: =SUMIF($I$12:$AF$12,"Plan",I22:AF22)/1000000 | H22: =SUMIF($I$12:$AF$12,"Actual",I22:AF22)/1000000 | I22: =SUMIF(Table4[Workstream],'$ Dashboard'!B22,Table4[Jan_2026_F]) | J22: =SUMIF(Table4[Workstream],'$ Dashboard'!B22,Table4[Jan_2026_A]) | K22: =SUMIF(Table4[Workstream],'$ Dashboard'!B22,Table4[Feb_2026_F]) | L22: =SUMIF(Table4[Workstream],'$ Dashboard'!B22,Table4[Feb_2026_A]) | M22: =SUMIF(Table4[Workstream],'$ Dashboard'!B22,Table4[Mar_2026_F]) | N22: =SUMIF(Table4[Workstream],'$ Dashboard'!B22,Table4[Mar_2026_A]) | O22: =SUMIF(Table4[Workstream],'$ Dashboard'!B22,Table4[Apr_2026_F]) | P22: =SUMIF(Table4[Workstream],'$ Dashboard'!B22,Table4[Apr_2026_A]) | Q22: =SUMIF(Table4[Workstream],'$ Dashboard'!B22,Table4[May_2026_F]) | R22: =SUMIF(Table4[Workstream],'$ Dashboard'!B22,Table4[May_2026_A]) | S22: =SUMIF(Table4[Workstream],'$ Dashboard'!B22,Table4[Jun_2026_F]) | T22: =SUMIF(Table4[Workstream],'$ Dashboard'!B22,Table4[Jun_2026_A]) | U22: =SUMIF(Table4[Workstream],'$ Dashboard'!B22,Table4[Jul_2026_F]) | V22: =SUMIF(Table4[Workstream],'$ Dashboard'!B22,Table4[Jul_2026_A]) | W22: =SUMIF(Table4[Workstream],'$ Dashboard'!B22,Table4[Aug_2026_F]) | X22: =SUMIF(Table4[Workstream],'$ Dashboard'!B22,Table4[Aug_2026_A]) | Y22: =SUMIF(Table4[Workstream],'$ Dashboard'!B22,Table4[Sep_2026_F]) | Z22: =SUMIF(Table4[Workstream],'$ Dashboard'!B22,Table4[Sep_2026_A]) | AA22: =SUMIF(Table4[Workstream],'$ Dashboard'!B22,Table4[Oct_2026_F]) | AB22: =SUMIF(Table4[Workstream],'$ Dashboard'!B22,Table4[Oct_2026_A]) | AC22: =SUMIF(Table4[Workstream],'$ Dashboard'!B22,Table4[Nov_2026_F]) | AD22: =SUMIF(Table4[Workstream],'$ Dashboard'!B22,Table4[Nov_2026_A]) | AE22: =SUMIF(Table4[Workstream],'$ Dashboard'!B22,Table4[Dec_2026_F]) | AF22: =SUMIF(Table4[Workstream],'$ Dashboard'!B22,Table4[Dec_2026_A])+SUMIF(Table46[Workstream],'$ Dashboard'!B22,Table46[Dec_26_A]) | AH22: =SUM(AW22:BG22)/1000000 | AI22: =SUMIF($AJ$12:$BG$12,"Actual",AJ22:BG22)/1000000 | CD22: =SUM(CE22:DB22)/1000000
D23: =SUM(G23,AH23) | E23: =SUM(H23,AI23) | G23: =SUMIF($I$12:$AF$12,"Plan",I23:AF23)/1000000 | H23: =SUMIF($I$12:$AF$12,"Actual",I23:AF23)/1000000 | I23: =SUMIF(Table410[Workstream],'$ Dashboard'!B23,Table410[Jan_2026_F]) | J23: =SUMIF(Table410[Workstream],'$ Dashboard'!B23,Table410[Jan_2026_A]) | K23: =SUMIF(Table410[Workstream],'$ Dashboard'!B23,Table410[Feb_2026_F]) | L23: =SUMIF(Table410[Workstream],'$ Dashboard'!B23,Table410[Feb_2026_A]) | M23: =SUMIF(Table410[Workstream],'$ Dashboard'!B23,Table410[Mar_2026_F]) | N23: =SUMIF(Table410[Workstream],'$ Dashboard'!B23,Table410[Mar_2026_A]) | O23: =SUMIF(Table410[Workstream],'$ Dashboard'!B23,Table410[Apr_2026_F]) | P23: =SUMIF(Table410[Workstream],'$ Dashboard'!B23,Table410[Apr_2026_A]) | Q23: =SUMIF(Table410[Workstream],'$ Dashboard'!B23,Table410[May_2026_F]) | R23: =SUMIF(Table410[Workstream],'$ Dashboard'!B23,Table410[May_2026_A]) | S23: =SUMIF(Table410[Workstream],'$ Dashboard'!B23,Table410[Jun_2026_F]) | T23: =SUMIF(Table410[Workstream],'$ Dashboard'!B23,Table410[Jun_2026_A]) | U23: =SUMIF(Table410[Workstream],'$ Dashboard'!B23,Table410[Jul_2026_F]) | V23: =SUMIF(Table410[Workstream],'$ Dashboard'!B23,Table410[Jul_2026_A]) | W23: =SUMIF(Table410[Workstream],'$ Dashboard'!B23,Table410[Aug_2026_F]) | X23: =SUMIF(Table410[Workstream],'$ Dashboard'!B23,Table410[Aug_2026_A]) | Y23: =SUMIF(Table410[Workstream],'$ Dashboard'!B23,Table410[Sep_2026_F]) | Z23: =SUMIF(Table410[Workstream],'$ Dashboard'!B23,Table410[Sep_2026_A]) | AA23: =SUMIF(Table410[Workstream],'$ Dashboard'!B23,Table410[Oct_2026_F]) | AB23: =SUMIF(Table410[Workstream],'$ Dashboard'!B23,Table410[Oct_2026_A]) | AC23: =SUMIF(Table410[Workstream],'$ Dashboard'!B23,Table410[Nov_2026_F]) | AD23: =SUMIF(Table410[Workstream],'$ Dashboard'!B23,Table410[Nov_2026_A]) | AE23: =SUMIF(Table410[Workstream],'$ Dashboard'!B23,Table410[Dec_2026_F]) | AF23: =SUMIF(Table410[Workstream],'$ Dashboard'!B23,Table410[Dec_2026_A])+SUMIF(Table46[Workstream],'$ Dashboard'!B23,Table46[Dec_26_A]) | AH23: =SUM(AW23:BG23)/1000000 | AI23: =SUMIF($AJ$12:$BG$12,"Actual",AJ23:BG23)/1000000 | CD23: =SUM(CE23:DB23)/1000000
D24: =SUM(G24,AH24) | E24: =SUM(H24,AI24) | G24: =SUMIF($I$12:$AF$12,"Plan",I24:AF24)/1000000 | H24: =SUMIF($I$12:$AF$12,"Actual",I24:AF24)/1000000 | I24: =SUMIF(Table410[Workstream],'$ Dashboard'!B24,Table410[Jan_2026_F]) | J24: =SUMIF(Table410[Workstream],'$ Dashboard'!B24,Table410[Jan_2026_A]) | K24: =SUMIF(Table410[Workstream],'$ Dashboard'!B24,Table410[Feb_2026_F]) | L24: =SUMIF(Table410[Workstream],'$ Dashboard'!B24,Table410[Feb_2026_A]) | M24: =SUMIF(Table410[Workstream],'$ Dashboard'!B24,Table410[Mar_2026_F]) | N24: =SUMIF(Table410[Workstream],'$ Dashboard'!B24,Table410[Mar_2026_A]) | O24: =SUMIF(Table410[Workstream],'$ Dashboard'!B24,Table410[Apr_2026_F]) | P24: =SUMIF(Table410[Workstream],'$ Dashboard'!B24,Table410[Apr_2026_A]) | Q24: =SUMIF(Table410[Workstream],'$ Dashboard'!B24,Table410[May_2026_F]) | R24: =SUMIF(Table410[Workstream],'$ Dashboard'!B24,Table410[May_2026_A]) | S24: =SUMIF(Table410[Workstream],'$ Dashboard'!B24,Table410[Jun_2026_F]) | T24: =SUMIF(Table410[Workstream],'$ Dashboard'!B24,Table410[Jun_2026_A]) | U24: =SUMIF(Table410[Workstream],'$ Dashboard'!B24,Table410[Jul_2026_F]) | V24: =SUMIF(Table410[Workstream],'$ Dashboard'!B24,Table410[Jul_2026_A]) | W24: =SUMIF(Table410[Workstream],'$ Dashboard'!B24,Table410[Aug_2026_F]) | X24: =SUMIF(Table410[Workstream],'$ Dashboard'!B24,Table410[Aug_2026_A]) | Y24: =SUMIF(Table410[Workstream],'$ Dashboard'!B24,Table410[Sep_2026_F]) | Z24: =SUMIF(Table410[Workstream],'$ Dashboard'!B24,Table410[Sep_2026_A]) | AA24: =SUMIF(Table410[Workstream],'$ Dashboard'!B24,Table410[Oct_2026_F]) | AB24: =SUMIF(Table410[Workstream],'$ Dashboard'!B24,Table410[Oct_2026_A]) | AC24: =SUMIF(Table410[Workstream],'$ Dashboard'!B24,Table410[Nov_2026_F]) | AD24: =SUMIF(Table410[Workstream],'$ Dashboard'!B24,Table410[Nov_2026_A]) | AE24: =SUMIF(Table410[Workstream],'$ Dashboard'!B24,Table410[Dec_2026_F]) | AF24: =SUMIF(Table410[Workstream],'$ Dashboard'!B24,Table410[Dec_2026_A])+SUMIF(Table46[Workstream],'$ Dashboard'!B24,Table46[Dec_26_A]) | AH24: =SUM(AW24:BG24)/1000000 | AI24: =SUMIF($AJ$12:$BG$12,"Actual",AJ24:BG24)/1000000
D25: =SUM(G25,AH25) | E25: =SUM(H25,AI25) | G25: =SUMIF($I$12:$AF$12,"Plan",I25:AF25)/1000000 | H25: =SUMIF($I$12:$AF$12,"Actual",I25:AF25)/1000000 | I25: =SUMIF(Table410[Workstream],'$ Dashboard'!B25,Table410[Jan_2026_F]) | J25: =SUMIF(Table410[Workstream],'$ Dashboard'!B25,Table410[Jan_2026_A]) | K25: =SUMIF(Table410[Workstream],'$ Dashboard'!B25,Table410[Feb_2026_F]) | L25: =SUMIF(Table410[Workstream],'$ Dashboard'!B25,Table410[Feb_2026_A]) | M25: =SUMIF(Table410[Workstream],'$ Dashboard'!B25,Table410[Mar_2026_F]) | N25: =SUMIF(Table410[Workstream],'$ Dashboard'!B25,Table410[Mar_2026_A]) | O25: =SUMIF(Table410[Workstream],'$ Dashboard'!B25,Table410[Apr_2026_F]) | P25: =SUMIF(Table410[Workstream],'$ Dashboard'!B25,Table410[Apr_2026_A]) | Q25: =SUMIF(Table410[Workstream],'$ Dashboard'!B25,Table410[May_2026_F]) | R25: =SUMIF(Table410[Workstream],'$ Dashboard'!B25,Table410[May_2026_A]) | S25: =SUMIF(Table410[Workstream],'$ Dashboard'!B25,Table410[Jun_2026_F]) | T25: =SUMIF(Table410[Workstream],'$ Dashboard'!B25,Table410[Jun_2026_A]) | U25: =SUMIF(Table410[Workstream],'$ Dashboard'!B25,Table410[Jul_2026_F]) | V25: =SUMIF(Table410[Workstream],'$ Dashboard'!B25,Table410[Jul_2026_A]) | W25: =SUMIF(Table410[Workstream],'$ Dashboard'!B25,Table410[Aug_2026_F]) | X25: =SUMIF(Table410[Workstream],'$ Dashboard'!B25,Table410[Aug_2026_A]) | Y25: =SUMIF(Table410[Workstream],'$ Dashboard'!B25,Table410[Sep_2026_F]) | Z25: =SUMIF(Table410[Workstream],'$ Dashboard'!B25,Table410[Sep_2026_A]) | AA25: =SUMIF(Table410[Workstream],'$ Dashboard'!B25,Table410[Oct_2026_F]) | AB25: =SUMIF(Table410[Workstream],'$ Dashboard'!B25,Table410[Oct_2026_A]) | AC25: =SUMIF(Table410[Workstream],'$ Dashboard'!B25,Table410[Nov_2026_F]) | AD25: =SUMIF(Table410[Workstream],'$ Dashboard'!B25,Table410[Nov_2026_A]) | AE25: =SUMIF(Table410[Workstream],'$ Dashboard'!B25,Table410[Dec_2026_F]) | AF25: =SUMIF(Table410[Workstream],'$ Dashboard'!B25,Table410[Dec_2026_A])+SUMIF(Table46[Workstream],'$ Dashboard'!B25,Table46[Dec_26_A]) | AH25: =SUM(AW25:BG25)/1000000 | AI25: =SUMIF($AJ$12:$BG$12,"Actual",AJ25:BG25)/1000000
D26: =SUM(G26,AH26) | E26: =SUM(H26,AI26) | G26: =SUMIF($I$12:$AF$12,"Plan",I26:AF26)/1000000 | H26: =SUMIF($I$12:$AF$12,"Actual",I26:AF26)/1000000 | I26: =SUMIF(Table410[Workstream],'$ Dashboard'!B26,Table410[Jan_2026_F]) | J26: =SUMIF(Table410[Workstream],'$ Dashboard'!B26,Table410[Jan_2026_A]) | K26: =SUMIF(Table410[Workstream],'$ Dashboard'!B26,Table410[Feb_2026_F]) | L26: =SUMIF(Table410[Workstream],'$ Dashboard'!B26,Table410[Feb_2026_A]) | M26: =SUMIF(Table410[Workstream],'$ Dashboard'!B26,Table410[Mar_2026_F]) | N26: =SUMIF(Table410[Workstream],'$ Dashboard'!B26,Table410[Mar_2026_A]) | O26: =SUMIF(Table410[Workstream],'$ Dashboard'!B26,Table410[Apr_2026_F]) | P26: =SUMIF(Table410[Workstream],'$ Dashboard'!B26,Table410[Apr_2026_A]) | Q26: =SUMIF(Table410[Workstream],'$ Dashboard'!B26,Table410[May_2026_F]) | R26: =SUMIF(Table410[Workstream],'$ Dashboard'!B26,Table410[May_2026_A]) | S26: =SUMIF(Table410[Workstream],'$ Dashboard'!B26,Table410[Jun_2026_F]) | T26: =SUMIF(Table410[Workstream],'$ Dashboard'!B26,Table410[Jun_2026_A]) | U26: =SUMIF(Table410[Workstream],'$ Dashboard'!B26,Table410[Jul_2026_F]) | V26: =SUMIF(Table410[Workstream],'$ Dashboard'!B26,Table410[Jul_2026_A]) | W26: =SUMIF(Table410[Workstream],'$ Dashboard'!B26,Table410[Aug_2026_F]) | X26: =SUMIF(Table410[Workstream],'$ Dashboard'!B26,Table410[Aug_2026_A]) | Y26: =SUMIF(Table410[Workstream],'$ Dashboard'!B26,Table410[Sep_2026_F]) | Z26: =SUMIF(Table410[Workstream],'$ Dashboard'!B26,Table410[Sep_2026_A]) | AA26: =SUMIF(Table410[Workstream],'$ Dashboard'!B26,Table410[Oct_2026_F]) | AB26: =SUMIF(Table410[Workstream],'$ Dashboard'!B26,Table410[Oct_2026_A]) | AC26: =SUMIF(Table410[Workstream],'$ Dashboard'!B26,Table410[Nov_2026_F]) | AD26: =SUMIF(Table410[Workstream],'$ Dashboard'!B26,Table410[Nov_2026_A]) | AE26: =SUMIF(Table410[Workstream],'$ Dashboard'!B26,Table410[Dec_2026_F]) | AF26: =SUMIF(Table410[Workstream],'$ Dashboard'!B26,Table410[Dec_2026_A])+SUMIF(Table46[Workstream],'$ Dashboard'!B26,Table46[Dec_26_A]) | AH26: =SUM(AW26:BG26)/1000000 | AI26: =SUMIF($AJ$12:$BG$12,"Actual",AJ26:BG26)/1000000 | CD26: =SUM(CE26:DB26)/1000000
D27: =SUM(G27,AH27) | E27: =SUM(H27,AI27) | G27: =SUMIF($I$12:$AF$12,"Plan",I27:AF27)/1000000 | H27: =SUMIF($I$12:$AF$12,"Actual",I27:AF27)/1000000 | I27: =SUMIF(Table410[Workstream],'$ Dashboard'!B27,Table410[Jan_2026_F]) | J27: =SUMIF(Table410[Workstream],'$ Dashboard'!B27,Table410[Jan_2026_A]) | K27: =SUMIF(Table410[Workstream],'$ Dashboard'!B27,Table410[Feb_2026_F]) | L27: =SUMIF(Table410[Workstream],'$ Dashboard'!B27,Table410[Feb_2026_A]) | M27: =SUMIF(Table410[Workstream],'$ Dashboard'!B27,Table410[Mar_2026_F]) | N27: =SUMIF(Table410[Workstream],'$ Dashboard'!B27,Table410[Mar_2026_A]) | O27: =SUMIF(Table410[Workstream],'$ Dashboard'!B27,Table410[Apr_2026_F]) | P27: =SUMIF(Table410[Workstream],'$ Dashboard'!B27,Table410[Apr_2026_A]) | Q27: =SUMIF(Table410[Workstream],'$ Dashboard'!B27,Table410[May_2026_F]) | R27: =SUMIF(Table410[Workstream],'$ Dashboard'!B27,Table410[May_2026_A]) | S27: =SUMIF(Table410[Workstream],'$ Dashboard'!B27,Table410[Jun_2026_F]) | T27: =SUMIF(Table410[Workstream],'$ Dashboard'!B27,Table410[Jun_2026_A]) | U27: =SUMIF(Table410[Workstream],'$ Dashboard'!B27,Table410[Jul_2026_F]) | V27: =SUMIF(Table410[Workstream],'$ Dashboard'!B27,Table410[Jul_2026_A]) | W27: =SUMIF(Table410[Workstream],'$ Dashboard'!B27,Table410[Aug_2026_F]) | X27: =SUMIF(Table410[Workstream],'$ Dashboard'!B27,Table410[Aug_2026_A]) | Y27: =SUMIF(Table410[Workstream],'$ Dashboard'!B27,Table410[Sep_2026_F]) | Z27: =SUMIF(Table410[Workstream],'$ Dashboard'!B27,Table410[Sep_2026_A]) | AA27: =SUMIF(Table410[Workstream],'$ Dashboard'!B27,Table410[Oct_2026_F]) | AB27: =SUMIF(Table410[Workstream],'$ Dashboard'!B27,Table410[Oct_2026_A]) | AC27: =SUMIF(Table410[Workstream],'$ Dashboard'!B27,Table410[Nov_2026_F]) | AD27: =SUMIF(Table410[Workstream],'$ Dashboard'!B27,Table410[Nov_2026_A]) | AE27: =SUMIF(Table410[Workstream],'$ Dashboard'!B27,Table410[Dec_2026_F]) | AF27: =SUMIF(Table410[Workstream],'$ Dashboard'!B27,Table410[Dec_2026_A])+SUMIF(Table46[Workstream],'$ Dashboard'!B27,Table46[Dec_26_A]) | AH27: =SUM(AW27:BG27)/1000000 | AI27: =SUMIF($AJ$12:$BG$12,"Actual",AJ27:BG27)/1000000 | CD27: =SUM(CE27:DB27)/1000000
D28: =SUM(G28,AH28) | E28: =SUM(H28,AI28) | G28: =SUMIF($I$12:$AF$12,"Plan",I28:AF28)/1000000 | H28: =SUMIF($I$12:$AF$12,"Actual",I28:AF28)/1000000 | I28: =SUMIF(Table410[Workstream],'$ Dashboard'!B28,Table410[Jan_2026_F]) | J28: =SUMIF(Table410[Workstream],'$ Dashboard'!B28,Table410[Jan_2026_A]) | K28: =SUMIF(Table410[Workstream],'$ Dashboard'!B28,Table410[Feb_2026_F]) | L28: =SUMIF(Table410[Workstream],'$ Dashboard'!B28,Table410[Feb_2026_A]) | M28: =SUMIF(Table410[Workstream],'$ Dashboard'!B28,Table410[Mar_2026_F]) | N28: =SUMIF(Table410[Workstream],'$ Dashboard'!B28,Table410[Mar_2026_A]) | O28: =SUMIF(Table410[Workstream],'$ Dashboard'!B28,Table410[Apr_2026_F]) | P28: =SUMIF(Table410[Workstream],'$ Dashboard'!B28,Table410[Apr_2026_A]) | Q28: =SUMIF(Table410[Workstream],'$ Dashboard'!B28,Table410[May_2026_F]) | R28: =SUMIF(Table410[Workstream],'$ Dashboard'!B28,Table410[May_2026_A]) | S28: =SUMIF(Table410[Workstream],'$ Dashboard'!B28,Table410[Jun_2026_F]) | T28: =SUMIF(Table410[Workstream],'$ Dashboard'!B28,Table410[Jun_2026_A]) | U28: =SUMIF(Table410[Workstream],'$ Dashboard'!B28,Table410[Jul_2026_F]) | V28: =SUMIF(Table410[Workstream],'$ Dashboard'!B28,Table410[Jul_2026_A]) | W28: =SUMIF(Table410[Workstream],'$ Dashboard'!B28,Table410[Aug_2026_F]) | X28: =SUMIF(Table410[Workstream],'$ Dashboard'!B28,Table410[Aug_2026_A]) | Y28: =SUMIF(Table410[Workstream],'$ Dashboard'!B28,Table410[Sep_2026_F]) | Z28: =SUMIF(Table410[Workstream],'$ Dashboard'!B28,Table410[Sep_2026_A]) | AA28: =SUMIF(Table410[Workstream],'$ Dashboard'!B28,Table410[Oct_2026_F]) | AB28: =SUMIF(Table410[Workstream],'$ Dashboard'!B28,Table410[Oct_2026_A]) | AC28: =SUMIF(Table410[Workstream],'$ Dashboard'!B28,Table410[Nov_2026_F]) | AD28: =SUMIF(Table410[Workstream],'$ Dashboard'!B28,Table410[Nov_2026_A]) | AE28: =SUMIF(Table410[Workstream],'$ Dashboard'!B28,Table410[Dec_2026_F]) | AF28: =SUMIF(Table410[Workstream],'$ Dashboard'!B28,Table410[Dec_2026_A])+SUMIF(Table46[Workstream],'$ Dashboard'!B28,Table46[Dec_26_A]) | AH28: =SUM(AW28:BG28)/1000000 | AI28: =SUMIF($AJ$12:$BG$12,"Actual",AJ28:BG28)/1000000 | CD28: =SUM(CE28:DB28)/1000000
D29: =SUM(G29,AH29) | E29: =SUM(H29,AI29) | G29: =SUMIF($I$12:$AF$12,"Plan",I29:AF29)/1000000 | H29: =SUMIF($I$12:$AF$12,"Actual",I29:AF29)/1000000 | I29: =SUMIF(Table410[Workstream],'$ Dashboard'!B29,Table410[Jan_2026_F]) | J29: =SUMIF(Table410[Workstream],'$ Dashboard'!B29,Table410[Jan_2026_A]) | K29: =SUMIF(Table410[Workstream],'$ Dashboard'!B29,Table410[Feb_2026_F]) | L29: =SUMIF(Table410[Workstream],'$ Dashboard'!B29,Table410[Feb_2026_A]) | M29: =SUMIF(Table410[Workstream],'$ Dashboard'!B29,Table410[Mar_2026_F]) | N29: =SUMIF(Table410[Workstream],'$ Dashboard'!B29,Table410[Mar_2026_A]) | O29: =SUMIF(Table410[Workstream],'$ Dashboard'!B29,Table410[Apr_2026_F]) | P29: =SUMIF(Table410[Workstream],'$ Dashboard'!B29,Table410[Apr_2026_A]) | Q29: =SUMIF(Table410[Workstream],'$ Dashboard'!B29,Table410[May_2026_F]) | R29: =SUMIF(Table410[Workstream],'$ Dashboard'!B29,Table410[May_2026_A]) | S29: =SUMIF(Table410[Workstream],'$ Dashboard'!B29,Table410[Jun_2026_F]) | T29: =SUMIF(Table410[Workstream],'$ Dashboard'!B29,Table410[Jun_2026_A]) | U29: =SUMIF(Table410[Workstream],'$ Dashboard'!B29,Table410[Jul_2026_F]) | V29: =SUMIF(Table410[Workstream],'$ Dashboard'!B29,Table410[Jul_2026_A]) | W29: =SUMIF(Table410[Workstream],'$ Dashboard'!B29,Table410[Aug_2026_F]) | X29: =SUMIF(Table410[Workstream],'$ Dashboard'!B29,Table410[Aug_2026_A]) | Y29: =SUMIF(Table410[Workstream],'$ Dashboard'!B29,Table410[Sep_2026_F]) | Z29: =SUMIF(Table410[Workstream],'$ Dashboard'!B29,Table410[Sep_2026_A]) | AA29: =SUMIF(Table410[Workstream],'$ Dashboard'!B29,Table410[Oct_2026_F]) | AB29: =SUMIF(Table410[Workstream],'$ Dashboard'!B29,Table410[Oct_2026_A]) | AC29: =SUMIF(Table410[Workstream],'$ Dashboard'!B29,Table410[Nov_2026_F]) | AD29: =SUMIF(Table410[Workstream],'$ Dashboard'!B29,Table410[Nov_2026_A]) | AE29: =SUMIF(Table410[Workstream],'$ Dashboard'!B29,Table410[Dec_2026_F]) | AF29: =SUMIF(Table410[Workstream],'$ Dashboard'!B29,Table410[Dec_2026_A])+SUMIF(Table46[Workstream],'$ Dashboard'!B29,Table46[Dec_26_A]) | AH29: =SUM(AW29:BG29)/1000000 | AI29: =SUMIF($AJ$12:$BG$12,"Actual",AJ29:BG29)/1000000 | CD29: =SUM(CE29:DB29)/1000000
B30: Total | D30: =SUM(D13:D29) | E30: =SUM(E13:E29) | G30: =SUM(G13:G29) | H30: =SUM(H13:H29) | I30: =SUM(I13:I29) | J30: =SUM(J13:J29) | K30: =SUM(K13:K29) | L30: =SUM(L13:L29) | M30: =SUM(M13:M29) | N30: =SUM(N13:N29) | ... AF30: =SUM(AF13:AF29) | AH30: =SUM(AH13:AH29) | AI30: =SUM(AI13:AI29) | AJ30: =SUM(AJ13:AJ29) | AK30: =SUM(AK13:AK29) | AL30: =SUM(AL13:AL29) | AM30: =SUM(AM13:AM29) | AN30: =SUM(AN13:AN29) | AO30: =SUM(AO13:AO29) | ... BG30: =SUM(BG13:BG29) | CD30: =SUM(CD13:CD29) | CE30: =SUM(CE13:CE29) | CF30: =SUM(CF13:CF29) | CG30: =SUM(CG13:CG29) | CH30: =SUM(CH13:CH29) | CI30: =SUM(CI13:CI29) | CJ30: =SUM(CJ13:CJ29) | CK30: =SUM(CK13:CK29) | ... DB30: =SUM(DB13:DB29)
AK31: =IFERROR(AK30/AJ30,0) | AM31: =IFERROR(AM30/AL30,0) | AO31: =IFERROR(AO30/AN30,0) | AQ31: =IFERROR(AQ30/AP30,0) | AS31: =IFERROR(AS30/AR30,0) | AU31: =IFERROR(AU30/AT30,0) | AW31: =IFERROR(AW30/AV30,0) | AY31: =IFERROR(AY30/AX30,0) | BA31: =IFERROR(BA30/AZ30,0) | BC31: =IFERROR(BC30/BB30,0) | BE31: =IFERROR(BE30/BD30,0) | BG31: =IFERROR(BG30/BF30,0)
D35: [2026 - 2027] | G35: [2026] | AH35: [2027]
B36: Business Resource cost by WS/PH | C36: Business/IT | D36: Program LE | E36: Program YTD Actual | G36: LE | H36: Actual | I36: 46023 | K36: 46054 | M36: 46082 | O36: 46113 | Q36: 46143 | S36: 46174 | U36: 46204 | W36: 46235 | Y36: 46266 | AA36: 46296 | AC36: 46327 | AE36: 46357 | AH36: LE | AI36: Actual | AJ36: 46388 | AL36: 46419 | AN36: 46447 | AP36: 46478 | AR36: 46508 | AT36: 46539 | AV36: 46569 | AX36: 46600 | AZ36: 46631 | BB36: 46661 | BD36: 46692 | BF36: 46722 | CD36: GIP | CE36: 46023 | CF36: 46054 | CG36: 46082 | CH36: 46113 | CI36: 46143 | CJ36: 46174 | CK36: 46204 | CL36: 46235 | CM36: 46266 | CN36: 46296 | CO36: 46327 | CP36: 46357 | CQ36: 46388 | CR36: 46419 | CS36: 46447 | CT36: 46478 | CU36: 46508 | CV36: 46539 | CW36: 46569 | CX36: 46600 | CY36: 46631 | CZ36: 46661 | DA36: 46692 | DB36: 46722
I37: Plan | J37: Actual | K37: Plan | L37: Actual | M37: Plan | N37: Actual | O37: Plan | P37: Actual | Q37: Plan | R37: Actual | S37: Plan | T37: Actual | U37: Plan | V37: Actual | W37: Plan | X37: Actual | Y37: Plan | Z37: Actual | AA37: Plan | AB37: Actual | AC37: Plan | AD37: Actual | AE37: Plan | AF37: Actual | AJ37: Plan | AK37: =IF(AJ36<=$B$5,"Actual","") | AL37: Plan | AM37: =IF(AL36<=$B$5,"Actual","") | AN37: Plan | AO37: =IF(AN36<=$B$5,"Actual","") | AP37: Plan | AQ37: =IF(AP36<=$B$5,"Actual","") | AR37: Plan | AS37: =IF(AR36<=$B$5,"Actual","") | AT37: Plan | AU37: =IF(AT36<=$B$5,"Actual","") | AV37: Plan | AW37: =IF(AV36<=$B$5,"Actual","") | AX37: Plan | AY37: =IF(AX36<=$B$5,"Actual","") | AZ37: Plan | BA37: =IF(AZ36<=$B$5,"Actual","") | BB37: Plan | BC37: =IF(BB36<=$B$5,"Actual","") | BD37: Plan | BE37: =IF(BD36<=$B$5,"Actual","") | BF37: Plan | BG37: =IF(BF36<=$B$5,"Actual","")
B38: Program Management | C38: Business | D38: =SUM(G38,AH38) | E38: =SUM(H38,AI38) | G38: =SUMIF($I$12:$AF$12,"Plan",I38:AF38)/1000000 | H38: =SUMIF($I$12:$AF$12,"Actual",I38:AF38)/1000000 | I38: =SUMIF(Table410[Workstream],'$ Dashboard'!B38,Table410[Jan_2026_F]) | J38: =SUMIF(Table410[Workstream],'$ Dashboard'!B38,Table410[Jan_2026_A]) | K38: =SUMIF(Table410[Workstream],'$ Dashboard'!B38,Table410[Feb_2026_F]) | L38: =SUMIF(Table410[Workstream],'$ Dashboard'!B38,Table410[Feb_2026_A]) | M38: =SUMIF(Table410[Workstream],'$ Dashboard'!B38,Table410[Mar_2026_F]) | N38: =SUMIF(Table410[Workstream],'$ Dashboard'!B38,Table410[Mar_2026_A]) | O38: =SUMIF(Table410[Workstream],'$ Dashboard'!B38,Table410[Apr_2026_F]) | P38: =SUMIF(Table410[Workstream],'$ Dashboard'!B38,Table410[Apr_2026_A]) | Q38: =SUMIF(Table410[Workstream],'$ Dashboard'!B38,Table410[May_2026_F]) | R38: =SUMIF(Table410[Workstream],'$ Dashboard'!B38,Table410[May_2026_A]) | S38: =SUMIF(Table410[Workstream],'$ Dashboard'!B38,Table410[Jun_2026_F]) | T38: =SUMIF(Table410[Workstream],'$ Dashboard'!B38,Table410[Jun_2026_A]) | U38: =SUMIF(Table410[Workstream],'$ Dashboard'!B38,Table410[Jul_2026_F]) | V38: =SUMIF(Table410[Workstream],'$ Dashboard'!B38,Table410[Jul_2026_A]) | W38: =SUMIF(Table410[Workstream],'$ Dashboard'!B38,Table410[Aug_2026_F]) | X38: =SUMIF(Table410[Workstream],'$ Dashboard'!B38,Table410[Aug_2026_A]) | Y38: =SUMIF(Table410[Workstream],'$ Dashboard'!B38,Table410[Sep_2026_F]) | Z38: =SUMIF(Table410[Workstream],'$ Dashboard'!B38,Table410[Sep_2026_A]) | AA38: =SUMIF(Table410[Workstream],'$ Dashboard'!B38,Table410[Oct_2026_F]) | AB38: =SUMIF(Table410[Workstream],'$ Dashboard'!B38,Table410[Oct_2026_A]) | AC38: =SUMIF(Table410[Workstream],'$ Dashboard'!B38,Table410[Nov_2026_F]) | AD38: =SUMIF(Table410[Workstream],'$ Dashboard'!B38,Table410[Nov_2026_A]) | AE38: =SUMIF(Table410[Workstream],'$ Dashboard'!B38,Table410[Dec_2026_F]) | AF38: =SUMIF(Table410[Workstream],'$ Dashboard'!B38,Table410[Dec_2026_A])+SUMIF(Table46[Workstream],'$ Dashboard'!B38,Table46[Dec_26_A]) | AH38: =SUM(AW38:BG38)/1000000 | AI38: =SUMIF($AJ$12:$BG$12,"Actual",AJ38:BG38)/1000000 | CD38: =SUM(CE38:DB38)/1000000
B39: Prosmar Crude | C39: Business | D39: =SUM(G39,AH39) | E39: =SUM(H39,AI39) | G39: =SUMIF($I$12:$AF$12,"Plan",I39:AF39)/1000000 | H39: =SUMIF($I$12:$AF$12,"Actual",I39:AF39)/1000000 | I39: =SUMIF(Table410[Workstream],'$ Dashboard'!B39,Table410[Jan_2026_F]) | J39: =SUMIF(Table410[Workstream],'$ Dashboard'!B39,Table410[Jan_2026_A]) | K39: =SUMIF(Table410[Workstream],'$ Dashboard'!B39,Table410[Feb_2026_F]) | L39: =SUMIF(Table410[Workstream],'$ Dashboard'!B39,Table410[Feb_2026_A]) | M39: =SUMIF(Table410[Workstream],'$ Dashboard'!B39,Table410[Mar_2026_F]) | N39: =SUMIF(Table410[Workstream],'$ Dashboard'!B39,Table410[Mar_2026_A]) | O39: =SUMIF(Table410[Workstream],'$ Dashboard'!B39,Table410[Apr_2026_F]) | P39: =SUMIF(Table410[Workstream],'$ Dashboard'!B39,Table410[Apr_2026_A]) | Q39: =SUMIF(Table410[Workstream],'$ Dashboard'!B39,Table410[May_2026_F]) | R39: =SUMIF(Table410[Workstream],'$ Dashboard'!B39,Table410[May_2026_A]) | S39: =SUMIF(Table410[Workstream],'$ Dashboard'!B39,Table410[Jun_2026_F]) | T39: =SUMIF(Table410[Workstream],'$ Dashboard'!B39,Table410[Jun_2026_A]) | U39: =SUMIF(Table410[Workstream],'$ Dashboard'!B39,Table410[Jul_2026_F]) | V39: =SUMIF(Table410[Workstream],'$ Dashboard'!B39,Table410[Jul_2026_A]) | W39: =SUMIF(Table410[Workstream],'$ Dashboard'!B39,Table410[Aug_2026_F]) | X39: =SUMIF(Table410[Workstream],'$ Dashboard'!B39,Table410[Aug_2026_A]) | Y39: =SUMIF(Table410[Workstream],'$ Dashboard'!B39,Table410[Sep_2026_F]) | Z39: =SUMIF(Table410[Workstream],'$ Dashboard'!B39,Table410[Sep_2026_A]) | AA39: =SUMIF(Table410[Workstream],'$ Dashboard'!B39,Table410[Oct_2026_F]) | AB39: =SUMIF(Table410[Workstream],'$ Dashboard'!B39,Table410[Oct_2026_A]) | AC39: =SUMIF(Table410[Workstream],'$ Dashboard'!B39,Table410[Nov_2026_F]) | AD39: =SUMIF(Table410[Workstream],'$ Dashboard'!B39,Table410[Nov_2026_A]) | AE39: =SUMIF(Table410[Workstream],'$ Dashboard'!B39,Table410[Dec_2026_F]) | AF39: =SUMIF(Table410[Workstream],'$ Dashboard'!B39,Table410[Dec_2026_A])+SUMIF(Table46[Workstream],'$ Dashboard'!B39,Table46[Dec_26_A]) | AH39: =SUM(AW39:BG39)/1000000 | AI39: =SUMIF($AJ$12:$BG$12,"Actual",AJ39:BG39)/1000000
B40: Prosmar Products | C40: Business | D40: =SUM(G40,AH40) | E40: =SUM(H40,AI40) | G40: =SUMIF($I$12:$AF$12,"Plan",I40:AF40)/1000000 | H40: =SUMIF($I$12:$AF$12,"Actual",I40:AF40)/1000000 | I40: =SUMIF(Table410[Workstream],'$ Dashboard'!B40,Table410[Jan_2026_F]) | J40: =SUMIF(Table410[Workstream],'$ Dashboard'!B40,Table410[Jan_2026_A]) | K40: =SUMIF(Table410[Workstream],'$ Dashboard'!B40,Table410[Feb_2026_F]) | L40: =SUMIF(Table410[Workstream],'$ Dashboard'!B40,Table410[Feb_2026_A]) | M40: =SUMIF(Table410[Workstream],'$ Dashboard'!B40,Table410[Mar_2026_F]) | N40: =SUMIF(Table410[Workstream],'$ Dashboard'!B40,Table410[Mar_2026_A]) | O40: =SUMIF(Table410[Workstream],'$ Dashboard'!B40,Table410[Apr_2026_F]) | P40: =SUMIF(Table410[Workstream],'$ Dashboard'!B40,Table410[Apr_2026_A]) | Q40: =SUMIF(Table410[Workstream],'$ Dashboard'!B40,Table410[May_2026_F]) | R40: =SUMIF(Table410[Workstream],'$ Dashboard'!B40,Table410[May_2026_A]) | S40: =SUMIF(Table410[Workstream],'$ Dashboard'!B40,Table410[Jun_2026_F]) | T40: =SUMIF(Table410[Workstream],'$ Dashboard'!B40,Table410[Jun_2026_A]) | U40: =SUMIF(Table410[Workstream],'$ Dashboard'!B40,Table410[Jul_2026_F]) | V40: =SUMIF(Table410[Workstream],'$ Dashboard'!B40,Table410[Jul_2026_A]) | W40: =SUMIF(Table410[Workstream],'$ Dashboard'!B40,Table410[Aug_2026_F]) | X40: =SUMIF(Table410[Workstream],'$ Dashboard'!B40,Table410[Aug_2026_A]) | Y40: =SUMIF(Table410[Workstream],'$ Dashboard'!B40,Table410[Sep_2026_F]) | Z40: =SUMIF(Table410[Workstream],'$ Dashboard'!B40,Table410[Sep_2026_A]) | AA40: =SUMIF(Table410[Workstream],'$ Dashboard'!B40,Table410[Oct_2026_F]) | AB40: =SUMIF(Table410[Workstream],'$ Dashboard'!B40,Table410[Oct_2026_A]) | AC40: =SUMIF(Table410[Workstream],'$ Dashboard'!B40,Table410[Nov_2026_F]) | AD40: =SUMIF(Table410[Workstream],'$ Dashboard'!B40,Table410[Nov_2026_A]) | AE40: =SUMIF(Table410[Workstream],'$ Dashboard'!B40,Table410[Dec_2026_F]) | AF40: =SUMIF(Table410[Workstream],'$ Dashboard'!B40,Table410[Dec_2026_A])+SUMIF(Table46[Workstream],'$ Dashboard'!B40,Table46[Dec_26_A]) | AH40: =SUM(AW40:BG40)/1000000 | AI40: =SUMIF($AJ$12:$BG$12,"Actual",AJ40:BG40)/1000000
B41: VPD | C41: Business | D41: =SUM(G41,AH41) | E41: =SUM(H41,AI41) | G41: =SUMIF($I$12:$AF$12,"Plan",I41:AF41)/1000000 | H41: =SUMIF($I$12:$AF$12,"Actual",I41:AF41)/1000000 | I41: =SUMIF(Table410[Workstream],'$ Dashboard'!B41,Table410[Jan_2026_F]) | J41: =SUMIF(Table410[Workstream],'$ Dashboard'!B41,Table410[Jan_2026_A]) | K41: =SUMIF(Table410[Workstream],'$ Dashboard'!B41,Table410[Feb_2026_F]) | L41: =SUMIF(Table410[Workstream],'$ Dashboard'!B41,Table410[Feb_2026_A]) | M41: =SUMIF(Table410[Workstream],'$ Dashboard'!B41,Table410[Mar_2026_F]) | N41: =SUMIF(Table410[Workstream],'$ Dashboard'!B41,Table410[Mar_2026_A]) | O41: =SUMIF(Table410[Workstream],'$ Dashboard'!B41,Table410[Apr_2026_F]) | P41: =SUMIF(Table410[Workstream],'$ Dashboard'!B41,Table410[Apr_2026_A]) | Q41: =SUMIF(Table410[Workstream],'$ Dashboard'!B41,Table410[May_2026_F]) | R41: =SUMIF(Table410[Workstream],'$ Dashboard'!B41,Table410[May_2026_A]) | S41: =SUMIF(Table410[Workstream],'$ Dashboard'!B41,Table410[Jun_2026_F]) | T41: =SUMIF(Table410[Workstream],'$ Dashboard'!B41,Table410[Jun_2026_A]) | U41: =SUMIF(Table410[Workstream],'$ Dashboard'!B41,Table410[Jul_2026_F]) | V41: =SUMIF(Table410[Workstream],'$ Dashboard'!B41,Table410[Jul_2026_A]) | W41: =SUMIF(Table410[Workstream],'$ Dashboard'!B41,Table410[Aug_2026_F]) | X41: =SUMIF(Table410[Workstream],'$ Dashboard'!B41,Table410[Aug_2026_A]) | Y41: =SUMIF(Table410[Workstream],'$ Dashboard'!B41,Table410[Sep_2026_F]) | Z41: =SUMIF(Table410[Workstream],'$ Dashboard'!B41,Table410[Sep_2026_A]) | AA41: =SUMIF(Table410[Workstream],'$ Dashboard'!B41,Table410[Oct_2026_F]) | AB41: =SUMIF(Table410[Workstream],'$ Dashboard'!B41,Table410[Oct_2026_A]) | AC41: =SUMIF(Table410[Workstream],'$ Dashboard'!B41,Table410[Nov_2026_F]) | AD41: =SUMIF(Table410[Workstream],'$ Dashboard'!B41,Table410[Nov_2026_A]) | AE41: =SUMIF(Table410[Workstream],'$ Dashboard'!B41,Table410[Dec_2026_F]) | AF41: =SUMIF(Table410[Workstream],'$ Dashboard'!B41,Table410[Dec_2026_A])+SUMIF(Table46[Workstream],'$ Dashboard'!B41,Table46[Dec_26_A]) | AH41: =SUM(AW41:BG41)/1000000 | AI41: =SUMIF($AJ$12:$BG$12,"Actual",AJ41:BG41)/1000000 | CD41: =SUM(CE41:DB41)/1000000
B42: GATOR | C42: Business | D42: =SUM(G42,AH42) | E42: =SUM(H42,AI42) | G42: =SUMIF($I$12:$AF$12,"Plan",I42:AF42)/1000000 | H42: =SUMIF($I$12:$AF$12,"Actual",I42:AF42)/1000000 | I42: =SUMIF(Table410[Workstream],'$ Dashboard'!B42,Table410[Jan_2026_F]) | J42: =SUMIF(Table410[Workstream],'$ Dashboard'!B42,Table410[Jan_2026_A]) | K42: =SUMIF(Table410[Workstream],'$ Dashboard'!B42,Table410[Feb_2026_F]) | L42: =SUMIF(Table410[Workstream],'$ Dashboard'!B42,Table410[Feb_2026_A]) | M42: =SUMIF(Table410[Workstream],'$ Dashboard'!B42,Table410[Mar_2026_F]) | N42: =SUMIF(Table410[Workstream],'$ Dashboard'!B42,Table410[Mar_2026_A]) | O42: =SUMIF(Table410[Workstream],'$ Dashboard'!B42,Table410[Apr_2026_F]) | P42: =SUMIF(Table410[Workstream],'$ Dashboard'!B42,Table410[Apr_2026_A]) | Q42: =SUMIF(Table410[Workstream],'$ Dashboard'!B42,Table410[May_2026_F]) | R42: =SUMIF(Table410[Workstream],'$ Dashboard'!B42,Table410[May_2026_A]) | S42: =SUMIF(Table410[Workstream],'$ Dashboard'!B42,Table410[Jun_2026_F]) | T42: =SUMIF(Table410[Workstream],'$ Dashboard'!B42,Table410[Jun_2026_A]) | U42: =SUMIF(Table410[Workstream],'$ Dashboard'!B42,Table410[Jul_2026_F]) | V42: =SUMIF(Table410[Workstream],'$ Dashboard'!B42,Table410[Jul_2026_A]) | W42: =SUMIF(Table410[Workstream],'$ Dashboard'!B42,Table410[Aug_2026_F]) | X42: =SUMIF(Table410[Workstream],'$ Dashboard'!B42,Table410[Aug_2026_A]) | Y42: =SUMIF(Table410[Workstream],'$ Dashboard'!B42,Table410[Sep_2026_F]) | Z42: =SUMIF(Table410[Workstream],'$ Dashboard'!B42,Table410[Sep_2026_A]) | AA42: =SUMIF(Table410[Workstream],'$ Dashboard'!B42,Table410[Oct_2026_F]) | AB42: =SUMIF(Table410[Workstream],'$ Dashboard'!B42,Table410[Oct_2026_A]) | AC42: =SUMIF(Table410[Workstream],'$ Dashboard'!B42,Table410[Nov_2026_F]) | AD42: =SUMIF(Table410[Workstream],'$ Dashboard'!B42,Table410[Nov_2026_A]) | AE42: =SUMIF(Table410[Workstream],'$ Dashboard'!B42,Table410[Dec_2026_F]) | AF42: =SUMIF(Table410[Workstream],'$ Dashboard'!B42,Table410[Dec_2026_A])+SUMIF(Table46[Workstream],'$ Dashboard'!B42,Table46[Dec_26_A]) | AH42: =SUM(AW42:BG42)/1000000 | AI42: =SUMIF($AJ$12:$BG$12,"Actual",AJ42:BG42)/1000000 | CD42: =SUM(CE42:DB42)/1000000
B43: USDF | C43: Business | D43: =SUM(G43,AH43) | E43: =SUM(H43,AI43) | G43: =SUMIF($I$12:$AF$12,"Plan",I43:AF43)/1000000 | H43: =SUMIF($I$12:$AF$12,"Actual",I43:AF43)/1000000 | I43: =SUMIF(Table410[Workstream],'$ Dashboard'!B43,Table410[Jan_2026_F]) | J43: =SUMIF(Table410[Workstream],'$ Dashboard'!B43,Table410[Jan_2026_A]) | K43: =SUMIF(Table410[Workstream],'$ Dashboard'!B43,Table410[Feb_2026_F]) | L43: =SUMIF(Table410[Workstream],'$ Dashboard'!B43,Table410[Feb_2026_A]) | M43: =SUMIF(Table410[Workstream],'$ Dashboard'!B43,Table410[Mar_2026_F]) | N43: =SUMIF(Table410[Workstream],'$ Dashboard'!B43,Table410[Mar_2026_A]) | O43: =SUMIF(Table410[Workstream],'$ Dashboard'!B43,Table410[Apr_2026_F]) | P43: =SUMIF(Table410[Workstream],'$ Dashboard'!B43,Table410[Apr_2026_A]) | Q43: =SUMIF(Table410[Workstream],'$ Dashboard'!B43,Table410[May_2026_F]) | R43: =SUMIF(Table410[Workstream],'$ Dashboard'!B43,Table410[May_2026_A]) | S43: =SUMIF(Table410[Workstream],'$ Dashboard'!B43,Table410[Jun_2026_F]) | T43: =SUMIF(Table410[Workstream],'$ Dashboard'!B43,Table410[Jun_2026_A]) | U43: =SUMIF(Table410[Workstream],'$ Dashboard'!B43,Table410[Jul_2026_F]) | V43: =SUMIF(Table410[Workstream],'$ Dashboard'!B43,Table410[Jul_2026_A]) | W43: =SUMIF(Table410[Workstream],'$ Dashboard'!B43,Table410[Aug_2026_F]) | X43: =SUMIF(Table410[Workstream],'$ Dashboard'!B43,Table410[Aug_2026_A]) | Y43: =SUMIF(Table410[Workstream],'$ Dashboard'!B43,Table410[Sep_2026_F]) | Z43: =SUMIF(Table410[Workstream],'$ Dashboard'!B43,Table410[Sep_2026_A]) | AA43: =SUMIF(Table410[Workstream],'$ Dashboard'!B43,Table410[Oct_2026_F]) | AB43: =SUMIF(Table410[Workstream],'$ Dashboard'!B43,Table410[Oct_2026_A]) | AC43: =SUMIF(Table410[Workstream],'$ Dashboard'!B43,Table410[Nov_2026_F]) | AD43: =SUMIF(Table410[Workstream],'$ Dashboard'!B43,Table410[Nov_2026_A]) | AE43: =SUMIF(Table410[Workstream],'$ Dashboard'!B43,Table410[Dec_2026_F]) | AF43: =SUMIF(Table410[Workstream],'$ Dashboard'!B43,Table410[Dec_2026_A])+SUMIF(Table46[Workstream],'$ Dashboard'!B43,Table46[Dec_26_A]) | AH43: =SUM(AW43:BG43)/1000000 | AI43: =SUMIF($AJ$12:$BG$12,"Actual",AJ43:BG43)/1000000 | CD43: =SUM(CE43:DB43)/1000000
B44: JIGSAW & PDS Process work | C44: Business | D44: =SUM(G44,AH44) | E44: =SUM(H44,AI44) | G44: =SUMIF($I$12:$AF$12,"Plan",I44:AF44)/1000000 | H44: =SUMIF($I$12:$AF$12,"Actual",I44:AF44)/1000000 | I44: =SUMIF(Table410[Workstream],'$ Dashboard'!B44,Table410[Jan_2026_F]) | J44: =SUMIF(Table410[Workstream],'$ Dashboard'!B44,Table410[Jan_2026_A]) | K44: =SUMIF(Table410[Workstream],'$ Dashboard'!B44,Table410[Feb_2026_F]) | L44: =SUMIF(Table410[Workstream],'$ Dashboard'!B44,Table410[Feb_2026_A]) | M44: =SUMIF(Table410[Workstream],'$ Dashboard'!B44,Table410[Mar_2026_F]) | N44: =SUMIF(Table410[Workstream],'$ Dashboard'!B44,Table410[Mar_2026_A]) | O44: =SUMIF(Table410[Workstream],'$ Dashboard'!B44,Table410[Apr_2026_F]) | P44: =SUMIF(Table410[Workstream],'$ Dashboard'!B44,Table410[Apr_2026_A]) | Q44: =SUMIF(Table410[Workstream],'$ Dashboard'!B44,Table410[May_2026_F]) | R44: =SUMIF(Table410[Workstream],'$ Dashboard'!B44,Table410[May_2026_A]) | S44: =SUMIF(Table410[Workstream],'$ Dashboard'!B44,Table410[Jun_2026_F]) | T44: =SUMIF(Table410[Workstream],'$ Dashboard'!B44,Table410[Jun_2026_A]) | U44: =SUMIF(Table410[Workstream],'$ Dashboard'!B44,Table410[Jul_2026_F]) | V44: =SUMIF(Table410[Workstream],'$ Dashboard'!B44,Table410[Jul_2026_A]) | W44: =SUMIF(Table410[Workstream],'$ Dashboard'!B44,Table410[Aug_2026_F]) | X44: =SUMIF(Table410[Workstream],'$ Dashboard'!B44,Table410[Aug_2026_A]) | Y44: =SUMIF(Table410[Workstream],'$ Dashboard'!B44,Table410[Sep_2026_F]) | Z44: =SUMIF(Table410[Workstream],'$ Dashboard'!B44,Table410[Sep_2026_A]) | AA44: =SUMIF(Table410[Workstream],'$ Dashboard'!B44,Table410[Oct_2026_F]) | AB44: =SUMIF(Table410[Workstream],'$ Dashboard'!B44,Table410[Oct_2026_A]) | AC44: =SUMIF(Table410[Workstream],'$ Dashboard'!B44,Table410[Nov_2026_F]) | AD44: =SUMIF(Table410[Workstream],'$ Dashboard'!B44,Table410[Nov_2026_A]) | AE44: =SUMIF(Table410[Workstream],'$ Dashboard'!B44,Table410[Dec_2026_F]) | AF44: =SUMIF(Table410[Workstream],'$ Dashboard'!B44,Table410[Dec_2026_A])+SUMIF(Table46[Workstream],'$ Dashboard'!B44,Table46[Dec_26_A]) | AH44: =SUM(AW44:BG44)/1000000 | AI44: =SUMIF($AJ$12:$BG$12,"Actual",AJ44:BG44)/1000000 | CD44: =SUM(CE44:DB44)/1000000
D45: =SUM(G45,AH45) | E45: =SUM(H45,AI45) | G45: =SUMIF($I$12:$AF$12,"Plan",I45:AF45)/1000000 | H45: =SUMIF($I$12:$AF$12,"Actual",I45:AF45)/1000000 | I45: =SUMIF(Table410[Workstream],'$ Dashboard'!B45,Table410[Jan_2026_F]) | J45: =SUMIF(Table410[Workstream],'$ Dashboard'!B45,Table410[Jan_2026_A]) | K45: =SUMIF(Table410[Workstream],'$ Dashboard'!B45,Table410[Feb_2026_F]) | L45: =SUMIF(Table410[Workstream],'$ Dashboard'!B45,Table410[Feb_2026_A]) | M45: =SUMIF(Table410[Workstream],'$ Dashboard'!B45,Table410[Mar_2026_F]) | N45: =SUMIF(Table410[Workstream],'$ Dashboard'!B45,Table410[Mar_2026_A]) | O45: =SUMIF(Table410[Workstream],'$ Dashboard'!B45,Table410[Apr_2026_F]) | P45: =SUMIF(Table410[Workstream],'$ Dashboard'!B45,Table410[Apr_2026_A]) | Q45: =SUMIF(Table410[Workstream],'$ Dashboard'!B45,Table410[May_2026_F]) | R45: =SUMIF(Table410[Workstream],'$ Dashboard'!B45,Table410[May_2026_A]) | S45: =SUMIF(Table410[Workstream],'$ Dashboard'!B45,Table410[Jun_2026_F]) | T45: =SUMIF(Table410[Workstream],'$ Dashboard'!B45,Table410[Jun_2026_A]) | U45: =SUMIF(Table410[Workstream],'$ Dashboard'!B45,Table410[Jul_2026_F]) | V45: =SUMIF(Table410[Workstream],'$ Dashboard'!B45,Table410[Jul_2026_A]) | W45: =SUMIF(Table410[Workstream],'$ Dashboard'!B45,Table410[Aug_2026_F]) | X45: =SUMIF(Table410[Workstream],'$ Dashboard'!B45,Table410[Aug_2026_A]) | Y45: =SUMIF(Table410[Workstream],'$ Dashboard'!B45,Table410[Sep_2026_F]) | Z45: =SUMIF(Table410[Workstream],'$ Dashboard'!B45,Table410[Sep_2026_A]) | AA45: =SUMIF(Table410[Workstream],'$ Dashboard'!B45,Table410[Oct_2026_F]) | AB45: =SUMIF(Table410[Workstream],'$ Dashboard'!B45,Table410[Oct_2026_A]) | AC45: =SUMIF(Table410[Workstream],'$ Dashboard'!B45,Table410[Nov_2026_F]) | AD45: =SUMIF(Table410[Workstream],'$ Dashboard'!B45,Table410[Nov_2026_A]) | AE45: =SUMIF(Table410[Workstream],'$ Dashboard'!B45,Table410[Dec_2026_F]) | AF45: =SUMIF(Table410[Workstream],'$ Dashboard'!B45,Table410[Dec_2026_A])+SUMIF(Table46[Workstream],'$ Dashboard'!B45,Table46[Dec_26_A]) | AH45: =SUM(AW45:BG45)/1000000 | AI45: =SUMIF($AJ$12:$BG$12,"Actual",AJ45:BG45)/1000000 | CD45: =SUM(CE45:DB45)/1000000
D46: =SUM(G46,AH46) | E46: =SUM(H46,AI46) | G46: =SUMIF($I$12:$AF$12,"Plan",I46:AF46)/1000000 | H46: =SUMIF($I$12:$AF$12,"Actual",I46:AF46)/1000000 | I46: =SUMIF(Table410[Workstream],'$ Dashboard'!B46,Table410[Jan_2026_F]) | J46: =SUMIF(Table410[Workstream],'$ Dashboard'!B46,Table410[Jan_2026_A]) | K46: =SUMIF(Table410[Workstream],'$ Dashboard'!B46,Table410[Feb_2026_F]) | L46: =SUMIF(Table410[Workstream],'$ Dashboard'!B46,Table410[Feb_2026_A]) | M46: =SUMIF(Table410[Workstream],'$ Dashboard'!B46,Table410[Mar_2026_F]) | N46: =SUMIF(Table410[Workstream],'$ Dashboard'!B46,Table410[Mar_2026_A]) | O46: =SUMIF(Table410[Workstream],'$ Dashboard'!B46,Table410[Apr_2026_F]) | P46: =SUMIF(Table410[Workstream],'$ Dashboard'!B46,Table410[Apr_2026_A]) | Q46: =SUMIF(Table410[Workstream],'$ Dashboard'!B46,Table410[May_2026_F]) | R46: =SUMIF(Table410[Workstream],'$ Dashboard'!B46,Table410[May_2026_A]) | S46: =SUMIF(Table410[Workstream],'$ Dashboard'!B46,Table410[Jun_2026_F]) | T46: =SUMIF(Table410[Workstream],'$ Dashboard'!B46,Table410[Jun_2026_A]) | U46: =SUMIF(Table410[Workstream],'$ Dashboard'!B46,Table410[Jul_2026_F]) | V46: =SUMIF(Table410[Workstream],'$ Dashboard'!B46,Table410[Jul_2026_A]) | W46: =SUMIF(Table410[Workstream],'$ Dashboard'!B46,Table410[Aug_2026_F]) | X46: =SUMIF(Table410[Workstream],'$ Dashboard'!B46,Table410[Aug_2026_A]) | Y46: =SUMIF(Table410[Workstream],'$ Dashboard'!B46,Table410[Sep_2026_F]) | Z46: =SUMIF(Table410[Workstream],'$ Dashboard'!B46,Table410[Sep_2026_A]) | AA46: =SUMIF(Table410[Workstream],'$ Dashboard'!B46,Table410[Oct_2026_F]) | AB46: =SUMIF(Table410[Workstream],'$ Dashboard'!B46,Table410[Oct_2026_A]) | AC46: =SUMIF(Table410[Workstream],'$ Dashboard'!B46,Table410[Nov_2026_F]) | AD46: =SUMIF(Table410[Workstream],'$ Dashboard'!B46,Table410[Nov_2026_A]) | AE46: =SUMIF(Table410[Workstream],'$ Dashboard'!B46,Table410[Dec_2026_F]) | AF46: =SUMIF(Table410[Workstream],'$ Dashboard'!B46,Table410[Dec_2026_A])+SUMIF(Table46[Workstream],'$ Dashboard'!B46,Table46[Dec_26_A]) | AH46: =SUM(AW46:BG46)/1000000 | AI46: =SUMIF($AJ$12:$BG$12,"Actual",AJ46:BG46)/1000000 | CD46: =SUM(CE46:DB46)/1000000
D47: =SUM(G47,AH47) | E47: =SUM(H47,AI47) | G47: =SUMIF($I$12:$AF$12,"Plan",I47:AF47)/1000000 | H47: =SUMIF($I$12:$AF$12,"Actual",I47:AF47)/1000000 | I47: =SUMIF(Table410[Workstream],'$ Dashboard'!B47,Table410[Jan_2026_F]) | J47: =SUMIF(Table410[Workstream],'$ Dashboard'!B47,Table410[Jan_2026_A]) | K47: =SUMIF(Table410[Workstream],'$ Dashboard'!B47,Table410[Feb_2026_F]) | L47: =SUMIF(Table410[Workstream],'$ Dashboard'!B47,Table410[Feb_2026_A]) | M47: =SUMIF(Table410[Workstream],'$ Dashboard'!B47,Table410[Mar_2026_F]) | N47: =SUMIF(Table410[Workstream],'$ Dashboard'!B47,Table410[Mar_2026_A]) | O47: =SUMIF(Table410[Workstream],'$ Dashboard'!B47,Table410[Apr_2026_F]) | P47: =SUMIF(Table410[Workstream],'$ Dashboard'!B47,Table410[Apr_2026_A]) | Q47: =SUMIF(Table410[Workstream],'$ Dashboard'!B47,Table410[May_2026_F]) | R47: =SUMIF(Table410[Workstream],'$ Dashboard'!B47,Table410[May_2026_A]) | S47: =SUMIF(Table410[Workstream],'$ Dashboard'!B47,Table410[Jun_2026_F]) | T47: =SUMIF(Table410[Workstream],'$ Dashboard'!B47,Table410[Jun_2026_A]) | U47: =SUMIF(Table410[Workstream],'$ Dashboard'!B47,Table410[Jul_2026_F]) | V47: =SUMIF(Table410[Workstream],'$ Dashboard'!B47,Table410[Jul_2026_A]) | W47: =SUMIF(Table410[Workstream],'$ Dashboard'!B47,Table410[Aug_2026_F]) | X47: =SUMIF(Table410[Workstream],'$ Dashboard'!B47,Table410[Aug_2026_A]) | Y47: =SUMIF(Table410[Workstream],'$ Dashboard'!B47,Table410[Sep_2026_F]) | Z47: =SUMIF(Table410[Workstream],'$ Dashboard'!B47,Table410[Sep_2026_A]) | AA47: =SUMIF(Table410[Workstream],'$ Dashboard'!B47,Table410[Oct_2026_F]) | AB47: =SUMIF(Table410[Workstream],'$ Dashboard'!B47,Table410[Oct_2026_A]) | AC47: =SUMIF(Table410[Workstream],'$ Dashboard'!B47,Table410[Nov_2026_F]) | AD47: =SUMIF(Table410[Workstream],'$ Dashboard'!B47,Table410[Nov_2026_A]) | AE47: =SUMIF(Table410[Workstream],'$ Dashboard'!B47,Table410[Dec_2026_F]) | AF47: =SUMIF(Table410[Workstream],'$ Dashboard'!B47,Table410[Dec_2026_A])+SUMIF(Table46[Workstream],'$ Dashboard'!B47,Table46[Dec_26_A]) | AH47: =SUM(AW47:BG47)/1000000 | AI47: =SUMIF($AJ$12:$BG$12,"Actual",AJ47:BG47)/1000000 | CD47: =SUM(CE47:DB47)/1000000
B48: Total | D48: =SUM(D38:D47) | E48: =SUM(E38:E47) | G48: =SUM(G38:G47) | H48: =SUM(H38:H47) | I48: =SUM(I38:I47) | J48: =SUM(J38:J47) | K48: =SUM(K38:K47) | L48: =SUM(L38:L47) | M48: =SUM(M38:M47) | N48: =SUM(N38:N47) | ... AF48: =SUM(AF38:AF47) | AH48: =SUM(AH38:AH47) | AI48: =SUM(AI38:AI47) | AJ48: =SUM(AJ38:AJ47) | AK48: =SUM(AK38:AK47) | AL48: =SUM(AL38:AL47) | AM48: =SUM(AM38:AM47) | AN48: =SUM(AN38:AN47) | AO48: =SUM(AO38:AO47) | ... BG48: =SUM(BG38:BG47) | CD48: =SUM(CD38:CD47) | CE48: =SUM(CE38:CE47) | CF48: =SUM(CF38:CF47) | CG48: =SUM(CG38:CG47) | CH48: =SUM(CH38:CH47) | CI48: =SUM(CI38:CI47) | CJ48: =SUM(CJ38:CJ47) | CK48: =SUM(CK38:CK47) | ... DB48: =SUM(DB38:DB47)
B52: Totals | D52: =SUM(G52,AH52) | E52: =SUM(H52,AI52) | G52: {=SUM(H52,SUMPRODUCT(($I$12:$AF$12="Plan")*($I$11:$AF$11>$B$5)*(I52:AF52))/1000000)} | H52: =SUMIF($I$12:$AF$12,"Actual",I52:AF52)/1000000 | I52: =SUMIF(Table4[Workstream],'$ Dashboard'!B52,Table4[Jan_2026_F])+SUMIF(Table46[Workstream],'$ Dashboard'!B52,Table46[Jan_26_F]) | AH52: =SUM(AW52:BG52)/1000000 | AI52: =SUMIF($AJ$12:$BG$12,"Actual",AJ52:BG52)/1000000 | CD52: =SUM(CE52:DB52)/1000000
B53: Resource + Non-Resource | D53: =SUM(D30,D77) | E53: =SUM(E30,E77,E48) | G53: =SUM(G30,G77,G48) | H53: =SUM(H30,H77,H48) | I53: =SUM(I30,I77) | J53: =SUM(J30,J77) | K53: =SUM(K30,K77) | L53: =SUM(L30,L77) | M53: =SUM(M30,M77) | N53: =SUM(N30,N77) | O53: =SUM(O30,O77) | P53: =SUM(P30,P77) | ... AF53: =SUM(AF30,AF77) | AH53: =SUM(AH30,AH52) | AI53: =SUM(AI30,AI52) | AJ53: =SUM(AJ30,AJ52) | AK53: =SUM(AK30,AK52) | AL53: =SUM(AL30,AL52) | AM53: =SUM(AM30,AM52) | AN53: =SUM(AN30,AN52) | AO53: =SUM(AO30,AO52) | ... BG53: =SUM(BG30,BG52) | CD53: =SUM(CE53:DB53)/1000000 | CE53: =SUM(CE30,CE52) | CF53: =SUM(CF30,CF52) | CG53: =SUM(CG30,CG52) | CH53: =SUM(CH30,CH52) | CI53: =SUM(CI30,CI52) | CJ53: =SUM(CJ30,CJ52) | CK53: =SUM(CK30,CK52) | CL53: =SUM(CL30,CL52) | ... DB53: =SUM(DB30,DB52)
D59: [2026 - 2027] | G59: [2026] | AH59: [2027]
B60: Non-Resource Cost by cost type | D60: Program LE | E60: Program YTD Actual | G60: LE | H60: Actual | I60: 46023 | K60: 46054 | M60: 46082 | O60: 46113 | Q60: 46143 | S60: 46174 | U60: 46204 | W60: 46235 | Y60: 46266 | AA60: 46296 | AC60: 46327 | AE60: 46357 | AH60: LE | AI60: Actual | AJ60: 46388 | AL60: 46419 | AN60: 46447 | AP60: 46478 | AR60: 46508 | AT60: 46539 | AV60: 46569 | AX60: 46600 | AZ60: 46631 | BB60: 46661 | BD60: 46692 | BF60: 46722 | CD60: GIP | CE60: 46023 | CF60: 46054 | CG60: 46082 | CH60: 46113 | CI60: 46143 | CJ60: 46174 | CK60: 46204 | CL60: 46235 | CM60: 46266 | CN60: 46296 | CO60: 46327 | CP60: 46357 | CQ60: 46388 | CR60: 46419 | CS60: 46447 | CT60: 46478 | CU60: 46508 | CV60: 46539 | CW60: 46569 | CX60: 46600 | CY60: 46631 | CZ60: 46661 | DA60: 46692 | DB60: 46722
I61: Plan | J61: Actual | K61: Plan | L61: Actual | M61: Plan | N61: Actual | O61: Plan | P61: Actual | Q61: Plan | R61: Actual | S61: Plan | T61: Actual | U61: Plan | V61: Actual | W61: Plan | X61: Actual | Y61: Plan | Z61: Actual | AA61: Plan | AB61: Actual | AC61: Plan | AD61: Actual | AE61: Plan | AF61: Actual | AJ61: Plan | AK61: =IF(AJ60<=$B$5,"Actual","") | AL61: Plan | AM61: =IF(AL60<=$B$5,"Actual","") | AN61: Plan | AO61: =IF(AN60<=$B$5,"Actual","") | AP61: Plan | AQ61: =IF(AP60<=$B$5,"Actual","") | AR61: Plan | AS61: =IF(AR60<=$B$5,"Actual","") | AT61: Plan | AU61: =IF(AT60<=$B$5,"Actual","") | AV61: Plan | AW61: =IF(AV60<=$B$5,"Actual","") | AX61: Plan | AY61: =IF(AX60<=$B$5,"Actual","") | AZ61: Plan | BA61: =IF(AZ60<=$B$5,"Actual","") | BB61: Plan | BC61: =IF(BB60<=$B$5,"Actual","") | BD61: Plan | BE61: =IF(BD60<=$B$5,"Actual","") | BF61: Plan | BG61: =IF(BF60<=$B$5,"Actual","")
B62: Travel Costs | D62: =SUM(G62,AH62) | E62: =SUM(H62,AI62) | G62: =SUMIF($I$12:$AF$12,"Plan",I62:AF62)/1000000 | H62: =SUMIF($I$12:$AF$12,"Actual",I62:AF62)/1000000 | I62: =SUMIF(Table46[Cost type],'$ Dashboard'!B62,Table46[Jan_26_F]) | J62: =SUMIF(Table46[Cost type],'$ Dashboard'!B13,Table46[Jan_26_Act]) | K62: =SUMIF(Table46[Cost type],'$ Dashboard'!B62,Table46[Feb_26_F]) | L62: =SUMIF(Table46[Cost type],'$ Dashboard'!B13,Table46[Feb_26_A]) | M62: =SUMIF(Table46[Cost type],'$ Dashboard'!B62,Table46[Mar_26_F]) | N62: =SUMIF(Table46[Cost type],'$ Dashboard'!B13,Table46[Mar_26_A]) | O62: =SUMIF(Table46[Cost type],'$ Dashboard'!B62,Table46[Apr_26_F]) | P62: =SUMIF(Table46[Cost type],'$ Dashboard'!B13,Table46[Apr_26_A]) | Q62: =SUMIF(Table46[Cost type],'$ Dashboard'!B62,Table46[May_26_F]) | R62: =SUMIF(Table46[Cost type],'$ Dashboard'!B13,Table46[May_26_A]) | S62: =SUMIF(Table46[Cost type],'$ Dashboard'!B62,Table46[Jun_26_F]) | T62: =SUMIF(Table46[Cost type],'$ Dashboard'!B13,Table46[Jun_26_A]) | U62: =SUMIF(Table46[Cost type],'$ Dashboard'!B62,Table46[Jul_26_F]) | V62: =SUMIF(Table46[Cost type],'$ Dashboard'!B13,Table46[Jul_26_A]) | W62: =SUMIF(Table46[Cost type],'$ Dashboard'!B62,Table46[Aug_26_F]) | X62: =SUMIF(Table46[Cost type],'$ Dashboard'!B13,Table46[Aug_26_A]) | Y62: =SUMIF(Table46[Cost type],'$ Dashboard'!B62,Table46[Sep_26_F]) | Z62: =SUMIF(Table46[Cost type],'$ Dashboard'!B13,Table46[Sep_26_A]) | AA62: =SUMIF(Table46[Cost type],'$ Dashboard'!B62,Table46[Oct_26_F]) | AB62: =SUMIF(Table46[Cost type],'$ Dashboard'!B13,Table46[Oct_26_A]) | AC62: =SUMIF(Table46[Cost type],'$ Dashboard'!B62,Table46[Nov_26_F]) | AD62: =SUMIF(Table46[Cost type],'$ Dashboard'!B68,Table46[Nov_26_A]) | AE62: =SUMIF(Table46[Cost type],'$ Dashboard'!B62,Table46[Dec_26_F]) | AF62: =SUMIF(Table46[Cost type],'$ Dashboard'!B68,Table46[Dec_26_A]) | AH62: =SUM(AW62:BG62)/1000000 | AI62: =SUMIF($AJ$12:$BG$12,"Actual",AJ62:BG62)/1000000 | CD62: =SUM(CE62:DB62)/1000000
B63: Staff Payroll Related Costs | D63: =SUM(G63,AH63) | E63: =SUM(H63,AI63) | G63: =SUMIF($I$12:$AF$12,"Plan",I63:AF63)/1000000 | H63: =SUMIF($I$12:$AF$12,"Actual",I63:AF63)/1000000 | I63: =SUMIF(Table46[Cost type],'$ Dashboard'!B63,Table46[Jan_26_F]) | J63: =SUMIF(Table46[Cost type],'$ Dashboard'!B14,Table46[Jan_26_Act]) | K63: =SUMIF(Table46[Cost type],'$ Dashboard'!B63,Table46[Feb_26_F]) | L63: =SUMIF(Table46[Cost type],'$ Dashboard'!B14,Table46[Feb_26_A]) | M63: =SUMIF(Table46[Cost type],'$ Dashboard'!B63,Table46[Mar_26_F]) | N63: =SUMIF(Table46[Cost type],'$ Dashboard'!B14,Table46[Mar_26_A]) | O63: =SUMIF(Table46[Cost type],'$ Dashboard'!B63,Table46[Apr_26_F]) | P63: =SUMIF(Table46[Cost type],'$ Dashboard'!B14,Table46[Apr_26_A]) | Q63: =SUMIF(Table46[Cost type],'$ Dashboard'!B63,Table46[May_26_F]) | R63: =SUMIF(Table46[Cost type],'$ Dashboard'!B14,Table46[May_26_A]) | S63: =SUMIF(Table46[Cost type],'$ Dashboard'!B63,Table46[Jun_26_F]) | T63: =SUMIF(Table46[Cost type],'$ Dashboard'!B14,Table46[Jun_26_A]) | U63: =SUMIF(Table46[Cost type],'$ Dashboard'!B63,Table46[Jul_26_F]) | V63: =SUMIF(Table46[Cost type],'$ Dashboard'!B14,Table46[Jul_26_A]) | W63: =SUMIF(Table46[Cost type],'$ Dashboard'!B63,Table46[Aug_26_F]) | X63: =SUMIF(Table46[Cost type],'$ Dashboard'!B14,Table46[Aug_26_A]) | Y63: =SUMIF(Table46[Cost type],'$ Dashboard'!B63,Table46[Sep_26_F]) | Z63: =SUMIF(Table46[Cost type],'$ Dashboard'!B14,Table46[Sep_26_A]) | AA63: =SUMIF(Table46[Cost type],'$ Dashboard'!B63,Table46[Oct_26_F]) | AB63: =SUMIF(Table46[Cost type],'$ Dashboard'!B14,Table46[Oct_26_A]) | AC63: =SUMIF(Table46[Cost type],'$ Dashboard'!B63,Table46[Nov_26_F]) | AD63: =SUMIF(Table46[Cost type],'$ Dashboard'!B69,Table46[Nov_26_A]) | AE63: =SUMIF(Table46[Cost type],'$ Dashboard'!B63,Table46[Dec_26_F]) | AF63: =SUMIF(Table46[Cost type],'$ Dashboard'!B69,Table46[Dec_26_A]) | AH63: =SUM(AW63:BG63)/1000000 | AI63: =SUMIF($AJ$12:$BG$12,"Actual",AJ63:BG63)/1000000 | CD63: =SUM(CE63:DB63)/1000000
B64: Non-payroll related training costs | D64: =SUM(G64,AH64) | E64: =SUM(H64,AI64) | G64: =SUMIF($I$12:$AF$12,"Plan",I64:AF64)/1000000 | H64: =SUMIF($I$12:$AF$12,"Actual",I64:AF64)/1000000 | I64: =SUMIF(Table46[Cost type],'$ Dashboard'!B64,Table46[Jan_26_F]) | J64: =SUMIF(Table46[Cost type],'$ Dashboard'!B15,Table46[Jan_26_Act]) | K64: =SUMIF(Table46[Cost type],'$ Dashboard'!B64,Table46[Feb_26_F]) | L64: =SUMIF(Table46[Cost type],'$ Dashboard'!B15,Table46[Feb_26_A]) | M64: =SUMIF(Table46[Cost type],'$ Dashboard'!B64,Table46[Mar_26_F]) | N64: =SUMIF(Table46[Cost type],'$ Dashboard'!B15,Table46[Mar_26_A]) | O64: =SUMIF(Table46[Cost type],'$ Dashboard'!B64,Table46[Apr_26_F]) | P64: =SUMIF(Table46[Cost type],'$ Dashboard'!B15,Table46[Apr_26_A]) | Q64: =SUMIF(Table46[Cost type],'$ Dashboard'!B64,Table46[May_26_F]) | R64: =SUMIF(Table46[Cost type],'$ Dashboard'!B15,Table46[May_26_A]) | S64: =SUMIF(Table46[Cost type],'$ Dashboard'!B64,Table46[Jun_26_F]) | T64: =SUMIF(Table46[Cost type],'$ Dashboard'!B15,Table46[Jun_26_A]) | U64: =SUMIF(Table46[Cost type],'$ Dashboard'!B64,Table46[Jul_26_F]) | V64: =SUMIF(Table46[Cost type],'$ Dashboard'!B15,Table46[Jul_26_A]) | W64: =SUMIF(Table46[Cost type],'$ Dashboard'!B64,Table46[Aug_26_F]) | X64: =SUMIF(Table46[Cost type],'$ Dashboard'!B15,Table46[Aug_26_A]) | Y64: =SUMIF(Table46[Cost type],'$ Dashboard'!B64,Table46[Sep_26_F]) | Z64: =SUMIF(Table46[Cost type],'$ Dashboard'!B15,Table46[Sep_26_A]) | AA64: =SUMIF(Table46[Cost type],'$ Dashboard'!B64,Table46[Oct_26_F]) | AB64: =SUMIF(Table46[Cost type],'$ Dashboard'!B15,Table46[Oct_26_A]) | AC64: =SUMIF(Table46[Cost type],'$ Dashboard'!B64,Table46[Nov_26_F]) | AD64: =SUMIF(Table46[Cost type],'$ Dashboard'!B70,Table46[Nov_26_A]) | AE64: =SUMIF(Table46[Cost type],'$ Dashboard'!B64,Table46[Dec_26_F]) | AF64: =SUMIF(Table46[Cost type],'$ Dashboard'!B70,Table46[Dec_26_A]) | AH64: =SUM(AW64:BG64)/1000000 | AI64: =SUMIF($AJ$12:$BG$12,"Actual",AJ64:BG64)/1000000 | CD64: =SUM(CE64:DB64)/1000000
B65: Admin costs/Audit/Assurance | D65: =SUM(G65,AH65) | E65: =SUM(H65,AI65) | G65: =SUMIF($I$12:$AF$12,"Plan",I65:AF65)/1000000 | H65: =SUMIF($I$12:$AF$12,"Actual",I65:AF65)/1000000 | I65: =SUMIF(Table46[Cost type],'$ Dashboard'!B65,Table46[Jan_26_F]) | J65: =SUMIF(Table46[Cost type],'$ Dashboard'!B16,Table46[Jan_26_Act]) | K65: =SUMIF(Table46[Cost type],'$ Dashboard'!B65,Table46[Feb_26_F]) | L65: =SUMIF(Table46[Cost type],'$ Dashboard'!B16,Table46[Feb_26_A]) | M65: =SUMIF(Table46[Cost type],'$ Dashboard'!B65,Table46[Mar_26_F]) | N65: =SUMIF(Table46[Cost type],'$ Dashboard'!B16,Table46[Mar_26_A]) | O65: =SUMIF(Table46[Cost type],'$ Dashboard'!B65,Table46[Apr_26_F]) | P65: =SUMIF(Table46[Cost type],'$ Dashboard'!B16,Table46[Apr_26_A]) | Q65: =SUMIF(Table46[Cost type],'$ Dashboard'!B65,Table46[May_26_F]) | R65: =SUMIF(Table46[Cost type],'$ Dashboard'!B16,Table46[May_26_A]) | S65: =SUMIF(Table46[Cost type],'$ Dashboard'!B65,Table46[Jun_26_F]) | T65: =SUMIF(Table46[Cost type],'$ Dashboard'!B16,Table46[Jun_26_A]) | U65: =SUMIF(Table46[Cost type],'$ Dashboard'!B65,Table46[Jul_26_F]) | V65: =SUMIF(Table46[Cost type],'$ Dashboard'!B16,Table46[Jul_26_A]) | W65: =SUMIF(Table46[Cost type],'$ Dashboard'!B65,Table46[Aug_26_F]) | X65: =SUMIF(Table46[Cost type],'$ Dashboard'!B16,Table46[Aug_26_A]) | Y65: =SUMIF(Table46[Cost type],'$ Dashboard'!B65,Table46[Sep_26_F]) | Z65: =SUMIF(Table46[Cost type],'$ Dashboard'!B16,Table46[Sep_26_A]) | AA65: =SUMIF(Table46[Cost type],'$ Dashboard'!B65,Table46[Oct_26_F]) | AB65: =SUMIF(Table46[Cost type],'$ Dashboard'!B16,Table46[Oct_26_A]) | AC65: =SUMIF(Table46[Cost type],'$ Dashboard'!B65,Table46[Nov_26_F]) | AD65: =SUMIF(Table46[Cost type],'$ Dashboard'!B71,Table46[Nov_26_A]) | AE65: =SUMIF(Table46[Cost type],'$ Dashboard'!B65,Table46[Dec_26_F]) | AF65: =SUMIF(Table46[Cost type],'$ Dashboard'!B71,Table46[Dec_26_A]) | AH65: =SUM(AW65:BG65)/1000000 | AI65: =SUMIF($AJ$12:$BG$12,"Actual",AJ65:BG65)/1000000 | CD65: =SUM(CE65:DB65)/1000000
B66: Software Licensing Purchsing including Azure | D66: =SUM(G66,AH66) | E66: =SUM(H66,AI66) | G66: =SUMIF($I$12:$AF$12,"Plan",I66:AF66)/1000000 | H66: =SUMIF($I$12:$AF$12,"Actual",I66:AF66)/1000000 | I66: =SUMIF(Table46[Cost type],'$ Dashboard'!B66,Table46[Jan_26_F]) | J66: =SUMIF(Table46[Cost type],'$ Dashboard'!B17,Table46[Jan_26_Act]) | K66: =SUMIF(Table46[Cost type],'$ Dashboard'!B66,Table46[Feb_26_F]) | L66: =SUMIF(Table46[Cost type],'$ Dashboard'!B17,Table46[Feb_26_A]) | M66: =SUMIF(Table46[Cost type],'$ Dashboard'!B66,Table46[Mar_26_F]) | N66: =SUMIF(Table46[Cost type],'$ Dashboard'!B17,Table46[Mar_26_A]) | O66: =SUMIF(Table46[Cost type],'$ Dashboard'!B66,Table46[Apr_26_F]) | P66: =SUMIF(Table46[Cost type],'$ Dashboard'!B17,Table46[Apr_26_A]) | Q66: =SUMIF(Table46[Cost type],'$ Dashboard'!B66,Table46[May_26_F]) | R66: =SUMIF(Table46[Cost type],'$ Dashboard'!B17,Table46[May_26_A]) | S66: =SUMIF(Table46[Cost type],'$ Dashboard'!B66,Table46[Jun_26_F]) | T66: =SUMIF(Table46[Cost type],'$ Dashboard'!B17,Table46[Jun_26_A]) | U66: =SUMIF(Table46[Cost type],'$ Dashboard'!B66,Table46[Jul_26_F]) | V66: =SUMIF(Table46[Cost type],'$ Dashboard'!B17,Table46[Jul_26_A]) | W66: =SUMIF(Table46[Cost type],'$ Dashboard'!B66,Table46[Aug_26_F]) | X66: =SUMIF(Table46[Cost type],'$ Dashboard'!B17,Table46[Aug_26_A]) | Y66: =SUMIF(Table46[Cost type],'$ Dashboard'!B66,Table46[Sep_26_F]) | Z66: =SUMIF(Table46[Cost type],'$ Dashboard'!B17,Table46[Sep_26_A]) | AA66: =SUMIF(Table46[Cost type],'$ Dashboard'!B66,Table46[Oct_26_F]) | AB66: =SUMIF(Table46[Cost type],'$ Dashboard'!B17,Table46[Oct_26_A]) | AC66: =SUMIF(Table46[Cost type],'$ Dashboard'!B66,Table46[Nov_26_F]) | AD66: =SUMIF(Table46[Cost type],'$ Dashboard'!B72,Table46[Nov_26_A]) | AE66: =SUMIF(Table46[Cost type],'$ Dashboard'!B66,Table46[Dec_26_F]) | AF66: =SUMIF(Table46[Cost type],'$ Dashboard'!B72,Table46[Dec_26_A]) | AH66: =SUM(AW66:BG66)/1000000 | AI66: =SUMIF($AJ$12:$BG$12,"Actual",AJ66:BG66)/1000000 | CD66: =SUM(CE66:DB66)/1000000
D67: =SUM(G67,AH67) | E67: =SUM(H67,AI67) | G67: =SUMIF($I$12:$AF$12,"Plan",I67:AF67)/1000000 | H67: =SUMIF($I$12:$AF$12,"Actual",I67:AF67)/1000000 | I67: =SUMIF(Table46[Cost type],'$ Dashboard'!B67,Table46[Jan_26_F]) | J67: =SUMIF(Table46[Cost type],'$ Dashboard'!B18,Table46[Jan_26_Act]) | K67: =SUMIF(Table46[Cost type],'$ Dashboard'!B67,Table46[Feb_26_F]) | L67: =SUMIF(Table46[Cost type],'$ Dashboard'!B18,Table46[Feb_26_A]) | M67: =SUMIF(Table46[Cost type],'$ Dashboard'!B67,Table46[Mar_26_F]) | N67: =SUMIF(Table46[Cost type],'$ Dashboard'!B18,Table46[Mar_26_A]) | O67: =SUMIF(Table46[Cost type],'$ Dashboard'!B67,Table46[Apr_26_F]) | P67: =SUMIF(Table46[Cost type],'$ Dashboard'!B18,Table46[Apr_26_A]) | Q67: =SUMIF(Table46[Cost type],'$ Dashboard'!B67,Table46[May_26_F]) | R67: =SUMIF(Table46[Cost type],'$ Dashboard'!B18,Table46[May_26_A]) | S67: =SUMIF(Table46[Cost type],'$ Dashboard'!B67,Table46[Jun_26_F]) | T67: =SUMIF(Table46[Cost type],'$ Dashboard'!B18,Table46[Jun_26_A]) | U67: =SUMIF(Table46[Cost type],'$ Dashboard'!B67,Table46[Jul_26_F]) | V67: =SUMIF(Table46[Cost type],'$ Dashboard'!B18,Table46[Jul_26_A]) | W67: =SUMIF(Table46[Cost type],'$ Dashboard'!B67,Table46[Aug_26_F]) | X67: =SUMIF(Table46[Cost type],'$ Dashboard'!B18,Table46[Aug_26_A]) | Y67: =SUMIF(Table46[Cost type],'$ Dashboard'!B67,Table46[Sep_26_F]) | Z67: =SUMIF(Table46[Cost type],'$ Dashboard'!B18,Table46[Sep_26_A]) | AA67: =SUMIF(Table46[Cost type],'$ Dashboard'!B67,Table46[Oct_26_F]) | AB67: =SUMIF(Table46[Cost type],'$ Dashboard'!B18,Table46[Oct_26_A]) | AC67: =SUMIF(Table46[Cost type],'$ Dashboard'!B67,Table46[Nov_26_F]) | AD67: =SUMIF(Table46[Cost type],'$ Dashboard'!B73,Table46[Nov_26_A]) | AE67: =SUMIF(Table46[Cost type],'$ Dashboard'!B67,Table46[Dec_26_F]) | AF67: =SUMIF(Table46[Cost type],'$ Dashboard'!B73,Table46[Dec_26_A]) | AH67: =SUM(AW67:BG67)/1000000 | AI67: =SUMIF($AJ$12:$BG$12,"Actual",AJ67:BG67)/1000000 | CD67: =SUM(CE67:DB67)/1000000
D68: =SUM(G68,AH68) | E68: =SUM(H68,AI68) | G68: =SUMIF($I$12:$AF$12,"Plan",I68:AF68)/1000000 | H68: =SUMIF($I$12:$AF$12,"Actual",I68:AF68)/1000000 | I68: =SUMIF(Table46[Cost type],'$ Dashboard'!B68,Table46[Jan_26_F]) | J68: =SUMIF(Table46[Cost type],'$ Dashboard'!B19,Table46[Jan_26_Act]) | K68: =SUMIF(Table46[Cost type],'$ Dashboard'!B68,Table46[Feb_26_F]) | L68: =SUMIF(Table46[Cost type],'$ Dashboard'!B19,Table46[Feb_26_A]) | M68: =SUMIF(Table46[Cost type],'$ Dashboard'!B68,Table46[Mar_26_F]) | N68: =SUMIF(Table46[Cost type],'$ Dashboard'!B19,Table46[Mar_26_A]) | O68: =SUMIF(Table46[Cost type],'$ Dashboard'!B68,Table46[Apr_26_F]) | P68: =SUMIF(Table46[Cost type],'$ Dashboard'!B19,Table46[Apr_26_A]) | Q68: =SUMIF(Table46[Cost type],'$ Dashboard'!B68,Table46[May_26_F]) | R68: =SUMIF(Table46[Cost type],'$ Dashboard'!B19,Table46[May_26_A]) | S68: =SUMIF(Table46[Cost type],'$ Dashboard'!B68,Table46[Jun_26_F]) | T68: =SUMIF(Table46[Cost type],'$ Dashboard'!B19,Table46[Jun_26_A]) | U68: =SUMIF(Table46[Cost type],'$ Dashboard'!B68,Table46[Jul_26_F]) | V68: =SUMIF(Table46[Cost type],'$ Dashboard'!B19,Table46[Jul_26_A]) | W68: =SUMIF(Table46[Cost type],'$ Dashboard'!B68,Table46[Aug_26_F]) | X68: =SUMIF(Table46[Cost type],'$ Dashboard'!B19,Table46[Aug_26_A]) | Y68: =SUMIF(Table46[Cost type],'$ Dashboard'!B68,Table46[Sep_26_F]) | Z68: =SUMIF(Table46[Cost type],'$ Dashboard'!B19,Table46[Sep_26_A]) | AA68: =SUMIF(Table46[Cost type],'$ Dashboard'!B68,Table46[Oct_26_F]) | AB68: =SUMIF(Table46[Cost type],'$ Dashboard'!B19,Table46[Oct_26_A]) | AC68: =SUMIF(Table46[Cost type],'$ Dashboard'!B68,Table46[Nov_26_F]) | AD68: =SUMIF(Table46[Cost type],'$ Dashboard'!B74,Table46[Nov_26_A]) | AE68: =SUMIF(Table46[Cost type],'$ Dashboard'!B68,Table46[Dec_26_F]) | AF68: =SUMIF(Table46[Cost type],'$ Dashboard'!B74,Table46[Dec_26_A]) | AH68: =SUM(AW68:BG68)/1000000 | AI68: =SUMIF($AJ$12:$BG$12,"Actual",AJ68:BG68)/1000000 | CD68: =SUM(CE68:DB68)/1000000
D69: =SUM(G69,AH69) | E69: =SUM(H69,AI69) | G69: =SUMIF($I$12:$AF$12,"Plan",I69:AF69)/1000000 | H69: =SUMIF($I$12:$AF$12,"Actual",I69:AF69)/1000000 | I69: =SUMIF(Table46[Cost type],'$ Dashboard'!B69,Table46[Jan_26_F]) | J69: =SUMIF(Table46[Cost type],'$ Dashboard'!B20,Table46[Jan_26_Act]) | K69: =SUMIF(Table46[Cost type],'$ Dashboard'!B69,Table46[Feb_26_F]) | L69: =SUMIF(Table46[Cost type],'$ Dashboard'!B20,Table46[Feb_26_A]) | M69: =SUMIF(Table46[Cost type],'$ Dashboard'!B69,Table46[Mar_26_F]) | N69: =SUMIF(Table46[Cost type],'$ Dashboard'!B20,Table46[Mar_26_A]) | O69: =SUMIF(Table46[Cost type],'$ Dashboard'!B69,Table46[Apr_26_F]) | P69: =SUMIF(Table46[Cost type],'$ Dashboard'!B20,Table46[Apr_26_A]) | Q69: =SUMIF(Table46[Cost type],'$ Dashboard'!B69,Table46[May_26_F]) | R69: =SUMIF(Table46[Cost type],'$ Dashboard'!B20,Table46[May_26_A]) | S69: =SUMIF(Table46[Cost type],'$ Dashboard'!B69,Table46[Jun_26_F]) | T69: =SUMIF(Table46[Cost type],'$ Dashboard'!B20,Table46[Jun_26_A]) | U69: =SUMIF(Table46[Cost type],'$ Dashboard'!B69,Table46[Jul_26_F]) | V69: =SUMIF(Table46[Cost type],'$ Dashboard'!B20,Table46[Jul_26_A]) | W69: =SUMIF(Table46[Cost type],'$ Dashboard'!B69,Table46[Aug_26_F]) | X69: =SUMIF(Table46[Cost type],'$ Dashboard'!B20,Table46[Aug_26_A]) | Y69: =SUMIF(Table46[Cost type],'$ Dashboard'!B69,Table46[Sep_26_F]) | Z69: =SUMIF(Table46[Cost type],'$ Dashboard'!B20,Table46[Sep_26_A]) | AA69: =SUMIF(Table46[Cost type],'$ Dashboard'!B69,Table46[Oct_26_F]) | AB69: =SUMIF(Table46[Cost type],'$ Dashboard'!B20,Table46[Oct_26_A]) | AC69: =SUMIF(Table46[Cost type],'$ Dashboard'!B69,Table46[Nov_26_F]) | AD69: =SUMIF(Table46[Cost type],'$ Dashboard'!B75,Table46[Nov_26_A]) | AE69: =SUMIF(Table46[Cost type],'$ Dashboard'!B69,Table46[Dec_26_F]) | AF69: =SUMIF(Table46[Cost type],'$ Dashboard'!B75,Table46[Dec_26_A]) | AH69: =SUM(AW69:BG69)/1000000 | AI69: =SUMIF($AJ$12:$BG$12,"Actual",AJ69:BG69)/1000000 | CD69: =SUM(CE69:DB69)/1000000
D70: =SUM(G70,AH70) | E70: =SUM(H70,AI70) | G70: =SUMIF($I$12:$AF$12,"Plan",I70:AF70)/1000000 | H70: =SUMIF($I$12:$AF$12,"Actual",I70:AF70)/1000000 | I70: =SUMIF(Table46[Cost type],'$ Dashboard'!B70,Table46[Jan_26_F]) | J70: =SUMIF(Table46[Cost type],'$ Dashboard'!B21,Table46[Jan_26_Act]) | K70: =SUMIF(Table46[Cost type],'$ Dashboard'!B70,Table46[Feb_26_F]) | L70: =SUMIF(Table46[Cost type],'$ Dashboard'!B21,Table46[Feb_26_A]) | M70: =SUMIF(Table46[Cost type],'$ Dashboard'!B70,Table46[Mar_26_F]) | N70: =SUMIF(Table46[Cost type],'$ Dashboard'!B21,Table46[Mar_26_A]) | O70: =SUMIF(Table46[Cost type],'$ Dashboard'!B70,Table46[Apr_26_F]) | P70: =SUMIF(Table46[Cost type],'$ Dashboard'!B21,Table46[Apr_26_A]) | Q70: =SUMIF(Table46[Cost type],'$ Dashboard'!B70,Table46[May_26_F]) | R70: =SUMIF(Table46[Cost type],'$ Dashboard'!B21,Table46[May_26_A]) | S70: =SUMIF(Table46[Cost type],'$ Dashboard'!B70,Table46[Jun_26_F]) | T70: =SUMIF(Table46[Cost type],'$ Dashboard'!B21,Table46[Jun_26_A]) | U70: =SUMIF(Table46[Cost type],'$ Dashboard'!B70,Table46[Jul_26_F]) | V70: =SUMIF(Table46[Cost type],'$ Dashboard'!B21,Table46[Jul_26_A]) | W70: =SUMIF(Table46[Cost type],'$ Dashboard'!B70,Table46[Aug_26_F]) | X70: =SUMIF(Table46[Cost type],'$ Dashboard'!B21,Table46[Aug_26_A]) | Y70: =SUMIF(Table46[Cost type],'$ Dashboard'!B70,Table46[Sep_26_F]) | Z70: =SUMIF(Table46[Cost type],'$ Dashboard'!B21,Table46[Sep_26_A]) | AA70: =SUMIF(Table46[Cost type],'$ Dashboard'!B70,Table46[Oct_26_F]) | AB70: =SUMIF(Table46[Cost type],'$ Dashboard'!B21,Table46[Oct_26_A]) | AC70: =SUMIF(Table46[Cost type],'$ Dashboard'!B70,Table46[Nov_26_F]) | AD70: =SUMIF(Table46[Cost type],'$ Dashboard'!B76,Table46[Nov_26_A]) | AE70: =SUMIF(Table46[Cost type],'$ Dashboard'!B70,Table46[Dec_26_F]) | AF70: =SUMIF(Table46[Cost type],'$ Dashboard'!B76,Table46[Dec_26_A]) | AH70: =SUM(AW70:BG70)/1000000 | AI70: =SUMIF($AJ$12:$BG$12,"Actual",AJ70:BG70)/1000000 | CD70: =SUM(CE70:DB70)/1000000
D71: =SUM(G71,AH71) | E71: =SUM(H71,AI71) | G71: =SUMIF($I$12:$AF$12,"Plan",I71:AF71)/1000000 | H71: =SUMIF($I$12:$AF$12,"Actual",I71:AF71)/1000000 | I71: =SUMIF(Table46[Cost type],'$ Dashboard'!B71,Table46[Jan_26_F]) | J71: =SUMIF(Table46[Cost type],'$ Dashboard'!B22,Table46[Jan_26_Act]) | K71: =SUMIF(Table46[Cost type],'$ Dashboard'!B71,Table46[Feb_26_F]) | L71: =SUMIF(Table46[Cost type],'$ Dashboard'!B22,Table46[Feb_26_A]) | M71: =SUMIF(Table46[Cost type],'$ Dashboard'!B71,Table46[Mar_26_F]) | N71: =SUMIF(Table46[Cost type],'$ Dashboard'!B22,Table46[Mar_26_A]) | O71: =SUMIF(Table46[Cost type],'$ Dashboard'!B71,Table46[Apr_26_F]) | P71: =SUMIF(Table46[Cost type],'$ Dashboard'!B22,Table46[Apr_26_A]) | Q71: =SUMIF(Table46[Cost type],'$ Dashboard'!B71,Table46[May_26_F]) | R71: =SUMIF(Table46[Cost type],'$ Dashboard'!B22,Table46[May_26_A]) | S71: =SUMIF(Table46[Cost type],'$ Dashboard'!B71,Table46[Jun_26_F]) | T71: =SUMIF(Table46[Cost type],'$ Dashboard'!B22,Table46[Jun_26_A]) | U71: =SUMIF(Table46[Cost type],'$ Dashboard'!B71,Table46[Jul_26_F]) | V71: =SUMIF(Table46[Cost type],'$ Dashboard'!B22,Table46[Jul_26_A]) | W71: =SUMIF(Table46[Cost type],'$ Dashboard'!B71,Table46[Aug_26_F]) | X71: =SUMIF(Table46[Cost type],'$ Dashboard'!B22,Table46[Aug_26_A]) | Y71: =SUMIF(Table46[Cost type],'$ Dashboard'!B71,Table46[Sep_26_F]) | Z71: =SUMIF(Table46[Cost type],'$ Dashboard'!B22,Table46[Sep_26_A]) | AA71: =SUMIF(Table46[Cost type],'$ Dashboard'!B71,Table46[Oct_26_F]) | AB71: =SUMIF(Table46[Cost type],'$ Dashboard'!B22,Table46[Oct_26_A]) | AC71: =SUMIF(Table46[Cost type],'$ Dashboard'!B71,Table46[Nov_26_F]) | AD71: =SUMIF(Table46[Cost type],'$ Dashboard'!B77,Table46[Nov_26_A]) | AE71: =SUMIF(Table46[Cost type],'$ Dashboard'!B71,Table46[Dec_26_F]) | AF71: =SUMIF(Table46[Cost type],'$ Dashboard'!B77,Table46[Dec_26_A]) | AH71: =SUM(AW71:BG71)/1000000 | AI71: =SUMIF($AJ$12:$BG$12,"Actual",AJ71:BG71)/1000000 | CD71: =SUM(CE71:DB71)/1000000
D72: =SUM(G72,AH72) | E72: =SUM(H72,AI72) | G72: =SUMIF($I$12:$AF$12,"Plan",I72:AF72)/1000000 | H72: =SUMIF($I$12:$AF$12,"Actual",I72:AF72)/1000000 | I72: =SUMIF(Table46[Cost type],'$ Dashboard'!B72,Table46[Jan_26_F]) | J72: =SUMIF(Table46[Cost type],'$ Dashboard'!B23,Table46[Jan_26_Act]) | K72: =SUMIF(Table46[Cost type],'$ Dashboard'!B72,Table46[Feb_26_F]) | L72: =SUMIF(Table46[Cost type],'$ Dashboard'!B23,Table46[Feb_26_A]) | M72: =SUMIF(Table46[Cost type],'$ Dashboard'!B72,Table46[Mar_26_F]) | N72: =SUMIF(Table46[Cost type],'$ Dashboard'!B23,Table46[Mar_26_A]) | O72: =SUMIF(Table46[Cost type],'$ Dashboard'!B72,Table46[Apr_26_F]) | P72: =SUMIF(Table46[Cost type],'$ Dashboard'!B23,Table46[Apr_26_A]) | Q72: =SUMIF(Table46[Cost type],'$ Dashboard'!B72,Table46[May_26_F]) | R72: =SUMIF(Table46[Cost type],'$ Dashboard'!B23,Table46[May_26_A]) | S72: =SUMIF(Table46[Cost type],'$ Dashboard'!B72,Table46[Jun_26_F]) | T72: =SUMIF(Table46[Cost type],'$ Dashboard'!B23,Table46[Jun_26_A]) | U72: =SUMIF(Table46[Cost type],'$ Dashboard'!B72,Table46[Jul_26_F]) | V72: =SUMIF(Table46[Cost type],'$ Dashboard'!B23,Table46[Jul_26_A]) | W72: =SUMIF(Table46[Cost type],'$ Dashboard'!B72,Table46[Aug_26_F]) | X72: =SUMIF(Table46[Cost type],'$ Dashboard'!B23,Table46[Aug_26_A]) | Y72: =SUMIF(Table46[Cost type],'$ Dashboard'!B72,Table46[Sep_26_F]) | Z72: =SUMIF(Table46[Cost type],'$ Dashboard'!B23,Table46[Sep_26_A]) | AA72: =SUMIF(Table46[Cost type],'$ Dashboard'!B72,Table46[Oct_26_F]) | AB72: =SUMIF(Table46[Cost type],'$ Dashboard'!B23,Table46[Oct_26_A]) | AC72: =SUMIF(Table46[Cost type],'$ Dashboard'!B72,Table46[Nov_26_F]) | AD72: =SUMIF(Table46[Cost type],'$ Dashboard'!B78,Table46[Nov_26_A]) | AE72: =SUMIF(Table46[Cost type],'$ Dashboard'!B72,Table46[Dec_26_F]) | AF72: =SUMIF(Table46[Cost type],'$ Dashboard'!B78,Table46[Dec_26_A]) | AH72: =SUM(AW72:BG72)/1000000 | AI72: =SUMIF($AJ$12:$BG$12,"Actual",AJ72:BG72)/1000000 | CD72: =SUM(CE72:DB72)/1000000
D73: =SUM(G73,AH73) | E73: =SUM(H73,AI73) | G73: =SUMIF($I$12:$AF$12,"Plan",I73:AF73)/1000000 | H73: =SUMIF($I$12:$AF$12,"Actual",I73:AF73)/1000000 | I73: =SUMIF(Table46[Cost type],'$ Dashboard'!B73,Table46[Jan_26_F]) | J73: =SUMIF(Table46[Cost type],'$ Dashboard'!B26,Table46[Jan_26_Act]) | K73: =SUMIF(Table46[Cost type],'$ Dashboard'!B73,Table46[Feb_26_F]) | L73: =SUMIF(Table46[Cost type],'$ Dashboard'!B26,Table46[Feb_26_A]) | M73: =SUMIF(Table46[Cost type],'$ Dashboard'!B73,Table46[Mar_26_F]) | N73: =SUMIF(Table46[Cost type],'$ Dashboard'!B26,Table46[Mar_26_A]) | O73: =SUMIF(Table46[Cost type],'$ Dashboard'!B73,Table46[Apr_26_F]) | P73: =SUMIF(Table46[Cost type],'$ Dashboard'!B26,Table46[Apr_26_A]) | Q73: =SUMIF(Table46[Cost type],'$ Dashboard'!B73,Table46[May_26_F]) | R73: =SUMIF(Table46[Cost type],'$ Dashboard'!B26,Table46[May_26_A]) | S73: =SUMIF(Table46[Cost type],'$ Dashboard'!B73,Table46[Jun_26_F]) | T73: =SUMIF(Table46[Cost type],'$ Dashboard'!B26,Table46[Jun_26_A]) | U73: =SUMIF(Table46[Cost type],'$ Dashboard'!B73,Table46[Jul_26_F]) | V73: =SUMIF(Table46[Cost type],'$ Dashboard'!B26,Table46[Jul_26_A]) | W73: =SUMIF(Table46[Cost type],'$ Dashboard'!B73,Table46[Aug_26_F]) | X73: =SUMIF(Table46[Cost type],'$ Dashboard'!B26,Table46[Aug_26_A]) | Y73: =SUMIF(Table46[Cost type],'$ Dashboard'!B73,Table46[Sep_26_F]) | Z73: =SUMIF(Table46[Cost type],'$ Dashboard'!B26,Table46[Sep_26_A]) | AA73: =SUMIF(Table46[Cost type],'$ Dashboard'!B73,Table46[Oct_26_F]) | AB73: =SUMIF(Table46[Cost type],'$ Dashboard'!B26,Table46[Oct_26_A]) | AC73: =SUMIF(Table46[Cost type],'$ Dashboard'!B73,Table46[Nov_26_F]) | AD73: =SUMIF(Table46[Cost type],'$ Dashboard'!B79,Table46[Nov_26_A]) | AE73: =SUMIF(Table46[Cost type],'$ Dashboard'!B73,Table46[Dec_26_F]) | AF73: =SUMIF(Table46[Cost type],'$ Dashboard'!B79,Table46[Dec_26_A]) | AH73: =SUM(AW73:BG73)/1000000 | AI73: =SUMIF($AJ$12:$BG$12,"Actual",AJ73:BG73)/1000000 | CD73: =SUM(CE73:DB73)/1000000
D74: =SUM(G74,AH74) | E74: =SUM(H74,AI74) | G74: =SUMIF($I$12:$AF$12,"Plan",I74:AF74)/1000000 | H74: =SUMIF($I$12:$AF$12,"Actual",I74:AF74)/1000000 | I74: =SUMIF(Table46[Cost type],'$ Dashboard'!B74,Table46[Jan_26_F]) | J74: =SUMIF(Table46[Cost type],'$ Dashboard'!B27,Table46[Jan_26_Act]) | K74: =SUMIF(Table46[Cost type],'$ Dashboard'!B74,Table46[Feb_26_F]) | L74: =SUMIF(Table46[Cost type],'$ Dashboard'!B27,Table46[Feb_26_A]) | M74: =SUMIF(Table46[Cost type],'$ Dashboard'!B74,Table46[Mar_26_F]) | N74: =SUMIF(Table46[Cost type],'$ Dashboard'!B27,Table46[Mar_26_A]) | O74: =SUMIF(Table46[Cost type],'$ Dashboard'!B74,Table46[Apr_26_F]) | P74: =SUMIF(Table46[Cost type],'$ Dashboard'!B27,Table46[Apr_26_A]) | Q74: =SUMIF(Table46[Cost type],'$ Dashboard'!B74,Table46[May_26_F]) | R74: =SUMIF(Table46[Cost type],'$ Dashboard'!B27,Table46[May_26_A]) | S74: =SUMIF(Table46[Cost type],'$ Dashboard'!B74,Table46[Jun_26_F]) | T74: =SUMIF(Table46[Cost type],'$ Dashboard'!B27,Table46[Jun_26_A]) | U74: =SUMIF(Table46[Cost type],'$ Dashboard'!B74,Table46[Jul_26_F]) | V74: =SUMIF(Table46[Cost type],'$ Dashboard'!B27,Table46[Jul_26_A]) | W74: =SUMIF(Table46[Cost type],'$ Dashboard'!B74,Table46[Aug_26_F]) | X74: =SUMIF(Table46[Cost type],'$ Dashboard'!B27,Table46[Aug_26_A]) | Y74: =SUMIF(Table46[Cost type],'$ Dashboard'!B74,Table46[Sep_26_F]) | Z74: =SUMIF(Table46[Cost type],'$ Dashboard'!B27,Table46[Sep_26_A]) | AA74: =SUMIF(Table46[Cost type],'$ Dashboard'!B74,Table46[Oct_26_F]) | AB74: =SUMIF(Table46[Cost type],'$ Dashboard'!B27,Table46[Oct_26_A]) | AC74: =SUMIF(Table46[Cost type],'$ Dashboard'!B74,Table46[Nov_26_F]) | AD74: =SUMIF(Table46[Cost type],'$ Dashboard'!B80,Table46[Nov_26_A]) | AE74: =SUMIF(Table46[Cost type],'$ Dashboard'!B74,Table46[Dec_26_F]) | AF74: =SUMIF(Table46[Cost type],'$ Dashboard'!B80,Table46[Dec_26_A]) | AH74: =SUM(AW74:BG74)/1000000 | AI74: =SUMIF($AJ$12:$BG$12,"Actual",AJ74:BG74)/1000000 | CD74: =SUM(CE74:DB74)/1000000
D75: =SUM(G75,AH75) | E75: =SUM(H75,AI75) | G75: =SUMIF($I$12:$AF$12,"Plan",I75:AF75)/1000000 | H75: =SUMIF($I$12:$AF$12,"Actual",I75:AF75)/1000000 | I75: =SUMIF(Table46[Cost type],'$ Dashboard'!B75,Table46[Jan_26_F]) | J75: =SUMIF(Table46[Cost type],'$ Dashboard'!B28,Table46[Jan_26_Act]) | K75: =SUMIF(Table46[Cost type],'$ Dashboard'!B75,Table46[Feb_26_F]) | L75: =SUMIF(Table46[Cost type],'$ Dashboard'!B28,Table46[Feb_26_A]) | M75: =SUMIF(Table46[Cost type],'$ Dashboard'!B75,Table46[Mar_26_F]) | N75: =SUMIF(Table46[Cost type],'$ Dashboard'!B28,Table46[Mar_26_A]) | O75: =SUMIF(Table46[Cost type],'$ Dashboard'!B75,Table46[Apr_26_F]) | P75: =SUMIF(Table46[Cost type],'$ Dashboard'!B28,Table46[Apr_26_A]) | Q75: =SUMIF(Table46[Cost type],'$ Dashboard'!B75,Table46[May_26_F]) | R75: =SUMIF(Table46[Cost type],'$ Dashboard'!B28,Table46[May_26_A]) | S75: =SUMIF(Table46[Cost type],'$ Dashboard'!B75,Table46[Jun_26_F]) | T75: =SUMIF(Table46[Cost type],'$ Dashboard'!B28,Table46[Jun_26_A]) | U75: =SUMIF(Table46[Cost type],'$ Dashboard'!B75,Table46[Jul_26_F]) | V75: =SUMIF(Table46[Cost type],'$ Dashboard'!B28,Table46[Jul_26_A]) | W75: =SUMIF(Table46[Cost type],'$ Dashboard'!B75,Table46[Aug_26_F]) | X75: =SUMIF(Table46[Cost type],'$ Dashboard'!B28,Table46[Aug_26_A]) | Y75: =SUMIF(Table46[Cost type],'$ Dashboard'!B75,Table46[Sep_26_F]) | Z75: =SUMIF(Table46[Cost type],'$ Dashboard'!B28,Table46[Sep_26_A]) | AA75: =SUMIF(Table46[Cost type],'$ Dashboard'!B75,Table46[Oct_26_F]) | AB75: =SUMIF(Table46[Cost type],'$ Dashboard'!B28,Table46[Oct_26_A]) | AC75: =SUMIF(Table46[Cost type],'$ Dashboard'!B75,Table46[Nov_26_F]) | AD75: =SUMIF(Table46[Cost type],'$ Dashboard'!B81,Table46[Nov_26_A]) | AE75: =SUMIF(Table46[Cost type],'$ Dashboard'!B75,Table46[Dec_26_F]) | AF75: =SUMIF(Table46[Cost type],'$ Dashboard'!B81,Table46[Dec_26_A]) | AH75: =SUM(AW75:BG75)/1000000 | AI75: =SUMIF($AJ$12:$BG$12,"Actual",AJ75:BG75)/1000000 | CD75: =SUM(CE75:DB75)/1000000
D76: =SUM(G76,AH76) | E76: =SUM(H76,AI76) | G76: =SUMIF($I$12:$AF$12,"Plan",I76:AF76)/1000000 | H76: =SUMIF($I$12:$AF$12,"Actual",I76:AF76)/1000000 | I76: =SUMIF(Table46[Cost type],'$ Dashboard'!B76,Table46[Jan_26_F]) | J76: =SUMIF(Table46[Cost type],'$ Dashboard'!B29,Table46[Jan_26_Act]) | K76: =SUMIF(Table46[Cost type],'$ Dashboard'!B76,Table46[Feb_26_F]) | L76: =SUMIF(Table46[Cost type],'$ Dashboard'!B29,Table46[Feb_26_A]) | M76: =SUMIF(Table46[Cost type],'$ Dashboard'!B76,Table46[Mar_26_F]) | N76: =SUMIF(Table46[Cost type],'$ Dashboard'!B29,Table46[Mar_26_A]) | O76: =SUMIF(Table46[Cost type],'$ Dashboard'!B76,Table46[Apr_26_F]) | P76: =SUMIF(Table46[Cost type],'$ Dashboard'!B29,Table46[Apr_26_A]) | Q76: =SUMIF(Table46[Cost type],'$ Dashboard'!B76,Table46[May_26_F]) | R76: =SUMIF(Table46[Cost type],'$ Dashboard'!B29,Table46[May_26_A]) | S76: =SUMIF(Table46[Cost type],'$ Dashboard'!B76,Table46[Jun_26_F]) | T76: =SUMIF(Table46[Cost type],'$ Dashboard'!B29,Table46[Jun_26_A]) | U76: =SUMIF(Table46[Cost type],'$ Dashboard'!B76,Table46[Jul_26_F]) | V76: =SUMIF(Table46[Cost type],'$ Dashboard'!B29,Table46[Jul_26_A]) | W76: =SUMIF(Table46[Cost type],'$ Dashboard'!B76,Table46[Aug_26_F]) | X76: =SUMIF(Table46[Cost type],'$ Dashboard'!B29,Table46[Aug_26_A]) | Y76: =SUMIF(Table46[Cost type],'$ Dashboard'!B76,Table46[Sep_26_F]) | Z76: =SUMIF(Table46[Cost type],'$ Dashboard'!B29,Table46[Sep_26_A]) | AA76: =SUMIF(Table46[Cost type],'$ Dashboard'!B76,Table46[Oct_26_F]) | AB76: =SUMIF(Table46[Cost type],'$ Dashboard'!B29,Table46[Oct_26_A]) | AC76: =SUMIF(Table46[Cost type],'$ Dashboard'!B76,Table46[Nov_26_F]) | AD76: =SUMIF(Table46[Cost type],'$ Dashboard'!B82,Table46[Nov_26_A]) | AE76: =SUMIF(Table46[Cost type],'$ Dashboard'!B76,Table46[Dec_26_F]) | AF76: =SUMIF(Table46[Cost type],'$ Dashboard'!B82,Table46[Dec_26_A]) | AH76: =SUM(AW76:BG76)/1000000 | AI76: =SUMIF($AJ$12:$BG$12,"Actual",AJ76:BG76)/1000000 | CD76: =SUM(CE76:DB76)/1000000
B77: Total | D77: =SUM(D62:D75) | E77: =SUM(E62:E75) | G77: =SUM(G62:G76) | H77: =SUM(H62:H76) | I77: =SUM(I62:I76) | J77: =SUM(J62:J76) | K77: =SUM(K62:K76) | L77: =SUM(L62:L76) | M77: =SUM(M62:M76) | N77: =SUM(N62:N76) | ... AF77: =SUM(AF62:AF76) | AH77: =SUM(AH62:AH76) | AI77: =SUM(AI62:AI76) | AJ77: =SUM(AJ62:AJ76) | AK77: =SUM(AK62:AK76) | AL77: =SUM(AL62:AL76) | AM77: =SUM(AM62:AM76) | AN77: =SUM(AN62:AN76) | AO77: =SUM(AO62:AO76) | ... BG77: =SUM(BG62:BG76) | CD77: =SUM(CD62:CD76) | CE77: =SUM(CE62:CE76) | CF77: =SUM(CF62:CF76) | CG77: =SUM(CG62:CG76) | CH77: =SUM(CH62:CH76) | CI77: =SUM(CI62:CI76) | CJ77: =SUM(CJ62:CJ76) | CK77: =SUM(CK62:CK76) | ... DB77: =SUM(DB62:DB76)
J78: =IFERROR(J77/I77,0) | L78: =IFERROR(L77/K77,0) | N78: =IFERROR(N77/M77,0) | P78: =IFERROR(P77/O77,0) | R78: =IFERROR(R77/Q77,0) | T78: =IFERROR(T77/S77,0) | V78: =IFERROR(V77/U77,0) | X78: =IFERROR(X77/W77,0) | Z78: =IFERROR(Z77/Y77,0) | AB78: =IFERROR(AB77/AA77,0) | AD78: =IFERROR(AD77/AC77,0) | AF78: =IFERROR(AF77/AE77,0) | AK78: =IFERROR(AK77/AJ77,0) | AM78: =IFERROR(AM77/AL77,0) | AO78: =IFERROR(AO77/AN77,0) | AQ78: =IFERROR(AQ77/AP77,0) | AS78: =IFERROR(AS77/AR77,0) | AU78: =IFERROR(AU77/AT77,0) | AW78: =IFERROR(AW77/AV77,0) | AY78: =IFERROR(AY77/AX77,0) | BA78: =IFERROR(BA77/AZ77,0) | BC78: =IFERROR(BC77/BB77,0) | BE78: =IFERROR(BE77/BD77,0) | BG78: =IFERROR(BG77/BF77,0)
D79: =SUM(G79,AH79) | E79: =SUM(H79,AI79) | G79: {=SUM(H79,SUMPRODUCT(($I$12:$AF$12="Plan")*($I$11:$AF$11>$B$5)*(I79:AF79))/1000000)} | H79: =SUMIF($I$12:$AF$12,"Actual",I79:AF79)/1000000 | I79: =SUMIF(Table4[Workstream],'$ Dashboard'!B79,Table4[Jan_2026_F])+SUMIF(Table46[Workstream],'$ Dashboard'!B79,Table46[Jan_26_F]) | AH79: =SUM(AW79:BG79)/1000000 | AI79: =SUMIF($AJ$12:$BG$12,"Actual",AJ79:BG79)/1000000 | CD79: =SUM(CE79:DB79)/1000000
B80: Program Total w contingency | D80: =SUM(D77,D79) | E80: =SUM(E77,E79) | G80: =SUM(G77,G79) | H80: =SUM(H77,H79) | I80: =SUM(I77,I79) | J80: =SUM(J77,J79) | K80: =SUM(K77,K79) | L80: =SUM(L77,L79) | M80: =SUM(M77,M79) | N80: =SUM(N77,N79) | ... AF80: =SUM(AF77,AF79) | AH80: =SUM(AH77,AH79) | AI80: =SUM(AI77,AI79) | AJ80: =SUM(AJ77,AJ79) | AK80: =SUM(AK77,AK79) | AL80: =SUM(AL77,AL79) | AM80: =SUM(AM77,AM79) | AN80: =SUM(AN77,AN79) | AO80: =SUM(AO77,AO79) | ... BG80: =SUM(BG77,BG79) | CD80: =SUM(CE80:DB80)/1000000 | CE80: =SUM(CE77,CE79) | CF80: =SUM(CF77,CF79) | CG80: =SUM(CG77,CG79) | CH80: =SUM(CH77,CH79) | CI80: =SUM(CI77,CI79) | CJ80: =SUM(CJ77,CJ79) | CK80: =SUM(CK77,CK79) | CL80: =SUM(CL77,CL79) | ... DB80: =SUM(DB77,DB79)

Sheet Business Manpower LE
AC2: 19
AB3: Hub days [excluding public holidays]
AC4: Service Center days [excluding public holidays]
BC5: 21 | BD5: 20 | BE5: 23 | BF5: 22 | BG5: 21 | BH5: 22 | BI5: 22 | BJ5: 22 | BK5: 22 | BL5: 21 | BM5: 22 | BN5: 23
AP6: =SUM(Table410[Jan_2026_Days_Actual]) | AQ6: =SUM(Table410[Feb_2026_Days_Actual]) | AR6: =SUM(Table410[Mar_2026_Days_Actual]) | AS6: =SUM(Table410[Apr_2026_Days_Actual]) | AT6: =SUM(Table410[May_2026_Days_Actual]) | AU6: =SUM(Table410[Jun_2026_Days_Actual]) | AV6: =SUM(Table410[Jul_2026_Days_Actual]) | AW6: =SUM(Table410[Aug_2026_Days_Actual]) | AX6: =SUM(Table410[Sep_2026_Days_Actual]) | AY6: =SUM(Table410[Oct_2026_Days_Actual]) | AZ6: =SUM(Table410[Nov_2026_Days_Actual]) | BA6: =SUM(Table410[Dec_2026_Days_Actual]) | BC6: =SUM(Table410[Jan_2027_Days_Forecast]) | BD6: =SUM(Table410[Feb_2027_Days_Forecast]) | BE6: =SUM(Table410[Mar_2027_Days_Forecast]) | BF6: =SUM(Table410[Apr_2027_Days_Forecast]) | BG6: =SUM(Table410[May_2027_Days_Forecast]) | BH6: =SUM(Table410[Jun_2027_Days_Forecast]) | BI6: =SUM(Table410[Jul_2027_Days_Forecast]) | BJ6: =SUM(Table410[Aug_2027_Days_Forecast]) | BK6: =SUM(Table410[Sep_2027_Days_Forecast]) | BL6: =SUM(Table410[Oct_2027_Days_Forecast]) | BM6: =SUM(Table410[Nov_2027_Days_Forecast]) | BN6: =SUM(Table410[Dec_2027_Days_Forecast]) | BQ6: =SUM(Table410[Jan_2026_F]) | BR6: =SUM(Table410[Jan_2026_A]) | BS6: =SUM(Table410[Jan_2026_V]) | BU6: =SUM(Table410[Feb_2026_F]) | BV6: =SUM(Table410[Feb_2026_A]) | BW6: =SUM(Table410[Feb_2026_D]) | BY6: =SUM(Table410[Mar_2026_F]) | BZ6: =SUM(Table410[Mar_2026_A]) | CA6: =SUM(Table410[Mar_2026_D]) | CC6: =SUM(Table410[Apr_2026_F]) | CD6: =SUM(Table410[Apr_2026_A]) | CE6: =SUM(Table410[Apr_2026_D]) | CG6: =SUM(Table410[May_2026_F]) | CH6: =SUM(Table410[May_2026_A]) | CI6: =SUM(Table410[May_2026_D]) | CK6: =SUM(Table410[Jun_2026_F]) | CL6: =SUM(Table410[Jun_2026_A]) | CM6: =SUM(Table410[Jun_2026_D]) | CO6: =SUM(Table410[Jul_2026_F]) | CP6: =SUM(Table410[Jul_2026_A]) | CQ6: =SUM(Table410[Jul_2026_D]) | CS6: =SUM(Table410[Aug_2026_F]) | CT6: =SUM(Table410[Aug_2026_A]) | CU6: =SUM(Table410[Aug_2026_D]) | CW6: =SUM(Table410[Sep_2026_F]) | CX6: =SUM(Table410[Sep_2026_A]) | CY6: =SUM(Table410[Sep_2026_D]) | DA6: =SUM(Table410[Oct_2026_F]) | DB6: =SUM(Table410[Oct_2026_A]) | DC6: =SUM(Table410[Oct_2026_D]) | DE6: =SUM(Table410[Nov_2026_F]) | DF6: =SUM(Table410[Nov_2026_A]) | DG6: =SUM(Table410[Nov_2026_D]) | DI6: =SUM(Table410[Dec_2026_F]) | DJ6: =SUM(Table410[Dec_2026_A]) | DK6: =SUM(Table410[Dec_2026_D]) | DN6: =SUM(Table410[Jan_2027_F]) | DO6: =SUM(Table410[Jan_2027_A]) | DP6: =SUM(Table410[Jan_2027_D]) | DQ6: =SUM(Table410[Feb_2027_F]) | DR6: =SUM(Table410[Feb_2027_A]) | DS6: =SUM(Table410[Feb_2027_D]) | DT6: =SUM(Table410[Mar_2027_F]) | DU6: =SUM(Table410[Mar_2027_A]) | DV6: =SUM(Table410[Mar_2027_D]) | DW6: =SUM(Table410[Apr_2027_F]) | DX6: =SUM(Table410[Apr_2027_A]) | DY6: =SUM(Table410[Apr_2027_D]) | DZ6: =SUM(Table410[May_2027_F]) | EA6: =SUM(Table410[May_2027_A]) | EB6: =SUM(Table410[May_2027_D]) | EC6: =SUM(Table410[Jun_2027_F]) | ED6: =SUM(Table410[Jun_2027_A]) | EE6: =SUM(Table410[Jun_2027_D]) | EF6: =SUM(Table410[Jul_2027_F]) | EG6: =SUM(Table410[Jul_2027_A]) | EH6: =SUM(Table410[Jul_2027_D]) | EI6: =SUM(Table410[Aug_2027_F]) | EJ6: =SUM(Table410[Aug_2027_A]) | EK6: =SUM(Table410[Aug_2027_D]) | EL6: =SUM(Table410[Sep_2027_F]) | EM6: =SUM(Table410[Sep_2027_A]) | EN6: =SUM(Table410[Sep_2027_D]) | EO6: =SUM(Table410[Oct_2027_F]) | EP6: =SUM(Table410[Oct_2027_A]) | EQ6: =SUM(Table410[Oct_2027_D]) | ER6: =SUM(Table410[Nov_2027_F]) | ES6: =SUM(Table410[Nov_2027_A]) | ET6: =SUM(Table410[Nov_2027_D]) | EU6: =SUM(Table410[Dec_2027_F]) | EV6: =SUM(Table410[Dec_2027_A]) | EW6: =SUM(Table410[Dec_2027_D])
AP7: =SUBTOTAL(9,Table410[Jan_2026_Days_Actual]) | AQ7: =SUBTOTAL(9,Table410[Feb_2026_Days_Actual]) | AR7: =SUBTOTAL(9,Table410[Mar_2026_Days_Actual]) | AS7: =SUBTOTAL(9,Table410[Apr_2026_Days_Actual]) | AT7: =SUBTOTAL(9,Table410[May_2026_Days_Actual]) | AU7: =SUBTOTAL(9,Table410[Jun_2026_Days_Actual]) | AV7: =SUBTOTAL(9,Table410[Jul_2026_Days_Actual]) | AW7: =SUBTOTAL(9,Table410[Aug_2026_Days_Actual]) | AX7: =SUBTOTAL(9,Table410[Sep_2026_Days_Actual]) | AY7: =SUBTOTAL(9,Table410[Oct_2026_Days_Actual]) | AZ7: =SUBTOTAL(9,Table410[Nov_2026_Days_Actual]) | BA7: =SUBTOTAL(9,Table410[Dec_2026_Days_Actual]) | BC7: =SUBTOTAL(9,Table410[Jan_2027_Days_Forecast]) | BD7: =SUBTOTAL(9,Table410[Feb_2027_Days_Forecast]) | BE7: =SUBTOTAL(9,Table410[Mar_2027_Days_Forecast]) | BF7: =SUBTOTAL(9,Table410[Apr_2027_Days_Forecast]) | BG7: =SUBTOTAL(9,Table410[May_2027_Days_Forecast]) | BH7: =SUBTOTAL(9,Table410[Jun_2027_Days_Forecast]) | BI7: =SUBTOTAL(9,Table410[Jul_2027_Days_Forecast]) | BJ7: =SUBTOTAL(9,Table410[Aug_2027_Days_Forecast]) | BK7: =SUBTOTAL(9,Table410[Sep_2027_Days_Forecast]) | BL7: =SUBTOTAL(9,Table410[Oct_2027_Days_Forecast]) | BM7: =SUBTOTAL(9,Table410[Nov_2027_Days_Forecast]) | BN7: =SUBTOTAL(9,Table410[Dec_2027_Days_Forecast]) | BQ7: =SUBTOTAL(9,Table410[Jan_2026_F]) | BR7: =SUBTOTAL(9,Table410[Jan_2026_A]) | BS7: =SUBTOTAL(9,Table410[Jan_2026_V]) | BU7: =SUBTOTAL(9,Table410[Feb_2026_F]) | BV7: =SUBTOTAL(9,Table410[Feb_2026_A]) | BW7: =SUBTOTAL(9,Table410[Feb_2026_D]) | BY7: =SUBTOTAL(9,Table410[Mar_2026_F]) | BZ7: =SUBTOTAL(9,Table410[Mar_2026_A]) | CA7: =SUBTOTAL(9,Table410[Mar_2026_D]) | CC7: =SUBTOTAL(9,Table410[Apr_2026_F]) | CD7: =SUBTOTAL(9,Table410[Apr_2026_A]) | CE7: =SUBTOTAL(9,Table410[Apr_2026_D]) | CG7: =SUBTOTAL(9,Table410[May_2026_F]) | CH7: =SUBTOTAL(9,Table410[May_2026_A]) | CI7: =SUBTOTAL(9,Table410[May_2026_D]) | CK7: =SUBTOTAL(9,Table410[Jun_2026_F]) | CL7: =SUBTOTAL(9,Table410[Jun_2026_A]) | CM7: =SUBTOTAL(9,Table410[Jun_2026_D]) | CO7: =SUBTOTAL(9,Table410[Jul_2026_F]) | CP7: =SUBTOTAL(9,Table410[Jul_2026_A]) | CQ7: =SUBTOTAL(9,Table410[Jul_2026_D]) | CS7: =SUBTOTAL(9,Table410[Aug_2026_F]) | CT7: =SUBTOTAL(9,Table410[Aug_2026_A]) | CU7: =SUBTOTAL(9,Table410[Aug_2026_D]) | CW7: =SUBTOTAL(9,Table410[Sep_2026_F]) | CX7: =SUBTOTAL(9,Table410[Sep_2026_A]) | CY7: =SUBTOTAL(9,Table410[Sep_2026_D]) | DA7: =SUBTOTAL(9,Table410[Oct_2026_F]) | DB7: =SUBTOTAL(9,Table410[Oct_2026_A]) | DC7: =SUBTOTAL(9,Table410[Oct_2026_D]) | DE7: =SUBTOTAL(9,Table410[Nov_2026_F]) | DF7: =SUBTOTAL(9,Table410[Nov_2026_A]) | DG7: =SUBTOTAL(9,Table410[Nov_2026_D]) | DI7: =SUBTOTAL(9,Table410[Dec_2026_F]) | DJ7: =SUBTOTAL(9,Table410[Dec_2026_A]) | DK7: =SUBTOTAL(9,Table410[Dec_2026_D]) | DN7: =SUBTOTAL(9,Table410[Jan_2027_F]) | DO7: =SUBTOTAL(9,Table410[Jan_2027_A]) | DP7: =SUBTOTAL(9,Table410[Jan_2027_D]) | DQ7: =SUBTOTAL(9,Table410[Feb_2027_F]) | DR7: =SUBTOTAL(9,Table410[Feb_2027_A]) | DS7: =SUBTOTAL(9,Table410[Feb_2027_D]) | DT7: =SUBTOTAL(9,Table410[Mar_2027_F]) | DU7: =SUBTOTAL(9,Table410[Mar_2027_A]) | DV7: =SUBTOTAL(9,Table410[Mar_2027_D]) | DW7: =SUBTOTAL(9,Table410[Apr_2027_F]) | DX7: =SUBTOTAL(9,Table410[Apr_2027_A]) | DY7: =SUBTOTAL(9,Table410[Apr_2027_D]) | DZ7: =SUBTOTAL(9,Table410[May_2027_F]) | EA7: =SUBTOTAL(9,Table410[May_2027_A]) | EB7: =SUBTOTAL(9,Table410[May_2027_D]) | EC7: =SUBTOTAL(9,Table410[Jun_2027_F]) | ED7: =SUBTOTAL(9,Table410[Jun_2027_A]) | EE7: =SUBTOTAL(9,Table410[Jun_2027_D]) | EF7: =SUBTOTAL(9,Table410[Jul_2027_F]) | EG7: =SUBTOTAL(9,Table410[Jul_2027_A]) | EH7: =SUBTOTAL(9,Table410[Jul_2027_D]) | EI7: =SUBTOTAL(9,Table410[Aug_2027_F]) | EJ7: =SUBTOTAL(9,Table410[Aug_2027_A]) | EK7: =SUBTOTAL(9,Table410[Aug_2027_D]) | EL7: =SUBTOTAL(9,Table410[Sep_2027_F]) | EM7: =SUBTOTAL(9,Table410[Sep_2027_A]) | EN7: =SUBTOTAL(9,Table410[Sep_2027_D]) | EO7: =SUBTOTAL(9,Table410[Oct_2027_F]) | EP7: =SUBTOTAL(9,Table410[Oct_2027_A]) | EQ7: =SUBTOTAL(9,Table410[Oct_2027_D]) | ER7: =SUBTOTAL(9,Table410[Nov_2027_F]) | ES7: =SUBTOTAL(9,Table410[Nov_2027_A]) | ET7: =SUBTOTAL(9,Table410[Nov_2027_D]) | EU7: =SUBTOTAL(9,Table410[Dec_2027_F]) | EV7: =SUBTOTAL(9,Table410[Dec_2027_A]) | EW7: =SUBTOTAL(9,Table410[Dec_2027_D])
AB8: 2026 | AP8: 2026 | BC8: 2027 | BQ8: 46047 | BU8: 46078 | BY8: 46106 | CC8: 46137 | CG8: 46167 | CK8: 46198 | CO8: 46228 | CS8: 46259 | CW8: 46290 | DA8: 46320 | DE8: 46351 | DI8: 46381 | DN8: 46412 | DQ8: 46443 | DT8: 46471 | DW8: 46502 | DZ8: 46532 | EC8: 46563 | EF8: 46593 | EI8: 46624 | EL8: 46655 | EO8: 46685 | ER8: 46716 | EU8: 46746
A9: Personal Number | B9: Workstream | C9: Staff Type | D9: Resource Name | E9: Resource Provider | F9: Resource Plan Number | G9: Country | H9: JG | I9: Resource Group / Team | J9: Project Role | K9: Status | L9: Cost Boolean | M9: Location | N9: Capability | O9: OPEX/CAPEX | P9: Tag | Q9: WBSE | R9: Planned Start Date | S9: Planned End Date | T9: Revised Start Date | U9: Revised End Date | V9: Actual Start Date | W9: Actual End Date | X9: Comments | Y9: RATE CONCAT | Z9: Rate | AA9: DAYS | AB9: Jan_2026_Days_Forecast | AC9: Feb_2026_Days_Forecast | AD9: Mar_2026_Days_Forecast | AE9: Apr_2026_Days_Forecast | AF9: May_2026_Days_Forecast | AG9: Jun_2026_Days_Forecast | AH9: Jul_2026_Days_Forecast | AI9: Aug_2026_Days_Forecast | AJ9: Sep_2026_Days_Forecast | AK9: Oct_2026_Days_Forecast | AL9: Nov_2026_Days_Forecast | AM9: Dec_2026_Days_Forecast | AN9: FTE | AO9: 2026_FTE | AP9: Jan_2026_Days_Actual | AQ9: Feb_2026_Days_Actual | AR9: Mar_2026_Days_Actual | AS9: Apr_2026_Days_Actual | AT9: May_2026_Days_Actual | AU9: Jun_2026_Days_Actual | AV9: Jul_2026_Days_Actual | AW9: Aug_2026_Days_Actual | AX9: Sep_2026_Days_Actual | AY9: Oct_2026_Days_Actual | AZ9: Nov_2026_Days_Actual | BA9: Dec_2026_Days_Actual | BB9: 2027_FTE | BC9: Jan_2027_Days_Forecast | BD9: Feb_2027_Days_Forecast | BE9: Mar_2027_Days_Forecast | BF9: Apr_2027_Days_Forecast | BG9: May_2027_Days_Forecast | BH9: Jun_2027_Days_Forecast | BI9: Jul_2027_Days_Forecast | BJ9: Aug_2027_Days_Forecast | BK9: Sep_2027_Days_Forecast | BL9: Oct_2027_Days_Forecast | BM9: Nov_2027_Days_Forecast | BN9: Dec_2027_Days_Forecast | BO9: COSTS | BP9: 2026_C | BQ9: Jan_2026_F | BR9: Jan_2026_A | BS9: Jan_2026_V | BT9: Jan_2026_V_Reason | BU9: Feb_2026_F | BV9: Feb_2026_A | BW9: Feb_2026_D | BX9: Feb_2026_V_Reason | BY9: Mar_2026_F | BZ9: Mar_2026_A | CA9: Mar_2026_D | CB9: Mar_2026_V_Reason | CC9: Apr_2026_F | CD9: Apr_2026_A | CE9: Apr_2026_D | CF9: Apr_2026_V_Reason | CG9: May_2026_F | CH9: May_2026_A | CI9: May_2026_D | CJ9: May_2026_V_Reason | CK9: Jun_2026_F | CL9: Jun_2026_A | CM9: Jun_2026_D | CN9: Jun_2026_V_Reason | CO9: Jul_2026_F | CP9: Jul_2026_A | CQ9: Jul_2026_D | CR9: Jul_2026_V_Reason | CS9: Aug_2026_F | CT9: Aug_2026_A | CU9: Aug_2026_D | CV9: Aug_2026_V_Reason | CW9: Sep_2026_F | CX9: Sep_2026_A | CY9: Sep_2026_D | CZ9: Sep_2026_V_Reason | DA9: Oct_2026_F | DB9: Oct_2026_A | DC9: Oct_2026_D | DD9: Oct_2026_V_Reason | DE9: Nov_2026_F | DF9: Nov_2026_A | DG9: Nov_2026_D | DH9: Nov_2026_V_Reason | DI9: Dec_2026_F | DJ9: Dec_2026_A | DK9: Dec_2026_D | DL9: Dec_2026_V_Reason | DM9: 2027_C | DN9: Jan_2027_F | DO9: Jan_2027_A | DP9: Jan_2027_D | DQ9: Feb_2027_F | DR9: Feb_2027_A | DS9: Feb_2027_D | DT9: Mar_2027_F | DU9: Mar_2027_A | DV9: Mar_2027_D | DW9: Apr_2027_F | DX9: Apr_2027_A | DY9: Apr_2027_D | DZ9: May_2027_F | EA9: May_2027_A | EB9: May_2027_D | EC9: Jun_2027_F | ED9: Jun_2027_A | EE9: Jun_2027_D | EF9: Jul_2027_F | EG9: Jul_2027_A | EH9: Jul_2027_D | EI9: Aug_2027_F | EJ9: Aug_2027_A | EK9: Aug_2027_D | EL9: Sep_2027_F | EM9: Sep_2027_A | EN9: Sep_2027_D | EO9: Oct_2027_F | EP9: Oct_2027_A | EQ9: Oct_2027_D | ER9: Nov_2027_F | ES9: Nov_2027_A | ET9: Nov_2027_D | EU9: Dec_2027_F | EV9: Dec_2027_A | EW9: Dec_2027_D
A10: PDSFS1001 | B10: Program Management | C10: Staff | D10: Anna Kordek | E10: Shell Business | G10: United Kingdom | H10: 4 | J10: Business PM | K10: In-seat | L10: 1 | M10: LON | N10: Project Management | O10: Capex | P10: Business | Q10: TBD | R10: 46023 | S10: 46387 | T10: 46023 | U10: 46387 | V10: 46023 | W10: 46387 | Y10: =CONCATENATE(Table410[[#This Row],[JG]],Table410[[#This Row],[Country]],Table410[[#This Row],[Resource Provider]]) | Z10: =VLOOKUP(Table410[[#This Row],[RATE CONCAT]],Tables!I:N,5,0) | AB10: 19 | AC10: 19 | AD10: 19 | AE10: 19 | AF10: 19 | AG10: 19 | AH10: 19 | AI10: 19 | AJ10: 19 | AK10: 19 | AL10: 19 | AM10: 19 | AN10: =IFERROR(AVERAGE(Table410[[#This Row],[Jan_2026_Days_Forecast]:[Dec_2026_Days_Forecast]]),0)/19 | AO10: =IFERROR(AVERAGE(Table410[[#This Row],[Jan_2026_Days_Actual]:[Dec_2026_Days_Actual]]),0)/19 | AP10: 19 | AQ10: 19 | AR10: 19 | AS10: 19 | AT10: 19 | AU10: 19 | AV10: 19 | AW10: 19 | AX10: 19 | AY10: 19 | AZ10: 19 | BA10: 19 | BB10: =IFERROR(AVERAGE(Table410[[#This Row],[Jan_2027_Days_Forecast]:[Dec_2027_Days_Forecast]]),0) | BQ10: =IFERROR(Table410[[#This Row],[Jan_2026_Days_Forecast]]*Table410[[#This Row],[Cost Boolean]]*(VLOOKUP(Table410[[#This Row],[RATE CONCAT]],Tables!I:N,5,0)),0) | BR10: =IFERROR(Table410[[#This Row],[Jan_2026_Days_Actual]]*Table410[[#This Row],[Cost Boolean]]*(VLOOKUP(Table410[[#This Row],[RATE CONCAT]],Tables!I:N,5,0)),0) | BS10: =Table410[[#This Row],[Jan_2026_F]]-Table410[[#This Row],[Jan_2026_A]] | BU10: =IFERROR(Table410[[#This Row],[Feb_2026_Days_Forecast]]*Table410[[#This Row],[Cost Boolean]]*(VLOOKUP(Table410[[#This Row],[RATE CONCAT]],Tables!I:N,5,0)),0) | BV10: =IFERROR(Table410[[#This Row],[Feb_2026_Days_Actual]]*Table410[[#This Row],[Cost Boolean]]*(VLOOKUP(Table410[[#This Row],[RATE CONCAT]],Tables!I:N,5,0)),0) | BW10: =Table410[[#This Row],[Feb_2026_F]]-Table410[[#This Row],[Feb_2026_A]] | BY10: =IFERROR(Table410[[#This Row],[Mar_2026_Days_Forecast]]*Table410[[#This Row],[Cost Boolean]]*(VLOOKUP(Table410[[#This Row],[RATE CONCAT]],Tables!I:N,5,0)),0) | BZ10: =IFERROR(Table410[[#This Row],[Mar_2026_Days_Actual]]*Table410[[#This Row],[Cost Boolean]]*(VLOOKUP(Table410[[#This Row],[RATE CONCAT]],Tables!I:N,5,0)),0) | CA10: =Table410[[#This Row],[Mar_2026_F]]-Table410[[#This Row],[Mar_2026_A]] | CC10: =IFERROR(Table410[[#This Row],[Apr_2026_Days_Forecast]]*Table410[[#This Row],[Cost Boolean]]*(VLOOKUP(Table410[[#This Row],[RATE CONCAT]],Tables!I:N,5,0)),0) | CD10: =IFERROR(Table410[[#This Row],[Apr_2026_Days_Actual]]*Table410[[#This Row],[Cost Boolean]]*(VLOOKUP(Table410[[#This Row],[RATE CONCAT]],Tables!I:N,5,0)),0) | CE10: =Table410[[#This Row],[Apr_2026_F]]-Table410[[#This Row],[Apr_2026_A]] | CG10: =IFERROR(Table410[[#This Row],[May_2026_Days_Forecast]] *Table410[[#This Row],[Cost Boolean]]*(VLOOKUP(Table410[[#This Row],[RATE CONCAT]],Tables!I:N,5,0)),0) | CH10: =IFERROR(Table410[[#This Row],[May_2026_Days_Actual]]*Table410[[#This Row],[Cost Boolean]]*(VLOOKUP(Table410[[#This Row],[RATE CONCAT]],Tables!I:N,5,0)),0) | CI10: =Table410[[#This Row],[May_2026_F]]-Table410[[#This Row],[May_2026_A]] | CK10: =IFERROR(Table410[[#This Row],[Jun_2026_Days_Forecast]]*Table410[[#This Row],[Cost Boolean]]*(VLOOKUP(Table410[[#This Row],[RATE CONCAT]],Tables!I:N,5,0)),0) | CL10: =IFERROR(Table410[[#This Row],[Jun_2026_Days_Actual]]*Table410[[#This Row],[Cost Boolean]]*(VLOOKUP(Table410[[#This Row],[RATE CONCAT]],Tables!I:N,5,0)),0) | CM10: =Table410[[#This Row],[Jun_2026_F]]-Table410[[#This Row],[Jun_2026_A]] | CO10: =IFERROR(Table410[[#This Row],[Jul_2026_Days_Forecast]]*Table410[[#This Row],[Cost Boolean]]*(VLOOKUP(Table410[[#This Row],[RATE CONCAT]],Tables!I:N,5,0)),0) | CP10: =IFERROR(Table410[[#This Row],[Jul_2026_Days_Actual]]*Table410[[#This Row],[Cost Boolean]]*(VLOOKUP(Table410[[#This Row],[RATE CONCAT]],Tables!I:N,5,0)),0) | CQ10: =Table410[[#This Row],[Jul_2026_F]]-Table410[[#This Row],[Jul_2026_A]] | CS10: =IFERROR(Table410[[#This Row],[Aug_2026_Days_Forecast]]*Table410[[#This Row],[Cost Boolean]]*(VLOOKUP(Table410[[#This Row],[RATE CONCAT]],Tables!I:N,5,0)),0) | CT10: =IFERROR(Table410[[#This Row],[Aug_2026_Days_Actual]]*Table410[[#This Row],[Cost Boolean]]*(VLOOKUP(Table410[[#This Row],[RATE CONCAT]],Tables!I:N,5,0)),0) | CU10: =Table410[[#This Row],[Aug_2026_F]]-Table410[[#This Row],[Aug_2026_A]] | CW10: =IFERROR(Table410[[#This Row],[Sep_2026_Days_Forecast]]*Table410[[#This Row],[Cost Boolean]]*(VLOOKUP(Table410[[#This Row],[RATE CONCAT]],Tables!I:N,5,0)),0) | CX10: =IFERROR(Table410[[#This Row],[Sep_2026_Days_Actual]]*Table410[[#This Row],[Cost Boolean]]*(VLOOKUP(Table410[[#This Row],[RATE CONCAT]],Tables!I:N,5,0)),0) | CY10: =Table410[[#This Row],[Sep_2026_F]]-Table410[[#This Row],[Sep_2026_A]] | DA10: =IFERROR(Table410[[#This Row],[Oct_2026_Days_Forecast]]*Table410[[#This Row],[Cost Boolean]]*(VLOOKUP(Table410[[#This Row],[RATE CONCAT]],Tables!I:N,5,0)),0) | DB10: =IFERROR(Table410[[#This Row],[Oct_2026_Days_Actual]]*Table410[[#This Row],[Cost Boolean]]*(VLOOKUP(Table410[[#This Row],[RATE CONCAT]],Tables!I:N,5,0)),0) | DC10: =Table410[[#This Row],[Oct_2026_F]]-Table410[[#This Row],[Oct_2026_A]] | DE10: =IFERROR(Table410[[#This Row],[Nov_2026_Days_Forecast]]*Table410[[#This Row],[Cost Boolean]]*(VLOOKUP(Table410[[#This Row],[RATE CONCAT]],Tables!I:N,5,0)),0) | DF10: =IFERROR(Table410[[#This Row],[Nov_2026_Days_Actual]]*Table410[[#This Row],[Cost Boolean]]*(VLOOKUP(Table410[[#This Row],[RATE CONCAT]],Tables!I:N,5,0)),0) | DG10: =Table410[[#This Row],[Nov_2026_F]]-Table410[[#This Row],[Nov_2026_A]] | DI10: =IFERROR(Table410[[#This Row],[Dec_2026_Days_Forecast]]*Table410[[#This Row],[Cost Boolean]]*(VLOOKUP(Table410[[#This Row],[RATE CONCAT]],Tables!I:N,5,0)),0) | DJ10: =IFERROR(Table410[[#This Row],[Dec_2026_Days_Actual]]*Table410[[#This Row],[Cost Boolean]]*(VLOOKUP(Table410[[#This Row],[RATE CONCAT]],Tables!I:N,5,0)),0) | DK10: =Table410[[#This Row],[Dec_2026_F]]-Table410[[#This Row],[Dec_2026_A]] | DN10: =IFERROR(Table410[[#This Row],[Jan_2027_Days_Forecast]]*Table410[[#This Row],[Cost Boolean]]*(VLOOKUP(Table410[[#This Row],[RATE CONCAT]],Tables!I:N,6,0)),0) | DO10: 0 | DP10: =Table410[[#This Row],[Jan_2027_F]]-Table410[[#This Row],[Jan_2027_A]] | DQ10: =IFERROR(Table410[[#This Row],[Feb_2027_Days_Forecast]]*Table410[[#This Row],[Cost Boolean]]*(VLOOKUP(Table410[[#This Row],[RATE CONCAT]],Tables!I:N,6,0)),0) | DR10: 0 | DS10: =Table410[[#This Row],[Feb_2027_F]]-Table410[[#This Row],[Feb_2027_A]] | DT10: =IFERROR(Table410[[#This Row],[Mar_2027_Days_Forecast]]*Table410[[#This Row],[Cost Boolean]]*(VLOOKUP(Table410[[#This Row],[RATE CONCAT]],Tables!I:N,6,0)),0) | DU10: 0 | DV10: =Table410[[#This Row],[Mar_2027_F]]-Table410[[#This Row],[Mar_2027_A]] | DW10: =IFERROR(Table410[[#This Row],[Apr_2027_Days_Forecast]]*Table410[[#This Row],[Cost Boolean]]*(VLOOKUP(Table410[[#This Row],[RATE CONCAT]],Tables!I:N,6,0)),0) | DX10: 0 | DY10: =Table410[[#This Row],[Apr_2027_F]]-Table410[[#This Row],[Apr_2027_A]] | DZ10: =IFERROR(Table410[[#This Row],[May_2027_Days_Forecast]]*Table410[[#This Row],[Cost Boolean]]*(VLOOKUP(Table410[[#This Row],[RATE CONCAT]],Tables!I:N,6,0)),0) | EA10: 0 | EB10: =Table410[[#This Row],[May_2027_F]]-Table410[[#This Row],[May_2027_A]] | EC10: =IFERROR(Table410[[#This Row],[Jun_2027_Days_Forecast]]*Table410[[#This Row],[Cost Boolean]]*(VLOOKUP(Table410[[#This Row],[RATE CONCAT]],Tables!I:N,6,0)),0) | ED10: 0 | EE10: =Table410[[#This Row],[Jun_2027_F]]-Table410[[#This Row],[Jun_2027_A]] | EF10: =IFERROR(Table410[[#This Row],[Jul_2027_Days_Forecast]]*Table410[[#This Row],[Cost Boolean]]*(VLOOKUP(Table410[[#This Row],[RATE CONCAT]],Tables!I:N,6,0)),0) | EG10: 0 | EH10: =Table410[[#This Row],[Jul_2027_F]]-Table410[[#This Row],[Jul_2027_A]] | EI10: =IFERROR(Table410[[#This Row],[Aug_2027_Days_Forecast]]*Table410[[#This Row],[Cost Boolean]]*(VLOOKUP(Table410[[#This Row],[RATE CONCAT]],Tables!I:N,6,0)),0) | EJ10: 0 | EK10: =Table410[[#This Row],[Aug_2027_F]]-Table410[[#This Row],[Aug_2027_A]] | EL10: =IFERROR(Table410[[#This Row],[Sep_2027_Days_Forecast]]*Table410[[#This Row],[Cost Boolean]]*(VLOOKUP(Table410[[#This Row],[RATE CONCAT]],Tables!I:N,6,0)),0) | EM10: 0 | EN10: =Table410[[#This Row],[Sep_2027_F]]-Table410[[#This Row],[Sep_2027_A]] | EO10: =IFERROR(Table410[[#This Row],[Oct_2027_Days_Forecast]]*Table410[[#This Row],[Cost Boolean]]*(VLOOKUP(Table410[[#This Row],[RATE CONCAT]],Tables!I:N,6,0)),0) | EP10: 0 | EQ10: =Table410[[#This Row],[Oct_2027_F]]-Table410[[#This Row],[Oct_2027_A]] | ER10: =IFERROR(Table410[[#This Row],[Nov_2027_Days_Forecast]]*Table410[[#This Row],[Cost Boolean]]*(VLOOKUP(Table410[[#This Row],[RATE CONCAT]],Tables!I:N,6,0)),0) | ES10: =IFERROR(Table410[[#This Row],[Dec_2027_Days_Forecast]]*Table410[[#This Row],[Location]]*(VLOOKUP(Table410[[#This Row],[DAYS]],Tables!J:P,6,0)),0) | ET10: =Table410[[#This Row],[Nov_2027_F]]-Table410[[#This Row],[Nov_2027_A]] | EU10: =IFERROR(Table410[[#This Row],[Dec_2027_Days_Forecast]]*Table410[[#This Row],[Cost Boolean]]*(VLOOKUP(Table410[[#This Row],[RATE CONCAT]],Tables!I:N,6,0)),0) | EV10: 0 | EW10: =Table410[[#This Row],[Dec_2027_F]]-Table410[[#This Row],[Dec_2027_A]]
A11: PDSFS1002 | B11: Program Management | C11: Staff | D11: Ben Poppelaars | E11: Shell Business | G11: United States | H11: 2 | J11: BOM | K11: In-seat | L11: 1 | M11: HOU | N11: Program Management | O11: Capex | P11: Business | Q11: TBD | R11: 46023 | S11: 46387 | T11: 46023 | U11: 46387 | V11: 46023 | W11: 46387 | Y11: =CONCATENATE(Table410[[#This Row],[JG]],Table410[[#This Row],[Country]],Table410[[#This Row],[Resource Provider]]) | Z11: =VLOOKUP(Table410[[#This Row],[RATE CONCAT]],Tables!I:N,5,0) | AB11: 19 | AC11: 19 | AD11: 19 | AE11: 19 | AF11: 19 | AG11: 19 | AH11: 19 | AI11: 19 | AJ11: 19 | AK11: 19 | AL11: 19 | AM11: 19 | AN11: =IFERROR(AVERAGE(Table410[[#This Row],[Jan_2026_Days_Forecast]:[Dec_2026_Days_Forecast]]),0)/19 | AO11: =IFERROR(AVERAGE(Table410[[#This Row],[Jan_2026_Days_Actual]:[Dec_2026_Days_Actual]]),0)/19 | AP11: 19 | AQ11: 19 | AR11: 19 | AS11: 19 | AT11: 19 | AU11: 19 | AV11: 19 | AW11: 19 | AX11: 19 | AY11: 19 | AZ11: 19 | BA11: 19 | BB11: =IFERROR(AVERAGE(Table410[[#This Row],[Jan_2027_Days_Forecast]:[Dec_2027_Days_Forecast]]),0) | BQ11: =IFERROR(Table410[[#This Row],[Jan_2026_Days_Forecast]]*Table410[[#This Row],[Cost Boolean]]*(VLOOKUP(Table410[[#This Row],[RATE CONCAT]],Tables!I:N,5,0)),0) | BR11: =IFERROR(Table410[[#This Row],[Jan_2026_Days_Actual]]*Table410[[#This Row],[Cost Boolean]]*(VLOOKUP(Table410[[#This Row],[RATE CONCAT]],Tables!I:N,5,0)),0) | BS11: =Table410[[#This Row],[Jan_2026_F]]-Table410[[#This Row],[Jan_2026_A]] | BU11: =IFERROR(Table410[[#This Row],[Feb_2026_Days_Forecast]]*Table410[[#This Row],[Cost Boolean]]*(VLOOKUP(Table410[[#This Row],[RATE CONCAT]],Tables!I:N,5,0)),0) | BV11: =IFERROR(Table410[[#This Row],[Feb_2026_Days_Actual]]*Table410[[#This Row],[Cost Boolean]]*(VLOOKUP(Table410[[#This Row],[RATE CONCAT]],Tables!I:N,5,0)),0) | BW11: =Table410[[#This Row],[Feb_2026_F]]-Table410[[#This Row],[Feb_2026_A]] | BY11: =IFERROR(Table410[[#This Row],[Mar_2026_Days_Forecast]]*Table410[[#This Row],[Cost Boolean]]*(VLOOKUP(Table410[[#This Row],[RATE CONCAT]],Tables!I:N,5,0)),0) | BZ11: =IFERROR(Table410[[#This Row],[Mar_2026_Days_Actual]]*Table410[[#This Row],[Cost Boolean]]*(VLOOKUP(Table410[[#This Row],[RATE CONCAT]],Tables!I:N,5,0)),0) | CA11: =Table410[[#This Row],[Mar_2026_F]]-Table410[[#This Row],[Mar_2026_A]] | CC11: =IFERROR(Table410[[#This Row],[Apr_2026_Days_Forecast]]*Table410[[#This Row],[Cost Boolean]]*(VLOOKUP(Table410[[#This Row],[RATE CONCAT]],Tables!I:N,5,0)),0) | CD11: =IFERROR(Table410[[#This Row],[Apr_2026_Days_Actual]]*Table410[[#This Row],[Cost Boolean]]*(VLOOKUP(Table410[[#This Row],[RATE CONCAT]],Tables!I:N,5,0)),0) | CE11: =Table410[[#This Row],[Apr_2026_F]]-Table410[[#This Row],[Apr_2026_A]] | CG11: =IFERROR(Table410[[#This Row],[May_2026_Days_Forecast]] *Table410[[#This Row],[Cost Boolean]]*(VLOOKUP(Table410[[#This Row],[RATE CONCAT]],Tables!I:N,5,0)),0) | CH11: =IFERROR(Table410[[#This Row],[May_2026_Days_Actual]]*Table410[[#This Row],[Cost Boolean]]*(VLOOKUP(Table410[[#This Row],[RATE CONCAT]],Tables!I:N,5,0)),0) | CI11: =Table410[[#This Row],[May_2026_F]]-Table410[[#This Row],[May_2026_A]] | CK11: =IFERROR(Table410[[#This Row],[Jun_2026_Days_Forecast]]*Table410[[#This Row],[Cost Boolean]]*(VLOOKUP(Table410[[#This Row],[RATE CONCAT]],Tables!I:N,5,0)),0) | CL11: =IFERROR(Table410[[#This Row],[Jun_2026_Days_Actual]]*Table410[[#This Row],[Cost Boolean]]*(VLOOKUP(Table410[[#This Row],[RATE CONCAT]],Tables!I:N,5,0)),0) | CM11: =Table410[[#This Row],[Jun_2026_F]]-Table410[[#This Row],[Jun_2026_A]] | CO11: =IFERROR(Table410[[#This Row],[Jul_2026_Days_Forecast]]*Table410[[#This Row],[Cost Boolean]]*(VLOOKUP(Table410[[#This Row],[RATE CONCAT]],Tables!I:N,5,0)),0) | CP11: =IFERROR(Table410[[#This Row],[Jul_2026_Days_Actual]]*Table410[[#This Row],[Cost Boolean]]*(VLOOKUP(Table410[[#This Row],[RATE CONCAT]],Tables!I:N,5,0)),0) | CQ11: =Table410[[#This Row],[Jul_2026_F]]-Table410[[#This Row],[Jul_2026_A]] | CS11: =IFERROR(Table410[[#This Row],[Aug_2026_Days_Forecast]]*Table410[[#This Row],[Cost Boolean]]*(VLOOKUP(Table410[[#This Row],[RATE CONCAT]],Tables!I:N,5,0)),0) | CT11: =IFERROR(Table410[[#This Row],[Aug_2026_Days_Actual]]*Table410[[#This Row],[Cost Boolean]]*(VLOOKUP(Table410[[#This Row],[RATE CONCAT]],Tables!I:N,5,0)),0) | CU11: =Table410[[#This Row],[Aug_2026_F]]-Table410[[#This Row],[Aug_2026_A]] | CW11: =IFERROR(Table410[[#This Row],[Sep_2026_Days_Forecast]]*Table410[[#This Row],[Cost Boolean]]*(VLOOKUP(Table410[[#This Row],[RATE CONCAT]],Tables!I:N,5,0)),0) | CX11: =IFERROR(Table410[[#This Row],[Sep_2026_Days_Actual]]*Table410[[#This Row],[Cost Boolean]]*(VLOOKUP(Table410[[#This Row],[RATE CONCAT]],Tables!I:N,5,0)),0) | CY11: =Table410[[#This Row],[Sep_2026_F]]-Table410[[#This Row],[Sep_2026_A]] | DA11: =IFERROR(Table410[[#This Row],[Oct_2026_Days_Forecast]]*Table410[[#This Row],[Cost Boolean]]*(VLOOKUP(Table410[[#This Row],[RATE CONCAT]],Tables!I:N,5,0)),0) | DB11: =IFERROR(Table410[[#This Row],[Oct_2026_Days_Actual]]*Table410[[#This Row],[Cost Boolean]]*(VLOOKUP(Table410[[#This Row],[RATE CONCAT]],Tables!I:N,5,0)),0) | DC11: =Table410[[#This Row],[Oct_2026_F]]-Table410[[#This Row],[Oct_2026_A]] | DE11: =IFERROR(Table410[[#This Row],[Nov_2026_Days_Forecast]]*Table410[[#This Row],[Cost Boolean]]*(VLOOKUP(Table410[[#This Row],[RATE CONCAT]],Tables!I:N,5,0)),0) | DF11: =IFERROR(Table410[[#This Row],[Nov_2026_Days_Actual]]*Table410[[#This Row],[Cost Boolean]]*(VLOOKUP(Table410[[#This Row],[RATE CONCAT]],Tables!I:N,5,0)),0) | DG11: =Table410[[#This Row],[Nov_2026_F]]-Table410[[#This Row],[Nov_2026_A]] | DI11: =IFERROR(Table410[[#This Row],[Dec_2026_Days_Forecast]]*Table410[[#This Row],[Cost Boolean]]*(VLOOKUP(Table410[[#This Row],[RATE CONCAT]],Tables!I:N,5,0)),0) | DJ11: =IFERROR(Table410[[#This Row],[Dec_2026_Days_Actual]]*Table410[[#This Row],[Cost Boolean]]*(VLOOKUP(Table410[[#This Row],[RATE CONCAT]],Tables!I:N,5,0)),0) | DK11: =Table410[[#This Row],[Dec_2026_F]]-Table410[[#This Row],[Dec_2026_A]] | DN11: =IFERROR(Table410[[#This Row],[Jan_2027_Days_Forecast]]*Table410[[#This Row],[Cost Boolean]]*(VLOOKUP(Table410[[#This Row],[RATE CONCAT]],Tables!I:N,6,0)),0) | DO11: 0 | DP11: =Table410[[#This Row],[Jan_2027_F]]-Table410[[#This Row],[Jan_2027_A]] | DQ11: =IFERROR(Table410[[#This Row],[Feb_2027_Days_Forecast]]*Table410[[#This Row],[Cost Boolean]]*(VLOOKUP(Table410[[#This Row],[RATE CONCAT]],Tables!I:N,6,0)),0) | DR11: 0 | DS11: =Table410[[#This Row],[Feb_2027_F]]-Table410[[#This Row],[Feb_2027_A]] | DT11: =IFERROR(Table410[[#This Row],[Mar_2027_Days_Forecast]]*Table410[[#This Row],[Cost Boolean]]*(VLOOKUP(Table410[[#This Row],[RATE CONCAT]],Tables!I:N,6,0)),0) | DU11: 0 | DV11: =Table410[[#This Row],[Mar_2027_F]]-Table410[[#This Row],[Mar_2027_A]] | DW11: =IFERROR(Table410[[#This Row],[Apr_2027_Days_Forecast]]*Table410[[#This Row],[Cost Boolean]]*(VLOOKUP(Table410[[#This Row],[RATE CONCAT]],Tables!I:N,6,0)),0) | DX11: 0 | DY11: =Table410[[#This Row],[Apr_2027_F]]-Table410[[#This Row],[Apr_2027_A]] | DZ11: =IFERROR(Table410[[#This Row],[May_2027_Days_Forecast]]*Table410[[#This Row],[Cost Boolean]]*(VLOOKUP(Table410[[#This Row],[RATE CONCAT]],Tables!I:N,6,0)),0) | EA11: 0 | EB11: =Table410[[#This Row],[May_2027_F]]-Table410[[#This Row],[May_2027_A]] | EC11: =IFERROR(Table410[[#This Row],[Jun_2027_Days_Forecast]]*Table410[[#This Row],[Cost Boolean]]*(VLOOKUP(Table410[[#This Row],[RATE CONCAT]],Tables!I:N,6,0)),0) | ED11: 0 | EE11: =Table410[[#This Row],[Jun_2027_F]]-Table410[[#This Row],[Jun_2027_A]] | EF11: =IFERROR(Table410[[#This Row],[Jul_2027_Days_Forecast]]*Table410[[#This Row],[Cost Boolean]]*(VLOOKUP(Table410[[#This Row],[RATE CONCAT]],Tables!I:N,6,0)),0) | EG11: 0 | EH11: =Table410[[#This Row],[Jul_2027_F]]-Table410[[#This Row],[Jul_2027_A]] | EI11: =IFERROR(Table410[[#This Row],[Aug_2027_Days_Forecast]]*Table410[[#This Row],[Cost Boolean]]*(VLOOKUP(Table410[[#This Row],[RATE CONCAT]],Tables!I:N,6,0)),0) | EJ11: 0 | EK11: =Table410[[#This Row],[Aug_2027_F]]-Table410[[#This Row],[Aug_2027_A]] | EL11: =IFERROR(Table410[[#This Row],[Sep_2027_Days_Forecast]]*Table410[[#This Row],[Cost Boolean]]*(VLOOKUP(Table410[[#This Row],[RATE CONCAT]],Tables!I:N,6,0)),0) | EM11: 0 | EN11: =Table410[[#This Row],[Sep_2027_F]]-Table410[[#This Row],[Sep_2027_A]] | EO11: =IFERROR(Table410[[#This Row],[Oct_2027_Days_Forecast]]*Table410[[#This Row],[Cost Boolean]]*(VLOOKUP(Table410[[#This Row],[RATE CONCAT]],Tables!I:N,6,0)),0) | EP11: 0 | EQ11: =Table410[[#This Row],[Oct_2027_F]]-Table410[[#This Row],[Oct_2027_A]] | ER11: =IFERROR(Table410[[#This Row],[Nov_2027_Days_Forecast]]*Table410[[#This Row],[Cost Boolean]]*(VLOOKUP(Table410[[#This Row],[RATE CONCAT]],Tables!I:N,6,0)),0) | ES11: 0 | ET11: =Table410[[#This Row],[Nov_2027_F]]-Table410[[#This Row],[Nov_2027_A]] | EU11: =IFERROR(Table410[[#This Row],[Dec_2027_Days_Forecast]]*Table410[[#This Row],[Cost Boolean]]*(VLOOKUP(Table410[[#This Row],[RATE CONCAT]],Tables!I:N,6,0)),0) | EV11: 0 | EW11: =Table410[[#This Row],[Dec_2027_F]]-Table410[[#This Row],[Dec_2027_A]]
A12: PDSFS1003 | B12: VPD | C12: Staff | D12: Shalini Mandala | E12: Shell Business | G12: United States | H12: 3 | J12: Developer | K12: In-seat | L12: 1 | M12: HOU | N12: Software development | O12: Capex | P12: Business | Q12: TBD | R12: 46023 | S12: 46387 | T12: 46023 | U12: 46387 | V12: 46023 | W12: 46387 | Y12: =CONCATENATE(Table410[[#This Row],[JG]],Table410[[#This Row],[Country]],Table410[[#This Row],[Resource Provider]]) | Z12: =VLOOKUP(Table410[[#This Row],[RATE CONCAT]],Tables!I:N,5,0) | AB12: 5 | AC12: 5 | AD12: 5 | AE12: 5 | AF12: 5 | AG12: 4 | AH12: 5 | AI12: 5 | AJ12: 5 | AK12: 5 | AL12: 5 | AM12: 4 | AN12: =IFERROR(AVERAGE(Table410[[#This Row],[Jan_2026_Days_Forecast]:[Dec_2026_Days_Forecast]]),0)/19 | AO12: =IFERROR(AVERAGE(Table410[[#This Row],[Jan_2026_Days_Actual]:[Dec_2026_Days_Actual]]),0)/19 | AP12: 5 | AQ12: 5 | AR12: 5 | AS12: 5 | AT12: 5 | AU12: 4 | AV12: 5 | AW12: 5 | AX12: 5 | AY12: 5 | AZ12: 5 | BA12: 4 | BB12: =IFERROR(AVERAGE(Table410[[#This Row],[Jan_2027_Days_Forecast]:[Dec_2027_Days_Forecast]]),0) | BQ12: =IFERROR(Table410[[#This Row],[Jan_2026_Days_Forecast]]*Table410[[#This Row],[Cost Boolean]]*(VLOOKUP(Table410[[#This Row],[RATE CONCAT]],Tables!I:N,5,0)),0) | BR12: =IFERROR(Table410[[#This Row],[Jan_2026_Days_Actual]]*Table410[[#This Row],[Cost Boolean]]*(VLOOKUP(Table410[[#This Row],[RATE CONCAT]],Tables!I:N,5,0)),0) | BS12: =Table410[[#This Row],[Jan_2026_F]]-Table410[[#This Row],[Jan_2026_A]] | BU12: =IFERROR(Table410[[#This Row],[Feb_2026_Days_Forecast]]*Table410[[#This Row],[Cost Boolean]]*(VLOOKUP(Table410[[#This Row],[RATE CONCAT]],Tables!I:N,5,0)),0) | BV12: =IFERROR(Table410[[#This Row],[Feb_2026_Days_Actual]]*Table410[[#This Row],[Cost Boolean]]*(VLOOKUP(Table410[[#This Row],[RATE CONCAT]],Tables!I:N,5,0)),0) | BW12: =Table410[[#This Row],[Feb_2026_F]]-Table410[[#This Row],[Feb_2026_A]] | BY12: =IFERROR(Table410[[#This Row],[Mar_2026_Days_Forecast]]*Table410[[#This Row],[Cost Boolean]]*(VLOOKUP(Table410[[#This Row],[RATE CONCAT]],Tables!I:N,5,0)),0) | BZ12: =IFERROR(Table410[[#This Row],[Mar_2026_Days_Actual]]*Table410[[#This Row],[Cost Boolean]]*(VLOOKUP(Table410[[#This Row],[RATE CONCAT]],Tables!I:N,5,0)),0) | CA12: =Table410[[#This Row],[Mar_2026_F]]-Table410[[#This Row],[Mar_2026_A]] | CC12: =IFERROR(Table410[[#This Row],[Apr_2026_Days_Forecast]]*Table410[[#This Row],[Cost Boolean]]*(VLOOKUP(Table410[[#This Row],[RATE CONCAT]],Tables!I:N,5,0)),0) | CD12: =IFERROR(Table410[[#This Row],[Apr_2026_Days_Actual]]*Table410[[#This Row],[Cost Boolean]]*(VLOOKUP(Table410[[#This Row],[RATE CONCAT]],Tables!I:N,5,0)),0) | CE12: =Table410[[#This Row],[Apr_2026_F]]-Table410[[#This Row],[Apr_2026_A]] | CG12: =IFERROR(Table410[[#This Row],[May_2026_Days_Forecast]] *Table410[[#This Row],[Cost Boolean]]*(VLOOKUP(Table410[[#This Row],[RATE CONCAT]],Tables!I:N,5,0)),0) | CH12: =IFERROR(Table410[[#This Row],[May_2026_Days_Actual]]*Table410[[#This Row],[Cost Boolean]]*(VLOOKUP(Table410[[#This Row],[RATE CONCAT]],Tables!I:N,5,0)),0) | CI12: =Table410[[#This Row],[May_2026_F]]-Table410[[#This Row],[May_2026_A]] | CK12: =IFERROR(Table410[[#This Row],[Jun_2026_Days_Forecast]]*Table410[[#This Row],[Cost Boolean]]*(VLOOKUP(Table410[[#This Row],[RATE CONCAT]],Tables!I:N,5,0)),0) | CL12: =IFERROR(Table410[[#This Row],[Jun_2026_Days_Actual]]*Table410[[#This Row],[Cost Boolean]]*(VLOOKUP(Table410[[#This Row],[RATE CONCAT]],Tables!I:N,5,0)),0) | CM12: =Table410[[#This Row],[Jun_2026_F]]-Table410[[#This Row],[Jun_2026_A]] | CO12: =IFERROR(Table410[[#This Row],[Jul_2026_Days_Forecast]]*Table410[[#This Row],[Cost Boolean]]*(VLOOKUP(Table410[[#This Row],[RATE CONCAT]],Tables!I:N,5,0)),0) | CP12: =IFERROR(Table410[[#This Row],[Jul_2026_Days_Actual]]*Table410[[#This Row],[Cost Boolean]]*(VLOOKUP(Table410[[#This Row],[RATE CONCAT]],Tables!I:N,5,0)),0) | CQ12: =Table410[[#This Row],[Jul_2026_F]]-Table410[[#This Row],[Jul_2026_A]] | CS12: =IFERROR(Table410[[#This Row],[Aug_2026_Days_Forecast]]*Table410[[#This Row],[Cost Boolean]]*(VLOOKUP(Table410[[#This Row],[RATE CONCAT]],Tables!I:N,5,0)),0) | CT12: =IFERROR(Table410[[#This Row],[Aug_2026_Days_Actual]]*Table410[[#This Row],[Cost Boolean]]*(VLOOKUP(Table410[[#This Row],[RATE CONCAT]],Tables!I:N,5,0)),0) | CU12: =Table410[[#This Row],[Aug_2026_F]]-Table410[[#This Row],[Aug_2026_A]] | CW12: =IFERROR(Table410[[#This Row],[Sep_2026_Days_Forecast]]*Table410[[#This Row],[Cost Boolean]]*(VLOOKUP(Table410[[#This Row],[RATE CONCAT]],Tables!I:N,5,0)),0) | CX12: =IFERROR(Table410[[#This Row],[Sep_2026_Days_Actual]]*Table410[[#This Row],[Cost Boolean]]*(VLOOKUP(Table410[[#This Row],[RATE CONCAT]],Tables!I:N,5,0)),0) | CY12: =Table410[[#This Row],[Sep_2026_F]]-Table410[[#This Row],[Sep_2026_A]] | DA12: =IFERROR(Table410[[#This Row],[Oct_2026_Days_Forecast]]*Table410[[#This Row],[Cost Boolean]]*(VLOOKUP(Table410[[#This Row],[RATE CONCAT]],Tables!I:N,5,0)),0) | DB12: =IFERROR(Table410[[#This Row],[Oct_2026_Days_Actual]]*Table410[[#This Row],[Cost Boolean]]*(VLOOKUP(Table410[[#This Row],[RATE CONCAT]],Tables!I:N,5,0)),0) | DC12: =Table410[[#This Row],[Oct_2026_F]]-Table410[[#This Row],[Oct_2026_A]] | DE12: =IFERROR(Table410[[#This Row],[Nov_2026_Days_Forecast]]*Table410[[#This Row],[Cost Boolean]]*(VLOOKUP(Table410[[#This Row],[RATE CONCAT]],Tables!I:N,5,0)),0) | DF12: =IFERROR(Table410[[#This Row],[Nov_2026_Days_Actual]]*Table410[[#This Row],[Cost Boolean]]*(VLOOKUP(Table410[[#This Row],[RATE CONCAT]],Tables!I:N,5,0)),0) | DG12: =Table410[[#This Row],[Nov_2026_F]]-Table410[[#This Row],[Nov_2026_A]] | DI12: =IFERROR(Table410[[#This Row],[Dec_2026_Days_Forecast]]*Table410[[#This Row],[Cost Boolean]]*(VLOOKUP(Table410[[#This Row],[RATE CONCAT]],Tables!I:N,5,0)),0) | DJ12: =IFERROR(Table410[[#This Row],[Dec_2026_Days_Actual]]*Table410[[#This Row],[Cost Boolean]]*(VLOOKUP(Table410[[#This Row],[RATE CONCAT]],Tables!I:N,5,0)),0) | DK12: =Table410[[#This Row],[Dec_2026_F]]-Table410[[#This Row],[Dec_2026_A]] | DN12: =IFERROR(Table410[[#This Row],[Jan_2027_Days_Forecast]]*Table410[[#This Row],[Cost Boolean]]*(VLOOKUP(Table410[[#This Row],[RATE CONCAT]],Tables!I:N,6,0)),0) | DO12: 0 | DP12: =Table410[[#This Row],[Jan_2027_F]]-Table410[[#This Row],[Jan_2027_A]] | DQ12: =IFERROR(Table410[[#This Row],[Feb_2027_Days_Forecast]]*Table410[[#This Row],[Cost Boolean]]*(VLOOKUP(Table410[[#This Row],[RATE CONCAT]],Tables!I:N,6,0)),0) | DR12: 0 | DS12: =Table410[[#This Row],[Feb_2027_F]]-Table410[[#This Row],[Feb_2027_A]] | DT12: =IFERROR(Table410[[#This Row],[Mar_2027_Days_Forecast]]*Table410[[#This Row],[Cost Boolean]]*(VLOOKUP(Table410[[#This Row],[RATE CONCAT]],Tables!I:N,6,0)),0) | DU12: 0 | DV12: =Table410[[#This Row],[Mar_2027_F]]-Table410[[#This Row],[Mar_2027_A]] | DW12: =IFERROR(Table410[[#This Row],[Apr_2027_Days_Forecast]]*Table410[[#This Row],[Cost Boolean]]*(VLOOKUP(Table410[[#This Row],[RATE CONCAT]],Tables!I:N,6,0)),0) | DX12: 0 | DY12: =Table410[[#This Row],[Apr_2027_F]]-Table410[[#This Row],[Apr_2027_A]] | DZ12: =IFERROR(Table410[[#This Row],[May_2027_Days_Forecast]]*Table410[[#This Row],[Cost Boolean]]*(VLOOKUP(Table410[[#This Row],[RATE CONCAT]],Tables!I:N,6,0)),0) | EA12: 0 | EB12: =Table410[[#This Row],[May_2027_F]]-Table410[[#This Row],[May_2027_A]] | EC12: =IFERROR(Table410[[#This Row],[Jun_2027_Days_Forecast]]*Table410[[#This Row],[Cost Boolean]]*(VLOOKUP(Table410[[#This Row],[RATE CONCAT]],Tables!I:N,6,0)),0) | ED12: 0 | EE12: =Table410[[#This Row],[Jun_2027_F]]-Table410[[#This Row],[Jun_2027_A]] | EF12: =IFERROR(Table410[[#This Row],[Jul_2027_Days_Forecast]]*Table410[[#This Row],[Cost Boolean]]*(VLOOKUP(Table410[[#This Row],[RATE CONCAT]],Tables!I:N,6,0)),0) | EG12: 0 | EH12: =Table410[[#This Row],[Jul_2027_F]]-Table410[[#This Row],[Jul_2027_A]] | EI12: =IFERROR(Table410[[#This Row],[Aug_2027_Days_Forecast]]*Table410[[#This Row],[Cost Boolean]]*(VLOOKUP(Table410[[#This Row],[RATE CONCAT]],Tables!I:N,6,0)),0) | EJ12: 0 | EK12: =Table410[[#This Row],[Aug_2027_F]]-Table410[[#This Row],[Aug_2027_A]] | EL12: =IFERROR(Table410[[#This Row],[Sep_2027_Days_Forecast]]*Table410[[#This Row],[Cost Boolean]]*(VLOOKUP(Table410[[#This Row],[RATE CONCAT]],Tables!I:N,6,0)),0) | EM12: 0 | EN12: =Table410[[#This Row],[Sep_2027_F]]-Table410[[#This Row],[Sep_2027_A]] | EO12: =IFERROR(Table410[[#This Row],[Oct_2027_Days_Forecast]]*Table410[[#This Row],[Cost Boolean]]*(VLOOKUP(Table410[[#This Row],[RATE CONCAT]],Tables!I:N,6,0)),0) | EP12: 0 | EQ12: =Table410[[#This Row],[Oct_2027_F]]-Table410[[#This Row],[Oct_2027_A]] | ER12: =IFERROR(Table410[[#This Row],[Nov_2027_Days_Forecast]]*Table410[[#This Row],[Cost Boolean]]*(VLOOKUP(Table410[[#This Row],[RATE CONCAT]],Tables!I:N,6,0)),0) | ES12: 0 | ET12: =Table410[[#This Row],[Nov_2027_F]]-Table410[[#This Row],[Nov_2027_A]] | EU12: =IFERROR(Table410[[#This Row],[Dec_2027_Days_Forecast]]*Table410[[#This Row],[Cost Boolean]]*(VLOOKUP(Table410[[#This Row],[RATE CONCAT]],Tables!I:N,6,0)),0) | EV12: 0 | EW12: =Table410[[#This Row],[Dec_2027_F]]-Table410[[#This Row],[Dec_2027_A]]
A13: PDSFS1009 | B13: Prosmar Crude | C13: Staff | D13: Dilan Velani | E13: Shell Business | G13: United Kingdom | H13: 5 | J13: Market Risk Analyst | K13: In-seat | L13: 1 | M13: LON | N13: Market Risk | O13: Capex | P13: Business | Q13: TBD | R13: 46023 | S13: 46387 | T13: 46023 | U13: 46387 | V13: 46023 | W13: 46387 | Y13: =CONCATENATE(Table410[[#This Row],[JG]],Table410[[#This Row],[Country]],Table410[[#This Row],[Resource Provider]]) | Z13: =VLOOKUP(Table410[[#This Row],[RATE CONCAT]],Tables!I:N,5,0) | AB13: 10 | AC13: 10 | AD13: 10 | AE13: 10 | AF13: 9 | AG13: 9 | AH13: 9 | AI13: 10 | AJ13: 10 | AK13: 10 | AL13: 9 | AM13: 9 | AN13: =IFERROR(AVERAGE(Table410[[#This Row],[Jan_2026_Days_Forecast]:[Dec_2026_Days_Forecast]]),0)/19 | AO13: =IFERROR(AVERAGE(Table410[[#This Row],[Jan_2026_Days_Actual]:[Dec_2026_Days_Actual]]),0)/19 | AP13: 10 | AQ13: 10 | AR13: 10 | AS13: 10 | AT13: 9 | AU13: 9 | AV13: 9 | AW13: 10 | AX13: 10 | AY13: 10 | AZ13: 9 | BA13: 9 | BB13: =IFERROR(AVERAGE(Table410[[#This Row],[Jan_2027_Days_Forecast]:[Dec_2027_Days_Forecast]]),0) | BQ13: =IFERROR(Table410[[#This Row],[Jan_2026_Days_Forecast]]*Table410[[#This Row],[Cost Boolean]]*(VLOOKUP(Table410[[#This Row],[RATE CONCAT]],Tables!I:N,5,0)),0) | BR13: =IFERROR(Table410[[#This Row],[Jan_2026_Days_Actual]]*Table410[[#This Row],[Cost Boolean]]*(VLOOKUP(Table410[[#This Row],[RATE CONCAT]],Tables!I:N,5,0)),0) | BS13: =Table410[[#This Row],[Jan_2026_F]]-Table410[[#This Row],[Jan_2026_A]] | BU13: =IFERROR(Table410[[#This Row],[Feb_2026_Days_Forecast]]*Table410[[#This Row],[Cost Boolean]]*(VLOOKUP(Table410[[#This Row],[RATE CONCAT]],Tables!I:N,5,0)),0) | BV13: =IFERROR(Table410[[#This Row],[Feb_2026_Days_Actual]]*Table410[[#This Row],[Cost Boolean]]*(VLOOKUP(Table410[[#This Row],[RATE CONCAT]],Tables!I:N,5,0)),0) | BW13: =Table410[[#This Row],[Feb_2026_F]]-Table410[[#This Row],[Feb_2026_A]] | BY13: =IFERROR(Table410[[#This Row],[Mar_2026_Days_Forecast]]*Table410[[#This Row],[Cost Boolean]]*(VLOOKUP(Table410[[#This Row],[RATE CONCAT]],Tables!I:N,5,0)),0) | BZ13: =IFERROR(Table410[[#This Row],[Mar_2026_Days_Actual]]*Table410[[#This Row],[Cost Boolean]]*(VLOOKUP(Table410[[#This Row],[RATE CONCAT]],Tables!I:N,5,0)),0) | CA13: =Table410[[#This Row],[Mar_2026_F]]-Table410[[#This Row],[Mar_2026_A]] | CC13: =IFERROR(Table410[[#This Row],[Apr_2026_Days_Forecast]]*Table410[[#This Row],[Cost Boolean]]*(VLOOKUP(Table410[[#This Row],[RATE CONCAT]],Tables!I:N,5,0)),0) | CD13: =IFERROR(Table410[[#This Row],[Apr_2026_Days_Actual]]*Table410[[#This Row],[Cost Boolean]]*(VLOOKUP(Table410[[#This Row],[RATE CONCAT]],Tables!I:N,5,0)),0) | CE13: =Table410[[#This Row],[Apr_2026_F]]-Table410[[#This Row],[Apr_2026_A]] | CG13: =IFERROR(Table410[[#This Row],[May_2026_Days_Forecast]] *Table410[[#This Row],[Cost Boolean]]*(VLOOKUP(Table410[[#This Row],[RATE CONCAT]],Tables!I:N,5,0)),0) | CH13: =IFERROR(Table410[[#This Row],[May_2026_Days_Actual]]*Table410[[#This Row],[Cost Boolean]]*(VLOOKUP(Table410[[#This Row],[RATE CONCAT]],Tables!I:N,5,0)),0) | CI13: =Table410[[#This Row],[May_2026_F]]-Table410[[#This Row],[May_2026_A]] | CK13: =IFERROR(Table410[[#This Row],[Jun_2026_Days_Forecast]]*Table410[[#This Row],[Cost Boolean]]*(VLOOKUP(Table410[[#This Row],[RATE CONCAT]],Tables!I:N,5,0)),0) | CL13: =IFERROR(Table410[[#This Row],[Jun_2026_Days_Actual]]*Table410[[#This Row],[Cost Boolean]]*(VLOOKUP(Table410[[#This Row],[RATE CONCAT]],Tables!I:N,5,0)),0) | CM13: =Table410[[#This Row],[Jun_2026_F]]-Table410[[#This Row],[Jun_2026_A]] | CO13: =IFERROR(Table410[[#This Row],[Jul_2026_Days_Forecast]]*Table410[[#This Row],[Cost Boolean]]*(VLOOKUP(Table410[[#This Row],[RATE CONCAT]],Tables!I:N,5,0)),0) | CP13: =IFERROR(Table410[[#This Row],[Jul_2026_Days_Actual]]*Table410[[#This Row],[Cost Boolean]]*(VLOOKUP(Table410[[#This Row],[RATE CONCAT]],Tables!I:N,5,0)),0) | CQ13: =Table410[[#This Row],[Jul_2026_F]]-Table410[[#This Row],[Jul_2026_A]] | CS13: =IFERROR(Table410[[#This Row],[Aug_2026_Days_Forecast]]*Table410[[#This Row],[Cost Boolean]]*(VLOOKUP(Table410[[#This Row],[RATE CONCAT]],Tables!I:N,5,0)),0) | CT13: =IFERROR(Table410[[#This Row],[Aug_2026_Days_Actual]]*Table410[[#This Row],[Cost Boolean]]*(VLOOKUP(Table410[[#This Row],[RATE CONCAT]],Tables!I:N,5,0)),0) | CU13: =Table410[[#This Row],[Aug_2026_F]]-Table410[[#This Row],[Aug_2026_A]] | CW13: =IFERROR(Table410[[#This Row],[Sep_2026_Days_Forecast]]*Table410[[#This Row],[Cost Boolean]]*(VLOOKUP(Table410[[#This Row],[RATE CONCAT]],Tables!I:N,5,0)),0) | CX13: =IFERROR(Table410[[#This Row],[Sep_2026_Days_Actual]]*Table410[[#This Row],[Cost Boolean]]*(VLOOKUP(Table410[[#This Row],[RATE CONCAT]],Tables!I:N,5,0)),0) | CY13: =Table410[[#This Row],[Sep_2026_F]]-Table410[[#This Row],[Sep_2026_A]] | DA13: =IFERROR(Table410[[#This Row],[Oct_2026_Days_Forecast]]*Table410[[#This Row],[Cost Boolean]]*(VLOOKUP(Table410[[#This Row],[RATE CONCAT]],Tables!I:N,5,0)),0) | DB13: =IFERROR(Table410[[#This Row],[Oct_2026_Days_Actual]]*Table410[[#This Row],[Cost Boolean]]*(VLOOKUP(Table410[[#This Row],[RATE CONCAT]],Tables!I:N,5,0)),0) | DC13: =Table410[[#This Row],[Oct_2026_F]]-Table410[[#This Row],[Oct_2026_A]] | DE13: =IFERROR(Table410[[#This Row],[Nov_2026_Days_Forecast]]*Table410[[#This Row],[Cost Boolean]]*(VLOOKUP(Table410[[#This Row],[RATE CONCAT]],Tables!I:N,5,0)),0) | DF13: =IFERROR(Table410[[#This Row],[Nov_2026_Days_Actual]]*Table410[[#This Row],[Cost Boolean]]*(VLOOKUP(Table410[[#This Row],[RATE CONCAT]],Tables!I:N,5,0)),0) | DG13: =Table410[[#This Row],[Nov_2026_F]]-Table410[[#This Row],[Nov_2026_A]] | DI13: =IFERROR(Table410[[#This Row],[Dec_2026_Days_Forecast]]*Table410[[#This Row],[Cost Boolean]]*(VLOOKUP(Table410[[#This Row],[RATE CONCAT]],Tables!I:N,5,0)),0) | DJ13: =IFERROR(Table410[[#This Row],[Dec_2026_Days_Actual]]*Table410[[#This Row],[Cost Boolean]]*(VLOOKUP(Table410[[#This Row],[RATE CONCAT]],Tables!I:N,5,0)),0) | DK13: =Table410[[#This Row],[Dec_2026_F]]-Table410[[#This Row],[Dec_2026_A]] | DN13: =IFERROR(Table410[[#This Row],[Jan_2027_Days_Forecast]]*Table410[[#This Row],[Cost Boolean]]*(VLOOKUP(Table410[[#This Row],[RATE CONCAT]],Tables!I:N,6,0)),0) | DO13: 0 | DP13: =Table410[[#This Row],[Jan_2027_F]]-Table410[[#This Row],[Jan_2027_A]] | DQ13: =IFERROR(Table410[[#This Row],[Feb_2027_Days_Forecast]]*Table410[[#This Row],[Cost Boolean]]*(VLOOKUP(Table410[[#This Row],[RATE CONCAT]],Tables!I:N,6,0)),0) | DR13: 0 | DS13: =Table410[[#This Row],[Feb_2027_F]]-Table410[[#This Row],[Feb_2027_A]] | DT13: =IFERROR(Table410[[#This Row],[Mar_2027_Days_Forecast]]*Table410[[#This Row],[Cost Boolean]]*(VLOOKUP(Table410[[#This Row],[RATE CONCAT]],Tables!I:N,6,0)),0) | DU13: 0 | DV13: =Table410[[#This Row],[Mar_2027_F]]-Table410[[#This Row],[Mar_2027_A]] | DW13: =IFERROR(Table410[[#This Row],[Apr_2027_Days_Forecast]]*Table410[[#This Row],[Cost Boolean]]*(VLOOKUP(Table410[[#This Row],[RATE CONCAT]],Tables!I:N,6,0)),0) | DX13: 0 | DY13: =Table410[[#This Row],[Apr_2027_F]]-Table410[[#This Row],[Apr_2027_A]] | DZ13: =IFERROR(Table410[[#This Row],[May_2027_Days_Forecast]]*Table410[[#This Row],[Cost Boolean]]*(VLOOKUP(Table410[[#This Row],[RATE CONCAT]],Tables!I:N,6,0)),0) | EA13: 0 | EB13: =Table410[[#This Row],[May_2027_F]]-Table410[[#This Row],[May_2027_A]] | EC13: =IFERROR(Table410[[#This Row],[Jun_2027_Days_Forecast]]*Table410[[#This Row],[Cost Boolean]]*(VLOOKUP(Table410[[#This Row],[RATE CONCAT]],Tables!I:N,6,0)),0) | ED13: 0 | EE13: =Table410[[#This Row],[Jun_2027_F]]-Table410[[#This Row],[Jun_2027_A]] | EF13: =IFERROR(Table410[[#This Row],[Jul_2027_Days_Forecast]]*Table410[[#This Row],[Cost Boolean]]*(VLOOKUP(Table410[[#This Row],[RATE CONCAT]],Tables!I:N,6,0)),0) | EG13: 0 | EH13: =Table410[[#This Row],[Jul_2027_F]]-Table410[[#This Row],[Jul_2027_A]] | EI13: =IFERROR(Table410[[#This Row],[Aug_2027_Days_Forecast]]*Table410[[#This Row],[Cost Boolean]]*(VLOOKUP(Table410[[#This Row],[RATE CONCAT]],Tables!I:N,6,0)),0) | EJ13: 0 | EK13: =Table410[[#This Row],[Aug_2027_F]]-Table410[[#This Row],[Aug_2027_A]] | EL13: =IFERROR(Table410[[#This Row],[Sep_2027_Days_Forecast]]*Table410[[#This Row],[Cost Boolean]]*(VLOOKUP(Table410[[#This Row],[RATE CONCAT]],Tables!I:N,6,0)),0) | EM13: 0 | EN13: =Table410[[#This Row],[Sep_2027_F]]-Table410[[#This Row],[Sep_2027_A]] | EO13: =IFERROR(Table410[[#This Row],[Oct_2027_Days_Forecast]]*Table410[[#This Row],[Cost Boolean]]*(VLOOKUP(Table410[[#This Row],[RATE CONCAT]],Tables!I:N,6,0)),0) | EP13: 0 | EQ13: =Table410[[#This Row],[Oct_2027_F]]-Table410[[#This Row],[Oct_2027_A]] | ER13: =IFERROR(Table410[[#This Row],[Nov_2027_Days_Forecast]]*Table410[[#This Row],[Cost Boolean]]*(VLOOKUP(Table410[[#This Row],[RATE CONCAT]],Tables!I:N,6,0)),0) | ES13: 0 | ET13: =Table410[[#This Row],[Nov_2027_F]]-Table410[[#This Row],[Nov_2027_A]] | EU13: =IFERROR(Table410[[#This Row],[Dec_2027_Days_Forecast]]*Table410[[#This Row],[Cost Boolean]]*(VLOOKUP(Table410[[#This Row],[RATE CONCAT]],Tables!I:N,6,0)),0) | EV13: 0 | EW13: =Table410[[#This Row],[Dec_2027_F]]-Table410[[#This Row],[Dec_2027_A]]
A14: PDSFS1012 | B14: Prosmar Products | C14: Staff | D14: Karina Toh | E14: Shell Business | G14: Singapore | H14: 4 | J14: Market Risk Analyst | K14: In-seat | L14: 1 | M14: SGP | N14: Market Risk | O14: Capex | P14: Business | Q14: TBD | R14: 46023 | S14: 46387 | T14: 46023 | U14: 46387 | V14: 46023 | W14: 46387 | Y14: =CONCATENATE(Table410[[#This Row],[JG]],Table410[[#This Row],[Country]],Table410[[#This Row],[Resource Provider]]) | Z14: =VLOOKUP(Table410[[#This Row],[RATE CONCAT]],Tables!I:N,5,0) | AB14: 10 | AC14: 10 | AD14: 10 | AE14: 10 | AF14: 9 | AG14: 9 | AH14: 9 | AI14: 10 | AJ14: 10 | AK14: 10 | AL14: 9 | AM14: 9 | AN14: =IFERROR(AVERAGE(Table410[[#This Row],[Jan_2026_Days_Forecast]:[Dec_2026_Days_Forecast]]),0)/19 | AO14: =IFERROR(AVERAGE(Table410[[#This Row],[Jan_2026_Days_Actual]:[Dec_2026_Days_Actual]]),0)/19 | AP14: 10 | AQ14: 10 | AR14: 10 | AS14: 10 | AT14: 9 | AU14: 9 | AV14: 9 | AW14: 10 | AX14: 10 | AY14: 10 | AZ14: 9 | BA14: 9 | BB14: =IFERROR(AVERAGE(Table410[[#This Row],[Jan_2027_Days_Forecast]:[Dec_2027_Days_Forecast]]),0) | BQ14: =IFERROR(Table410[[#This Row],[Jan_2026_Days_Forecast]]*Table410[[#This Row],[Cost Boolean]]*(VLOOKUP(Table410[[#This Row],[RATE CONCAT]],Tables!I:N,5,0)),0) | BR14: =IFERROR(Table410[[#This Row],[Jan_2026_Days_Actual]]*Table410[[#This Row],[Cost Boolean]]*(VLOOKUP(Table410[[#This Row],[RATE CONCAT]],Tables!I:N,5,0)),0) | BS14: =Table410[[#This Row],[Jan_2026_F]]-Table410[[#This Row],[Jan_2026_A]] | BU14: =IFERROR(Table410[[#This Row],[Feb_2026_Days_Forecast]]*Table410[[#This Row],[Cost Boolean]]*(VLOOKUP(Table410[[#This Row],[RATE CONCAT]],Tables!I:N,5,0)),0) | BW14: =Table410[[#This Row],[Feb_2026_F]]-Table410[[#This Row],[Feb_2026_A]] | BY14: =IFERROR(Table410[[#This Row],[Mar_2026_Days_Forecast]]*Table410[[#This Row],[Cost Boolean]]*(VLOOKUP(Table410[[#This Row],[RATE CONCAT]],Tables!I:N,5,0)),0) | CA14: =Table410[[#This Row],[Mar_2026_F]]-Table410[[#This Row],[Mar_2026_A]] | CC14: =IFERROR(Table410[[#This Row],[Apr_2026_Days_Forecast]]*Table410[[#This Row],[Cost Boolean]]*(VLOOKUP(Table410[[#This Row],[RATE CONCAT]],Tables!I:N,5,0)),0) | CE14: =Table410[[#This Row],[Apr_2026_F]]-Table410[[#This Row],[Apr_2026_A]] | CG14: =IFERROR(Table410[[#This Row],[May_2026_Days_Forecast]] *Table410[[#This Row],[Cost Boolean]]*(VLOOKUP(Table410[[#This Row],[RATE CONCAT]],Tables!I:N,5,0)),0) | CH14: =IFERROR(Table410[[#This Row],[May_2026_Days_Actual]]*Table410[[#This Row],[Cost Boolean]]*(VLOOKUP(Table410[[#This Row],[RATE CONCAT]],Tables!I:N,5,0)),0) | CI14: =Table410[[#This Row],[May_2026_F]]-Table410[[#This Row],[May_2026_A]] | CK14: =IFERROR(Table410[[#This Row],[Jun_2026_Days_Forecast]]*Table410[[#This Row],[Cost Boolean]]*(VLOOKUP(Table410[[#This Row],[RATE CONCAT]],Tables!I:N,5,0)),0) | CL14: =IFERROR(Table410[[#This Row],[Jun_2026_Days_Actual]]*Table410[[#This Row],[Cost Boolean]]*(VLOOKUP(Table410[[#This Row],[RATE CONCAT]],Tables!I:N,5,0)),0) | CM14: =Table410[[#This Row],[Jun_2026_F]]-Table410[[#This Row],[Jun_2026_A]] | CO14: =IFERROR(Table410[[#This Row],[Jul_2026_Days_Forecast]]*Table410[[#This Row],[Cost Boolean]]*(VLOOKUP(Table410[[#This Row],[RATE CONCAT]],Tables!I:N,5,0)),0) | CP14: =IFERROR(Table410[[#This Row],[Jul_2026_Days_Actual]]*Table410[[#This Row],[Cost Boolean]]*(VLOOKUP(Table410[[#This Row],[RATE CONCAT]],Tables!I:N,5,0)),0) | CQ14: =Table410[[#This Row],[Jul_2026_F]]-Table410[[#This Row],[Jul_2026_A]] | CS14: =IFERROR(Table410[[#This Row],[Aug_2026_Days_Forecast]]*Table410[[#This Row],[Cost Boolean]]*(VLOOKUP(Table410[[#This Row],[RATE CONCAT]],Tables!I:N,5,0)),0) | CT14: =IFERROR(Table410[[#This Row],[Aug_2026_Days_Actual]]*Table410[[#This Row],[Cost Boolean]]*(VLOOKUP(Table410[[#This Row],[RATE CONCAT]],Tables!I:N,5,0)),0) | CU14: =Table410[[#This Row],[Aug_2026_F]]-Table410[[#This Row],[Aug_2026_A]] | CW14: =IFERROR(Table410[[#This Row],[Sep_2026_Days_Forecast]]*Table410[[#This Row],[Cost Boolean]]*(VLOOKUP(Table410[[#This Row],[RATE CONCAT]],Tables!I:N,5,0)),0) | CX14: =IFERROR(Table410[[#This Row],[Sep_2026_Days_Actual]]*Table410[[#This Row],[Cost Boolean]]*(VLOOKUP(Table410[[#This Row],[RATE CONCAT]],Tables!I:N,5,0)),0) | CY14: =Table410[[#This Row],[Sep_2026_F]]-Table410[[#This Row],[Sep_2026_A]] | DA14: =IFERROR(Table410[[#This Row],[Oct_2026_Days_Forecast]]*Table410[[#This Row],[Cost Boolean]]*(VLOOKUP(Table410[[#This Row],[RATE CONCAT]],Tables!I:N,5,0)),0) | DB14: =IFERROR(Table410[[#This Row],[Oct_2026_Days_Actual]]*Table410[[#This Row],[Cost Boolean]]*(VLOOKUP(Table410[[#This Row],[RATE CONCAT]],Tables!I:N,5,0)),0) | DC14: =Table410[[#This Row],[Oct_2026_F]]-Table410[[#This Row],[Oct_2026_A]] | DE14: =IFERROR(Table410[[#This Row],[Nov_2026_Days_Forecast]]*Table410[[#This Row],[Cost Boolean]]*(VLOOKUP(Table410[[#This Row],[RATE CONCAT]],Tables!I:N,5,0)),0) | DF14: =IFERROR(Table410[[#This Row],[Nov_2026_Days_Actual]]*Table410[[#This Row],[Cost Boolean]]*(VLOOKUP(Table410[[#This Row],[RATE CONCAT]],Tables!I:N,5,0)),0) | DG14: =Table410[[#This Row],[Nov_2026_F]]-Table410[[#This Row],[Nov_2026_A]] | DI14: =IFERROR(Table410[[#This Row],[Dec_2026_Days_Forecast]]*Table410[[#This Row],[Cost Boolean]]*(VLOOKUP(Table410[[#This Row],[RATE CONCAT]],Tables!I:N,5,0)),0) | DJ14: =IFERROR(Table410[[#This Row],[Dec_2026_Days_Actual]]*Table410[[#This Row],[Cost Boolean]]*(VLOOKUP(Table410[[#This Row],[RATE CONCAT]],Tables!I:N,5,0)),0) | DK14: =Table410[[#This Row],[Dec_2026_F]]-Table410[[#This Row],[Dec_2026_A]] | DN14: =IFERROR(Table410[[#This Row],[Jan_2027_Days_Forecast]]*Table410[[#This Row],[Cost Boolean]]*(VLOOKUP(Table410[[#This Row],[RATE CONCAT]],Tables!I:N,6,0)),0) | DO14: 0 | DP14: =Table410[[#This Row],[Jan_2027_F]]-Table410[[#This Row],[Jan_2027_A]] | DQ14: =IFERROR(Table410[[#This Row],[Feb_2027_Days_Forecast]]*Table410[[#This Row],[Cost Boolean]]*(VLOOKUP(Table410[[#This Row],[RATE CONCAT]],Tables!I:N,6,0)),0) | DR14: 0 | DS14: =Table410[[#This Row],[Feb_2027_F]]-Table410[[#This Row],[Feb_2027_A]] | DT14: =IFERROR(Table410[[#This Row],[Mar_2027_Days_Forecast]]*Table410[[#This Row],[Cost Boolean]]*(VLOOKUP(Table410[[#This Row],[RATE CONCAT]],Tables!I:N,6,0)),0) | DU14: 0 | DV14: =Table410[[#This Row],[Mar_2027_F]]-Table410[[#This Row],[Mar_2027_A]] | DW14: =IFERROR(Table410[[#This Row],[Apr_2027_Days_Forecast]]*Table410[[#This Row],[Cost Boolean]]*(VLOOKUP(Table410[[#This Row],[RATE CONCAT]],Tables!I:N,6,0)),0) | DX14: 0 | DY14: =Table410[[#This Row],[Apr_2027_F]]-Table410[[#This Row],[Apr_2027_A]] | DZ14: =IFERROR(Table410[[#This Row],[May_2027_Days_Forecast]]*Table410[[#This Row],[Cost Boolean]]*(VLOOKUP(Table410[[#This Row],[RATE CONCAT]],Tables!I:N,6,0)),0) | EA14: 0 | EB14: =Table410[[#This Row],[May_2027_F]]-Table410[[#This Row],[May_2027_A]] | EC14: =IFERROR(Table410[[#This Row],[Jun_2027_Days_Forecast]]*Table410[[#This Row],[Cost Boolean]]*(VLOOKUP(Table410[[#This Row],[RATE CONCAT]],Tables!I:N,6,0)),0) | ED14: 0 | EE14: =Table410[[#This Row],[Jun_2027_F]]-Table410[[#This Row],[Jun_2027_A]] | EF14: =IFERROR(Table410[[#This Row],[Jul_2027_Days_Forecast]]*Table410[[#This Row],[Cost Boolean]]*(VLOOKUP(Table410[[#This Row],[RATE CONCAT]],Tables!I:N,6,0)),0) | EG14: 0 | EH14: =Table410[[#This Row],[Jul_2027_F]]-Table410[[#This Row],[Jul_2027_A]] | EI14: =IFERROR(Table410[[#This Row],[Aug_2027_Days_Forecast]]*Table410[[#This Row],[Cost Boolean]]*(VLOOKUP(Table410[[#This Row],[RATE CONCAT]],Tables!I:N,6,0)),0) | EJ14: 0 | EK14: =Table410[[#This Row],[Aug_2027_F]]-Table410[[#This Row],[Aug_2027_A]] | EL14: =IFERROR(Table410[[#This Row],[Sep_2027_Days_Forecast]]*Table410[[#This Row],[Cost Boolean]]*(VLOOKUP(Table410[[#This Row],[RATE CONCAT]],Tables!I:N,6,0)),0) | EM14: 0 | EN14: =Table410[[#This Row],[Sep_2027_F]]-Table410[[#This Row],[Sep_2027_A]] | EO14: =IFERROR(Table410[[#This Row],[Oct_2027_Days_Forecast]]*Table410[[#This Row],[Cost Boolean]]*(VLOOKUP(Table410[[#This Row],[RATE CONCAT]],Tables!I:N,6,0)),0) | EP14: 0 | EQ14: =Table410[[#This Row],[Oct_2027_F]]-Table410[[#This Row],[Oct_2027_A]] | ER14: =IFERROR(Table410[[#This Row],[Nov_2027_Days_Forecast]]*Table410[[#This Row],[Cost Boolean]]*(VLOOKUP(Table410[[#This Row],[RATE CONCAT]],Tables!I:N,6,0)),0) | ES14: 0 | ET14: =Table410[[#This Row],[Nov_2027_F]]-Table410[[#This Row],[Nov_2027_A]] | EU14: =IFERROR(Table410[[#This Row],[Dec_2027_Days_Forecast]]*Table410[[#This Row],[Cost Boolean]]*(VLOOKUP(Table410[[#This Row],[RATE CONCAT]],Tables!I:N,6,0)),0) | EV14: 0 | EW14: =Table410[[#This Row],[Dec_2027_F]]-Table410[[#This Row],[Dec_2027_A]]
A15: PDSFS1016 | B15: GATOR | C15: Staff | D15: Ding Luo | E15: Shell Business | G15: Netherlands | H15: 4 | J15: PDT Data Analyst | K15: In-seat | L15: 1 | M15: ROT | N15: Data integration | O15: Capex | P15: Business | Q15: TBD | R15: 46113 | S15: 46387 | T15: 46023 | U15: 46387 | V15: 46113 | W15: 46387 | Y15: =CONCATENATE(Table410[[#This Row],[JG]],Table410[[#This Row],[Country]],Table410[[#This Row],[Resource Provider]]) | Z15: =VLOOKUP(Table410[[#This Row],[RATE CONCAT]],Tables!I:N,5,0) | AE15: 5 | AF15: 5 | AG15: 4 | AH15: 5 | AI15: 5 | AN15: =IFERROR(AVERAGE(Table410[[#This Row],[Jan_2026_Days_Forecast]:[Dec_2026_Days_Forecast]]),0)/19 | AO15: =IFERROR(AVERAGE(Table410[[#This Row],[Jan_2026_Days_Actual]:[Dec_2026_Days_Actual]]),0)/19 | AS15: 5 | AT15: 5 | AU15: 4 | AV15: 5 | AW15: 5 | BB15: =IFERROR(AVERAGE(Table410[[#This Row],[Jan_2027_Days_Forecast]:[Dec_2027_Days_Forecast]]),0) | BQ15: =IFERROR(Table410[[#This Row],[Jan_2026_Days_Forecast]]*Table410[[#This Row],[Cost Boolean]]*(VLOOKUP(Table410[[#This Row],[RATE CONCAT]],Tables!I:N,5,0)),0) | BR15: =IFERROR(Table410[[#This Row],[Jan_2026_Days_Actual]]*Table410[[#This Row],[Cost Boolean]]*(VLOOKUP(Table410[[#This Row],[RATE CONCAT]],Tables!I:N,5,0)),0) | BS15: =Table410[[#This Row],[Jan_2026_F]]-Table410[[#This Row],[Jan_2026_A]] | BU15: =IFERROR(Table410[[#This Row],[Feb_2026_Days_Forecast]]*Table410[[#This Row],[Cost Boolean]]*(VLOOKUP(Table410[[#This Row],[RATE CONCAT]],Tables!I:N,5,0)),0) | BV15: =IFERROR(Table410[[#This Row],[Feb_2026_Days_Actual]]*Table410[[#This Row],[Cost Boolean]]*(VLOOKUP(Table410[[#This Row],[RATE CONCAT]],Tables!I:N,5,0)),0) | BW15: =Table410[[#This Row],[Feb_2026_F]]-Table410[[#This Row],[Feb_2026_A]] | BY15: =IFERROR(Table410[[#This Row],[Mar_2026_Days_Forecast]]*Table410[[#This Row],[Cost Boolean]]*(VLOOKUP(Table410[[#This Row],[RATE CONCAT]],Tables!I:N,5,0)),0) | BZ15: =IFERROR(Table410[[#This Row],[Mar_2026_Days_Actual]]*Table410[[#This Row],[Cost Boolean]]*(VLOOKUP(Table410[[#This Row],[RATE CONCAT]],Tables!I:N,5,0)),0) | CA15: =Table410[[#This Row],[Mar_2026_F]]-Table410[[#This Row],[Mar_2026_A]] | CC15: =IFERROR(Table410[[#This Row],[Apr_2026_Days_Forecast]]*Table410[[#This Row],[Cost Boolean]]*(VLOOKUP(Table410[[#This Row],[RATE CONCAT]],Tables!I:N,5,0)),0) | CD15: =IFERROR(Table410[[#This Row],[Apr_2026_Days_Actual]]*Table410[[#This Row],[Cost Boolean]]*(VLOOKUP(Table410[[#This Row],[RATE CONCAT]],Tables!I:N,5,0)),0) | CE15: =Table410[[#This Row],[Apr_2026_F]]-Table410[[#This Row],[Apr_2026_A]] | CG15: =IFERROR(Table410[[#This Row],[May_2026_Days_Forecast]] *Table410[[#This Row],[Cost Boolean]]*(VLOOKUP(Table410[[#This Row],[RATE CONCAT]],Tables!I:N,5,0)),0) | CH15: =IFERROR(Table410[[#This Row],[May_2026_Days_Actual]]*Table410[[#This Row],[Cost Boolean]]*(VLOOKUP(Table410[[#This Row],[RATE CONCAT]],Tables!I:N,5,0)),0) | CI15: =Table410[[#This Row],[May_2026_F]]-Table410[[#This Row],[May_2026_A]] | CK15: =IFERROR(Table410[[#This Row],[Jun_2026_Days_Forecast]]*Table410[[#This Row],[Cost Boolean]]*(VLOOKUP(Table410[[#This Row],[RATE CONCAT]],Tables!I:N,5,0)),0) | CL15: =IFERROR(Table410[[#This Row],[Jun_2026_Days_Actual]]*Table410[[#This Row],[Cost Boolean]]*(VLOOKUP(Table410[[#This Row],[RATE CONCAT]],Tables!I:N,5,0)),0) | CM15: =Table410[[#This Row],[Jun_2026_F]]-Table410[[#This Row],[Jun_2026_A]] | CO15: =IFERROR(Table410[[#This Row],[Jul_2026_Days_Forecast]]*Table410[[#This Row],[Cost Boolean]]*(VLOOKUP(Table410[[#This Row],[RATE CONCAT]],Tables!I:N,5,0)),0) | CP15: =IFERROR(Table410[[#This Row],[Jul_2026_Days_Actual]]*Table410[[#This Row],[Cost Boolean]]*(VLOOKUP(Table410[[#This Row],[RATE CONCAT]],Tables!I:N,5,0)),0) | CQ15: =Table410[[#This Row],[Jul_2026_F]]-Table410[[#This Row],[Jul_2026_A]] | CS15: =IFERROR(Table410[[#This Row],[Aug_2026_Days_Forecast]]*Table410[[#This Row],[Cost Boolean]]*(VLOOKUP(Table410[[#This Row],[RATE CONCAT]],Tables!I:N,5,0)),0) | CT15: =IFERROR(Table410[[#This Row],[Aug_2026_Days_Actual]]*Table410[[#This Row],[Cost Boolean]]*(VLOOKUP(Table410[[#This Row],[RATE CONCAT]],Tables!I:N,5,0)),0) | CU15: =Table410[[#This Row],[Aug_2026_F]]-Table410[[#This Row],[Aug_2026_A]] | CW15: =IFERROR(Table410[[#This Row],[Sep_2026_Days_Forecast]]*Table410[[#This Row],[Cost Boolean]]*(VLOOKUP(Table410[[#This Row],[RATE CONCAT]],Tables!I:N,5,0)),0) | CX15: =IFERROR(Table410[[#This Row],[Sep_2026_Days_Actual]]*Table410[[#This Row],[Cost Boolean]]*(VLOOKUP(Table410[[#This Row],[RATE CONCAT]],Tables!I:N,5,0)),0) | CY15: =Table410[[#This Row],[Sep_2026_F]]-Table410[[#This Row],[Sep_2026_A]] | DA15: =IFERROR(Table410[[#This Row],[Oct_2026_Days_Forecast]]*Table410[[#This Row],[Cost Boolean]]*(VLOOKUP(Table410[[#This Row],[RATE CONCAT]],Tables!I:N,5,0)),0) | DB15: =IFERROR(Table410[[#This Row],[Oct_2026_Days_Actual]]*Table410[[#This Row],[Cost Boolean]]*(VLOOKUP(Table410[[#This Row],[RATE CONCAT]],Tables!I:N,5,0)),0) | DC15: =Table410[[#This Row],[Oct_2026_F]]-Table410[[#This Row],[Oct_2026_A]] | DE15: =IFERROR(Table410[[#This Row],[Nov_2026_Days_Forecast]]*Table410[[#This Row],[Cost Boolean]]*(VLOOKUP(Table410[[#This Row],[RATE CONCAT]],Tables!I:N,5,0)),0) | DF15: =IFERROR(Table410[[#This Row],[Nov_2026_Days_Actual]]*Table410[[#This Row],[Cost Boolean]]*(VLOOKUP(Table410[[#This Row],[RATE CONCAT]],Tables!I:N,5,0)),0) | DG15: =Table410[[#This Row],[Nov_2026_F]]-Table410[[#This Row],[Nov_2026_A]] | DI15: =IFERROR(Table410[[#This Row],[Dec_2026_Days_Forecast]]*Table410[[#This Row],[Cost Boolean]]*(VLOOKUP(Table410[[#This Row],[RATE CONCAT]],Tables!I:N,5,0)),0) | DJ15: =IFERROR(Table410[[#This Row],[Dec_2026_Days_Actual]]*Table410[[#This Row],[Cost Boolean]]*(VLOOKUP(Table410[[#This Row],[RATE CONCAT]],Tables!I:N,5,0)),0) | DK15: =Table410[[#This Row],[Dec_2026_F]]-Table410[[#This Row],[Dec_2026_A]] | DN15: =IFERROR(Table410[[#This Row],[Jan_2027_Days_Forecast]]*Table410[[#This Row],[Cost Boolean]]*(VLOOKUP(Table410[[#This Row],[RATE CONCAT]],Tables!I:N,6,0)),0) | DO15: 0 | DP15: =Table410[[#This Row],[Jan_2027_F]]-Table410[[#This Row],[Jan_2027_A]] | DQ15: =IFERROR(Table410[[#This Row],[Feb_2027_Days_Forecast]]*Table410[[#This Row],[Cost Boolean]]*(VLOOKUP(Table410[[#This Row],[RATE CONCAT]],Tables!I:N,6,0)),0) | DR15: 0 | DS15: =Table410[[#This Row],[Feb_2027_F]]-Table410[[#This Row],[Feb_2027_A]] | DT15: =IFERROR(Table410[[#This Row],[Mar_2027_Days_Forecast]]*Table410[[#This Row],[Cost Boolean]]*(VLOOKUP(Table410[[#This Row],[RATE CONCAT]],Tables!I:N,6,0)),0) | DU15: 0 | DV15: =Table410[[#This Row],[Mar_2027_F]]-Table410[[#This Row],[Mar_2027_A]] | DW15: =IFERROR(Table410[[#This Row],[Apr_2027_Days_Forecast]]*Table410[[#This Row],[Cost Boolean]]*(VLOOKUP(Table410[[#This Row],[RATE CONCAT]],Tables!I:N,6,0)),0) | DX15: 0 | DY15: =Table410[[#This Row],[Apr_2027_F]]-Table410[[#This Row],[Apr_2027_A]] | DZ15: =IFERROR(Table410[[#This Row],[May_2027_Days_Forecast]]*Table410[[#This Row],[Cost Boolean]]*(VLOOKUP(Table410[[#This Row],[RATE CONCAT]],Tables!I:N,6,0)),0) | EA15: 0 | EB15: =Table410[[#This Row],[May_2027_F]]-Table410[[#This Row],[May_2027_A]] | EC15: =IFERROR(Table410[[#This Row],[Jun_2027_Days_Forecast]]*Table410[[#This Row],[Cost Boolean]]*(VLOOKUP(Table410[[#This Row],[RATE CONCAT]],Tables!I:N,6,0)),0) | ED15: 0 | EE15: =Table410[[#This Row],[Jun_2027_F]]-Table410[[#This Row],[Jun_2027_A]] | EF15: =IFERROR(Table410[[#This Row],[Jul_2027_Days_Forecast]]*Table410[[#This Row],[Cost Boolean]]*(VLOOKUP(Table410[[#This Row],[RATE CONCAT]],Tables!I:N,6,0)),0) | EG15: 0 | EH15: =Table410[[#This Row],[Jul_2027_F]]-Table410[[#This Row],[Jul_2027_A]] | EI15: =IFERROR(Table410[[#This Row],[Aug_2027_Days_Forecast]]*Table410[[#This Row],[Cost Boolean]]*(VLOOKUP(Table410[[#This Row],[RATE CONCAT]],Tables!I:N,6,0)),0) | EJ15: 0 | EK15: =Table410[[#This Row],[Aug_2027_F]]-Table410[[#This Row],[Aug_2027_A]] | EL15: =IFERROR(Table410[[#This Row],[Sep_2027_Days_Forecast]]*Table410[[#This Row],[Cost Boolean]]*(VLOOKUP(Table410[[#This Row],[RATE CONCAT]],Tables!I:N,6,0)),0) | EM15: 0 | EN15: =Table410[[#This Row],[Sep_2027_F]]-Table410[[#This Row],[Sep_2027_A]] | EO15: =IFERROR(Table410[[#This Row],[Oct_2027_Days_Forecast]]*Table410[[#This Row],[Cost Boolean]]*(VLOOKUP(Table410[[#This Row],[RATE CONCAT]],Tables!I:N,6,0)),0) | EP15: 0 | EQ15: =Table410[[#This Row],[Oct_2027_F]]-Table410[[#This Row],[Oct_2027_A]] | ER15: =IFERROR(Table410[[#This Row],[Nov_2027_Days_Forecast]]*Table410[[#This Row],[Cost Boolean]]*(VLOOKUP(Table410[[#This Row],[RATE CONCAT]],Tables!I:N,6,0)),0) | ES15: 0 | ET15: =Table410[[#This Row],[Nov_2027_F]]-Table410[[#This Row],[Nov_2027_A]] | EU15: =IFERROR(Table410[[#This Row],[Dec_2027_Days_Forecast]]*Table410[[#This Row],[Cost Boolean]]*(VLOOKUP(Table410[[#This Row],[RATE CONCAT]],Tables!I:N,6,0)),0) | EV15: 0 | EW15: =Table410[[#This Row],[Dec_2027_F]]-Table410[[#This Row],[Dec_2027_A]]
A16: PDSFS1019 | B16: GATOR | C16: Staff | D16: Daniel Harlow | E16: Shell Business | G16: United States | H16: 4 | J16: Charterer | K16: In-seat | L16: 1 | M16: HOU | N16: Chartering | O16: Capex | P16: Business | Q16: TBD | R16: 46023 | S16: 46387 | T16: 46023 | U16: 46387 | V16: 46023 | W16: 46387 | Y16: =CONCATENATE(Table410[[#This Row],[JG]],Table410[[#This Row],[Country]],Table410[[#This Row],[Resource Provider]]) | Z16: =VLOOKUP(Table410[[#This Row],[RATE CONCAT]],Tables!I:N,5,0) | AB16: 5 | AC16: 5 | AD16: 5 | AE16: 5 | AF16: 5 | AG16: 4 | AH16: 5 | AI16: 5 | AJ16: 5 | AK16: 5 | AL16: 5 | AM16: 4 | AN16: =IFERROR(AVERAGE(Table410[[#This Row],[Jan_2026_Days_Forecast]:[Dec_2026_Days_Forecast]]),0)/19 | AO16: =IFERROR(AVERAGE(Table410[[#This Row],[Jan_2026_Days_Actual]:[Dec_2026_Days_Actual]]),0)/19 | AP16: 5 | AQ16: 5 | AR16: 5 | AS16: 5 | AT16: 5 | AU16: 4 | AV16: 5 | AW16: 5 | AX16: 5 | AY16: 5 | AZ16: 5 | BA16: 4 | BB16: =IFERROR(AVERAGE(Table410[[#This Row],[Jan_2027_Days_Forecast]:[Dec_2027_Days_Forecast]]),0) | BQ16: =IFERROR(Table410[[#This Row],[Jan_2026_Days_Forecast]]*Table410[[#This Row],[Cost Boolean]]*(VLOOKUP(Table410[[#This Row],[RATE CONCAT]],Tables!I:N,5,0)),0) | BR16: =IFERROR(Table410[[#This Row],[Jan_2026_Days_Actual]]*Table410[[#This Row],[Cost Boolean]]*(VLOOKUP(Table410[[#This Row],[RATE CONCAT]],Tables!I:N,5,0)),0) | BS16: =Table410[[#This Row],[Jan_2026_F]]-Table410[[#This Row],[Jan_2026_A]] | BU16: =IFERROR(Table410[[#This Row],[Feb_2026_Days_Forecast]]*Table410[[#This Row],[Cost Boolean]]*(VLOOKUP(Table410[[#This Row],[RATE CONCAT]],Tables!I:N,5,0)),0) | BV16: =IFERROR(Table410[[#This Row],[Feb_2026_Days_Actual]]*Table410[[#This Row],[Cost Boolean]]*(VLOOKUP(Table410[[#This Row],[RATE CONCAT]],Tables!I:N,5,0)),0) | BW16: =Table410[[#This Row],[Feb_2026_F]]-Table410[[#This Row],[Feb_2026_A]] | BY16: =IFERROR(Table410[[#This Row],[Mar_2026_Days_Forecast]]*Table410[[#This Row],[Cost Boolean]]*(VLOOKUP(Table410[[#This Row],[RATE CONCAT]],Tables!I:N,5,0)),0) | BZ16: =IFERROR(Table410[[#This Row],[Mar_2026_Days_Actual]]*Table410[[#This Row],[Cost Boolean]]*(VLOOKUP(Table410[[#This Row],[RATE CONCAT]],Tables!I:N,5,0)),0) | CA16: =Table410[[#This Row],[Mar_2026_F]]-Table410[[#This Row],[Mar_2026_A]] | CC16: =IFERROR(Table410[[#This Row],[Apr_2026_Days_Forecast]]*Table410[[#This Row],[Cost Boolean]]*(VLOOKUP(Table410[[#This Row],[RATE CONCAT]],Tables!I:N,5,0)),0) | CD16: =IFERROR(Table410[[#This Row],[Apr_2026_Days_Actual]]*Table410[[#This Row],[Cost Boolean]]*(VLOOKUP(Table410[[#This Row],[RATE CONCAT]],Tables!I:N,5,0)),0) | CE16: =Table410[[#This Row],[Apr_2026_F]]-Table410[[#This Row],[Apr_2026_A]] | CG16: =IFERROR(Table410[[#This Row],[May_2026_Days_Forecast]] *Table410[[#This Row],[Cost Boolean]]*(VLOOKUP(Table410[[#This Row],[RATE CONCAT]],Tables!I:N,5,0)),0) | CH16: =IFERROR(Table410[[#This Row],[May_2026_Days_Actual]]*Table410[[#This Row],[Cost Boolean]]*(VLOOKUP(Table410[[#This Row],[RATE CONCAT]],Tables!I:N,5,0)),0) | CI16: =Table410[[#This Row],[May_2026_F]]-Table410[[#This Row],[May_2026_A]] | CK16: =IFERROR(Table410[[#This Row],[Jun_2026_Days_Forecast]]*Table410[[#This Row],[Cost Boolean]]*(VLOOKUP(Table410[[#This Row],[RATE CONCAT]],Tables!I:N,5,0)),0) | CL16: =IFERROR(Table410[[#This Row],[Jun_2026_Days_Actual]]*Table410[[#This Row],[Cost Boolean]]*(VLOOKUP(Table410[[#This Row],[RATE CONCAT]],Tables!I:N,5,0)),0) | CM16: =Table410[[#This Row],[Jun_2026_F]]-Table410[[#This Row],[Jun_2026_A]] | CO16: =IFERROR(Table410[[#This Row],[Jul_2026_Days_Forecast]]*Table410[[#This Row],[Cost Boolean]]*(VLOOKUP(Table410[[#This Row],[RATE CONCAT]],Tables!I:N,5,0)),0) | CP16: =IFERROR(Table410[[#This Row],[Jul_2026_Days_Actual]]*Table410[[#This Row],[Cost Boolean]]*(VLOOKUP(Table410[[#This Row],[RATE CONCAT]],Tables!I:N,5,0)),0) | CQ16: =Table410[[#This Row],[Jul_2026_F]]-Table410[[#This Row],[Jul_2026_A]] | CS16: =IFERROR(Table410[[#This Row],[Aug_2026_Days_Forecast]]*Table410[[#This Row],[Cost Boolean]]*(VLOOKUP(Table410[[#This Row],[RATE CONCAT]],Tables!I:N,5,0)),0) | CT16: =IFERROR(Table410[[#This Row],[Aug_2026_Days_Actual]]*Table410[[#This Row],[Cost Boolean]]*(VLOOKUP(Table410[[#This Row],[RATE CONCAT]],Tables!I:N,5,0)),0) | CU16: =Table410[[#This Row],[Aug_2026_F]]-Table410[[#This Row],[Aug_2026_A]] | CW16: =IFERROR(Table410[[#This Row],[Sep_2026_Days_Forecast]]*Table410[[#This Row],[Cost Boolean]]*(VLOOKUP(Table410[[#This Row],[RATE CONCAT]],Tables!I:N,5,0)),0) | CX16: =IFERROR(Table410[[#This Row],[Sep_2026_Days_Actual]]*Table410[[#This Row],[Cost Boolean]]*(VLOOKUP(Table410[[#This Row],[RATE CONCAT]],Tables!I:N,5,0)),0) | CY16: =Table410[[#This Row],[Sep_2026_F]]-Table410[[#This Row],[Sep_2026_A]] | DA16: =IFERROR(Table410[[#This Row],[Oct_2026_Days_Forecast]]*Table410[[#This Row],[Cost Boolean]]*(VLOOKUP(Table410[[#This Row],[RATE CONCAT]],Tables!I:N,5,0)),0) | DB16: =IFERROR(Table410[[#This Row],[Oct_2026_Days_Actual]]*Table410[[#This Row],[Cost Boolean]]*(VLOOKUP(Table410[[#This Row],[RATE CONCAT]],Tables!I:N,5,0)),0) | DC16: =Table410[[#This Row],[Oct_2026_F]]-Table410[[#This Row],[Oct_2026_A]] | DE16: =IFERROR(Table410[[#This Row],[Nov_2026_Days_Forecast]]*Table410[[#This Row],[Cost Boolean]]*(VLOOKUP(Table410[[#This Row],[RATE CONCAT]],Tables!I:N,5,0)),0) | DF16: =IFERROR(Table410[[#This Row],[Nov_2026_Days_Actual]]*Table410[[#This Row],[Cost Boolean]]*(VLOOKUP(Table410[[#This Row],[RATE CONCAT]],Tables!I:N,5,0)),0) | DG16: =Table410[[#This Row],[Nov_2026_F]]-Table410[[#This Row],[Nov_2026_A]] | DI16: =IFERROR(Table410[[#This Row],[Dec_2026_Days_Forecast]]*Table410[[#This Row],[Cost Boolean]]*(VLOOKUP(Table410[[#This Row],[RATE CONCAT]],Tables!I:N,5,0)),0) | DJ16: =IFERROR(Table410[[#This Row],[Dec_2026_Days_Actual]]*Table410[[#This Row],[Cost Boolean]]*(VLOOKUP(Table410[[#This Row],[RATE CONCAT]],Tables!I:N,5,0)),0) | DK16: =Table410[[#This Row],[Dec_2026_F]]-Table410[[#This Row],[Dec_2026_A]] | DN16: =IFERROR(Table410[[#This Row],[Jan_2027_Days_Forecast]]*Table410[[#This Row],[Cost Boolean]]*(VLOOKUP(Table410[[#This Row],[RATE CONCAT]],Tables!I:N,6,0)),0) | DO16: 0 | DP16: =Table410[[#This Row],[Jan_2027_F]]-Table410[[#This Row],[Jan_2027_A]] | DQ16: =IFERROR(Table410[[#This Row],[Feb_2027_Days_Forecast]]*Table410[[#This Row],[Cost Boolean]]*(VLOOKUP(Table410[[#This Row],[RATE CONCAT]],Tables!I:N,6,0)),0) | DR16: 0 | DS16: =Table410[[#This Row],[Feb_2027_F]]-Table410[[#This Row],[Feb_2027_A]] | DT16: =IFERROR(Table410[[#This Row],[Mar_2027_Days_Forecast]]*Table410[[#This Row],[Cost Boolean]]*(VLOOKUP(Table410[[#This Row],[RATE CONCAT]],Tables!I:N,6,0)),0) | DU16: 0 | DV16: =Table410[[#This Row],[Mar_2027_F]]-Table410[[#This Row],[Mar_2027_A]] | DW16: =IFERROR(Table410[[#This Row],[Apr_2027_Days_Forecast]]*Table410[[#This Row],[Cost Boolean]]*(VLOOKUP(Table410[[#This Row],[RATE CONCAT]],Tables!I:N,6,0)),0) | DX16: 0 | DY16: =Table410[[#This Row],[Apr_2027_F]]-Table410[[#This Row],[Apr_2027_A]] | DZ16: =IFERROR(Table410[[#This Row],[May_2027_Days_Forecast]]*Table410[[#This Row],[Cost Boolean]]*(VLOOKUP(Table410[[#This Row],[RATE CONCAT]],Tables!I:N,6,0)),0) | EA16: 0 | EB16: =Table410[[#This Row],[May_2027_F]]-Table410[[#This Row],[May_2027_A]] | EC16: =IFERROR(Table410[[#This Row],[Jun_2027_Days_Forecast]]*Table410[[#This Row],[Cost Boolean]]*(VLOOKUP(Table410[[#This Row],[RATE CONCAT]],Tables!I:N,6,0)),0) | ED16: 0 | EE16: =Table410[[#This Row],[Jun_2027_F]]-Table410[[#This Row],[Jun_2027_A]] | EF16: =IFERROR(Table410[[#This Row],[Jul_2027_Days_Forecast]]*Table410[[#This Row],[Cost Boolean]]*(VLOOKUP(Table410[[#This Row],[RATE CONCAT]],Tables!I:N,6,0)),0) | EG16: 0 | EH16: =Table410[[#This Row],[Jul_2027_F]]-Table410[[#This Row],[Jul_2027_A]] | EI16: =IFERROR(Table410[[#This Row],[Aug_2027_Days_Forecast]]*Table410[[#This Row],[Cost Boolean]]*(VLOOKUP(Table410[[#This Row],[RATE CONCAT]],Tables!I:N,6,0)),0) | EJ16: 0 | EK16: =Table410[[#This Row],[Aug_2027_F]]-Table410[[#This Row],[Aug_2027_A]] | EL16: =IFERROR(Table410[[#This Row],[Sep_2027_Days_Forecast]]*Table410[[#This Row],[Cost Boolean]]*(VLOOKUP(Table410[[#This Row],[RATE CONCAT]],Tables!I:N,6,0)),0) | EM16: 0 | EN16: =Table410[[#This Row],[Sep_2027_F]]-Table410[[#This Row],[Sep_2027_A]] | EO16: =IFERROR(Table410[[#This Row],[Oct_2027_Days_Forecast]]*Table410[[#This Row],[Cost Boolean]]*(VLOOKUP(Table410[[#This Row],[RATE CONCAT]],Tables!I:N,6,0)),0) | EP16: 0 | EQ16: =Table410[[#This Row],[Oct_2027_F]]-Table410[[#This Row],[Oct_2027_A]] | ER16: =IFERROR(Table410[[#This Row],[Nov_2027_Days_Forecast]]*Table410[[#This Row],[Cost Boolean]]*(VLOOKUP(Table410[[#This Row],[RATE CONCAT]],Tables!I:N,6,0)),0) | ES16: 0 | ET16: =Table410[[#This Row],[Nov_2027_F]]-Table410[[#This Row],[Nov_2027_A]] | EU16: =IFERROR(Table410[[#This Row],[Dec_2027_Days_Forecast]]*Table410[[#This Row],[Cost Boolean]]*(VLOOKUP(Table410[[#This Row],[RATE CONCAT]],Tables!I:N,6,0)),0) | EV16: 0 | EW16: =Table410[[#This Row],[Dec_2027_F]]-Table410[[#This Row],[Dec_2027_A]]
A17: PDSFS1024 | B17: DA Desk | C17: Staff | D17: Anishka Irving | E17: Shell Business | G17: United Kingdom | H17: 4 | J17: Finance Lead | K17: In-seat | L17: 0 | M17: LON | N17: Finance | O17: Opex | P17: Business | Q17: TBD | R17: 46023 | S17: 46387 | T17: 46023 | U17: 46387 | V17: 46023 | W17: 46387 | Y17: =CONCATENATE(Table410[[#This Row],[JG]],Table410[[#This Row],[Country]],Table410[[#This Row],[Resource Provider]]) | Z17: =VLOOKUP(Table410[[#This Row],[RATE CONCAT]],Tables!I:N,5,0) | AB17: 5 | AC17: 5 | AD17: 5 | AE17: 5 | AF17: 5 | AG17: 4 | AH17: 5 | AI17: 5 | AN17: =IFERROR(AVERAGE(Table410[[#This Row],[Jan_2026_Days_Forecast]:[Dec_2026_Days_Forecast]]),0)/19 | AO17: =IFERROR(AVERAGE(Table410[[#This Row],[Jan_2026_Days_Actual]:[Dec_2026_Days_Actual]]),0)/19 | AP17: 5 | AQ17: 5 | AR17: 5 | AS17: 5 | AT17: 5 | AU17: 4 | AV17: 5 | AW17: 5 | BB17: =IFERROR(AVERAGE(Table410[[#This Row],[Jan_2027_Days_Forecast]:[Dec_2027_Days_Forecast]]),0) | BQ17: =IFERROR(Table410[[#This Row],[Jan_2026_Days_Forecast]]*Table410[[#This Row],[Cost Boolean]]*(VLOOKUP(Table410[[#This Row],[RATE CONCAT]],Tables!I:N,5,0)),0) | BR17: =IFERROR(Table410[[#This Row],[Jan_2026_Days_Actual]]*Table410[[#This Row],[Cost Boolean]]*(VLOOKUP(Table410[[#This Row],[RATE CONCAT]],Tables!I:N,5,0)),0) | BS17: =Table410[[#This Row],[Jan_2026_F]]-Table410[[#This Row],[Jan_2026_A]] | BU17: =IFERROR(Table410[[#This Row],[Feb_2026_Days_Forecast]]*Table410[[#This Row],[Cost Boolean]]*(VLOOKUP(Table410[[#This Row],[RATE CONCAT]],Tables!I:N,5,0)),0) | BV17: =IFERROR(Table410[[#This Row],[Feb_2026_Days_Actual]]*Table410[[#This Row],[Cost Boolean]]*(VLOOKUP(Table410[[#This Row],[RATE CONCAT]],Tables!I:N,5,0)),0) | BW17: =Table410[[#This Row],[Feb_2026_F]]-Table410[[#This Row],[Feb_2026_A]] | BY17: =IFERROR(Table410[[#This Row],[Mar_2026_Days_Forecast]]*Table410[[#This Row],[Cost Boolean]]*(VLOOKUP(Table410[[#This Row],[RATE CONCAT]],Tables!I:N,5,0)),0) | BZ17: =IFERROR(Table410[[#This Row],[Mar_2026_Days_Actual]]*Table410[[#This Row],[Cost Boolean]]*(VLOOKUP(Table410[[#This Row],[RATE CONCAT]],Tables!I:N,5,0)),0) | CA17: =Table410[[#This Row],[Mar_2026_F]]-Table410[[#This Row],[Mar_2026_A]] | CC17: =IFERROR(Table410[[#This Row],[Apr_2026_Days_Forecast]]*Table410[[#This Row],[Cost Boolean]]*(VLOOKUP(Table410[[#This Row],[RATE CONCAT]],Tables!I:N,5,0)),0) | CD17: =IFERROR(Table410[[#This Row],[Apr_2026_Days_Actual]]*Table410[[#This Row],[Cost Boolean]]*(VLOOKUP(Table410[[#This Row],[RATE CONCAT]],Tables!I:N,5,0)),0) | CE17: =Table410[[#This Row],[Apr_2026_F]]-Table410[[#This Row],[Apr_2026_A]] | CG17: =IFERROR(Table410[[#This Row],[May_2026_Days_Forecast]] *Table410[[#This Row],[Cost Boolean]]*(VLOOKUP(Table410[[#This Row],[RATE CONCAT]],Tables!I:N,5,0)),0) | CH17: =IFERROR(Table410[[#This Row],[May_2026_Days_Actual]]*Table410[[#This Row],[Cost Boolean]]*(VLOOKUP(Table410[[#This Row],[RATE CONCAT]],Tables!I:N,5,0)),0) | CI17: =Table410[[#This Row],[May_2026_F]]-Table410[[#This Row],[May_2026_A]] | CK17: =IFERROR(Table410[[#This Row],[Jun_2026_Days_Forecast]]*Table410[[#This Row],[Cost Boolean]]*(VLOOKUP(Table410[[#This Row],[RATE CONCAT]],Tables!I:N,5,0)),0) | CL17: =IFERROR(Table410[[#This Row],[Jun_2026_Days_Actual]]*Table410[[#This Row],[Cost Boolean]]*(VLOOKUP(Table410[[#This Row],[RATE CONCAT]],Tables!I:N,5,0)),0) | CM17: =Table410[[#This Row],[Jun_2026_F]]-Table410[[#This Row],[Jun_2026_A]] | CO17: =IFERROR(Table410[[#This Row],[Jul_2026_Days_Forecast]]*Table410[[#This Row],[Cost Boolean]]*(VLOOKUP(Table410[[#This Row],[RATE CONCAT]],Tables!I:N,5,0)),0) | CP17: =IFERROR(Table410[[#This Row],[Jul_2026_Days_Actual]]*Table410[[#This Row],[Cost Boolean]]*(VLOOKUP(Table410[[#This Row],[RATE CONCAT]],Tables!I:N,5,0)),0) | CQ17: =Table410[[#This Row],[Jul_2026_F]]-Table410[[#This Row],[Jul_2026_A]] | CS17: =IFERROR(Table410[[#This Row],[Aug_2026_Days_Forecast]]*Table410[[#This Row],[Cost Boolean]]*(VLOOKUP(Table410[[#This Row],[RATE CONCAT]],Tables!I:N,5,0)),0) | CT17: =IFERROR(Table410[[#This Row],[Aug_2026_Days_Actual]]*Table410[[#This Row],[Cost Boolean]]*(VLOOKUP(Table410[[#This Row],[RATE CONCAT]],Tables!I:N,5,0)),0) | CU17: =Table410[[#This Row],[Aug_2026_F]]-Table410[[#This Row],[Aug_2026_A]] | CW17: =IFERROR(Table410[[#This Row],[Sep_2026_Days_Forecast]]*Table410[[#This Row],[Cost Boolean]]*(VLOOKUP(Table410[[#This Row],[RATE CONCAT]],Tables!I:N,5,0)),0) | CX17: =IFERROR(Table410[[#This Row],[Sep_2026_Days_Actual]]*Table410[[#This Row],[Cost Boolean]]*(VLOOKUP(Table410[[#This Row],[RATE CONCAT]],Tables!I:N,5,0)),0) | CY17: =Table410[[#This Row],[Sep_2026_F]]-Table410[[#This Row],[Sep_2026_A]] | DA17: =IFERROR(Table410[[#This Row],[Oct_2026_Days_Forecast]]*Table410[[#This Row],[Cost Boolean]]*(VLOOKUP(Table410[[#This Row],[RATE CONCAT]],Tables!I:N,5,0)),0) | DB17: =IFERROR(Table410[[#This Row],[Oct_2026_Days_Actual]]*Table410[[#This Row],[Cost Boolean]]*(VLOOKUP(Table410[[#This Row],[RATE CONCAT]],Tables!I:N,5,0)),0) | DC17: =Table410[[#This Row],[Oct_2026_F]]-Table410[[#This Row],[Oct_2026_A]] | DE17: =IFERROR(Table410[[#This Row],[Nov_2026_Days_Forecast]]*Table410[[#This Row],[Cost Boolean]]*(VLOOKUP(Table410[[#This Row],[RATE CONCAT]],Tables!I:N,5,0)),0) | DF17: =IFERROR(Table410[[#This Row],[Nov_2026_Days_Actual]]*Table410[[#This Row],[Cost Boolean]]*(VLOOKUP(Table410[[#This Row],[RATE CONCAT]],Tables!I:N,5,0)),0) | DG17: =Table410[[#This Row],[Nov_2026_F]]-Table410[[#This Row],[Nov_2026_A]] | DI17: =IFERROR(Table410[[#This Row],[Dec_2026_Days_Forecast]]*Table410[[#This Row],[Cost Boolean]]*(VLOOKUP(Table410[[#This Row],[RATE CONCAT]],Tables!I:N,5,0)),0) | DJ17: =IFERROR(Table410[[#This Row],[Dec_2026_Days_Actual]]*Table410[[#This Row],[Cost Boolean]]*(VLOOKUP(Table410[[#This Row],[RATE CONCAT]],Tables!I:N,5,0)),0) | DK17: =Table410[[#This Row],[Dec_2026_F]]-Table410[[#This Row],[Dec_2026_A]] | DN17: =IFERROR(Table410[[#This Row],[Jan_2027_Days_Forecast]]*Table410[[#This Row],[Cost Boolean]]*(VLOOKUP(Table410[[#This Row],[RATE CONCAT]],Tables!I:N,6,0)),0) | DO17: 0 | DP17: =Table410[[#This Row],[Jan_2027_F]]-Table410[[#This Row],[Jan_2027_A]] | DQ17: =IFERROR(Table410[[#This Row],[Feb_2027_Days_Forecast]]*Table410[[#This Row],[Cost Boolean]]*(VLOOKUP(Table410[[#This Row],[RATE CONCAT]],Tables!I:N,6,0)),0) | DR17: 0 | DS17: =Table410[[#This Row],[Feb_2027_F]]-Table410[[#This Row],[Feb_2027_A]] | DT17: =IFERROR(Table410[[#This Row],[Mar_2027_Days_Forecast]]*Table410[[#This Row],[Cost Boolean]]*(VLOOKUP(Table410[[#This Row],[RATE CONCAT]],Tables!I:N,6,0)),0) | DU17: 0 | DV17: =Table410[[#This Row],[Mar_2027_F]]-Table410[[#This Row],[Mar_2027_A]] | DW17: =IFERROR(Table410[[#This Row],[Apr_2027_Days_Forecast]]*Table410[[#This Row],[Cost Boolean]]*(VLOOKUP(Table410[[#This Row],[RATE CONCAT]],Tables!I:N,6,0)),0) | DX17: 0 | DY17: =Table410[[#This Row],[Apr_2027_F]]-Table410[[#This Row],[Apr_2027_A]] | DZ17: =IFERROR(Table410[[#This Row],[May_2027_Days_Forecast]]*Table410[[#This Row],[Cost Boolean]]*(VLOOKUP(Table410[[#This Row],[RATE CONCAT]],Tables!I:N,6,0)),0) | EA17: 0 | EB17: =Table410[[#This Row],[May_2027_F]]-Table410[[#This Row],[May_2027_A]] | EC17: =IFERROR(Table410[[#This Row],[Jun_2027_Days_Forecast]]*Table410[[#This Row],[Cost Boolean]]*(VLOOKUP(Table410[[#This Row],[RATE CONCAT]],Tables!I:N,6,0)),0) | ED17: 0 | EE17: =Table410[[#This Row],[Jun_2027_F]]-Table410[[#This Row],[Jun_2027_A]] | EF17: =IFERROR(Table410[[#This Row],[Jul_2027_Days_Forecast]]*Table410[[#This Row],[Cost Boolean]]*(VLOOKUP(Table410[[#This Row],[RATE CONCAT]],Tables!I:N,6,0)),0) | EG17: 0 | EH17: =Table410[[#This Row],[Jul_2027_F]]-Table410[[#This Row],[Jul_2027_A]] | EI17: =IFERROR(Table410[[#This Row],[Aug_2027_Days_Forecast]]*Table410[[#This Row],[Cost Boolean]]*(VLOOKUP(Table410[[#This Row],[RATE CONCAT]],Tables!I:N,6,0)),0) | EJ17: 0 | EK17: =Table410[[#This Row],[Aug_2027_F]]-Table410[[#This Row],[Aug_2027_A]] | EL17: =IFERROR(Table410[[#This Row],[Sep_2027_Days_Forecast]]*Table410[[#This Row],[Cost Boolean]]*(VLOOKUP(Table410[[#This Row],[RATE CONCAT]],Tables!I:N,6,0)),0) | EM17: 0 | EN17: =Table410[[#This Row],[Sep_2027_F]]-Table410[[#This Row],[Sep_2027_A]] | EO17: =IFERROR(Table410[[#This Row],[Oct_2027_Days_Forecast]]*Table410[[#This Row],[Cost Boolean]]*(VLOOKUP(Table410[[#This Row],[RATE CONCAT]],Tables!I:N,6,0)),0) | EP17: 0 | EQ17: =Table410[[#This Row],[Oct_2027_F]]-Table410[[#This Row],[Oct_2027_A]] | ER17: =IFERROR(Table410[[#This Row],[Nov_2027_Days_Forecast]]*Table410[[#This Row],[Cost Boolean]]*(VLOOKUP(Table410[[#This Row],[RATE CONCAT]],Tables!I:N,6,0)),0) | ES17: 0 | ET17: =Table410[[#This Row],[Nov_2027_F]]-Table410[[#This Row],[Nov_2027_A]] | EU17: =IFERROR(Table410[[#This Row],[Dec_2027_Days_Forecast]]*Table410[[#This Row],[Cost Boolean]]*(VLOOKUP(Table410[[#This Row],[RATE CONCAT]],Tables!I:N,6,0)),0) | EV17: 0 | EW17: =Table410[[#This Row],[Dec_2027_F]]-Table410[[#This Row],[Dec_2027_A]]
A18: PDSFS1027 | B18: USDF | C18: Staff | D18: Raquel Alvarado | E18: Shell Business | G18: United States | H18: 2 | J18: USDF Business Lead | K18: In-seat | L18: 0 | M18: HOU | N18: Chartering management | O18: Opex | P18: Business | Q18: TBD | R18: 46023 | S18: 46387 | T18: 46023 | U18: 46387 | V18: 46023 | W18: 46387 | Y18: =CONCATENATE(Table410[[#This Row],[JG]],Table410[[#This Row],[Country]],Table410[[#This Row],[Resource Provider]]) | Z18: =VLOOKUP(Table410[[#This Row],[RATE CONCAT]],Tables!I:N,5,0) | AC18: 10 | AD18: 10 | AE18: 10 | AF18: 9 | AG18: 9 | AH18: 9 | AI18: 10 | AJ18: 10 | AK18: 10 | AN18: =IFERROR(AVERAGE(Table410[[#This Row],[Jan_2026_Days_Forecast]:[Dec_2026_Days_Forecast]]),0)/19 | AO18: =IFERROR(AVERAGE(Table410[[#This Row],[Jan_2026_Days_Actual]:[Dec_2026_Days_Actual]]),0)/19 | AQ18: 10 | AR18: 10 | AS18: 10 | AT18: 9 | AU18: 9 | AV18: 9 | AW18: 10 | AX18: 10 | AY18: 10 | BB18: =IFERROR(AVERAGE(Table410[[#This Row],[Jan_2027_Days_Forecast]:[Dec_2027_Days_Forecast]]),0) | BQ18: =IFERROR(Table410[[#This Row],[Jan_2026_Days_Forecast]]*Table410[[#This Row],[Cost Boolean]]*(VLOOKUP(Table410[[#This Row],[RATE CONCAT]],Tables!I:N,5,0)),0) | BR18: =IFERROR(Table410[[#This Row],[Jan_2026_Days_Actual]]*Table410[[#This Row],[Cost Boolean]]*(VLOOKUP(Table410[[#This Row],[RATE CONCAT]],Tables!I:N,5,0)),0) | BS18: =Table410[[#This Row],[Jan_2026_F]]-Table410[[#This Row],[Jan_2026_A]] | BU18: =IFERROR(Table410[[#This Row],[Feb_2026_Days_Forecast]]*Table410[[#This Row],[Cost Boolean]]*(VLOOKUP(Table410[[#This Row],[RATE CONCAT]],Tables!I:N,5,0)),0) | BV18: =IFERROR(Table410[[#This Row],[Feb_2026_Days_Actual]]*Table410[[#This Row],[Cost Boolean]]*(VLOOKUP(Table410[[#This Row],[RATE CONCAT]],Tables!I:N,5,0)),0) | BW18: =Table410[[#This Row],[Feb_2026_F]]-Table410[[#This Row],[Feb_2026_A]] | BY18: =IFERROR(Table410[[#This Row],[Mar_2026_Days_Forecast]]*Table410[[#This Row],[Cost Boolean]]*(VLOOKUP(Table410[[#This Row],[RATE CONCAT]],Tables!I:N,5,0)),0) | BZ18: =IFERROR(Table410[[#This Row],[Mar_2026_Days_Actual]]*Table410[[#This Row],[Cost Boolean]]*(VLOOKUP(Table410[[#This Row],[RATE CONCAT]],Tables!I:N,5,0)),0) | CA18: =Table410[[#This Row],[Mar_2026_F]]-Table410[[#This Row],[Mar_2026_A]] | CC18: =IFERROR(Table410[[#This Row],[Apr_2026_Days_Forecast]]*Table410[[#This Row],[Cost Boolean]]*(VLOOKUP(Table410[[#This Row],[RATE CONCAT]],Tables!I:N,5,0)),0) | CD18: =IFERROR(Table410[[#This Row],[Apr_2026_Days_Actual]]*Table410[[#This Row],[Cost Boolean]]*(VLOOKUP(Table410[[#This Row],[RATE CONCAT]],Tables!I:N,5,0)),0) | CE18: =Table410[[#This Row],[Apr_2026_F]]-Table410[[#This Row],[Apr_2026_A]] | CG18: =IFERROR(Table410[[#This Row],[May_2026_Days_Forecast]] *Table410[[#This Row],[Cost Boolean]]*(VLOOKUP(Table410[[#This Row],[RATE CONCAT]],Tables!I:N,5,0)),0) | CH18: =IFERROR(Table410[[#This Row],[May_2026_Days_Actual]]*Table410[[#This Row],[Cost Boolean]]*(VLOOKUP(Table410[[#This Row],[RATE CONCAT]],Tables!I:N,5,0)),0) | CI18: =Table410[[#This Row],[May_2026_F]]-Table410[[#This Row],[May_2026_A]] | CK18: =IFERROR(Table410[[#This Row],[Jun_2026_Days_Forecast]]*Table410[[#This Row],[Cost Boolean]]*(VLOOKUP(Table410[[#This Row],[RATE CONCAT]],Tables!I:N,5,0)),0) | CL18: =IFERROR(Table410[[#This Row],[Jun_2026_Days_Actual]]*Table410[[#This Row],[Cost Boolean]]*(VLOOKUP(Table410[[#This Row],[RATE CONCAT]],Tables!I:N,5,0)),0) | CM18: =Table410[[#This Row],[Jun_2026_F]]-Table410[[#This Row],[Jun_2026_A]] | CO18: =IFERROR(Table410[[#This Row],[Jul_2026_Days_Forecast]]*Table410[[#This Row],[Cost Boolean]]*(VLOOKUP(Table410[[#This Row],[RATE CONCAT]],Tables!I:N,5,0)),0) | CP18: =IFERROR(Table410[[#This Row],[Jul_2026_Days_Actual]]*Table410[[#This Row],[Cost Boolean]]*(VLOOKUP(Table410[[#This Row],[RATE CONCAT]],Tables!I:N,5,0)),0) | CQ18: =Table410[[#This Row],[Jul_2026_F]]-Table410[[#This Row],[Jul_2026_A]] | CS18: =IFERROR(Table410[[#This Row],[Aug_2026_Days_Forecast]]*Table410[[#This Row],[Cost Boolean]]*(VLOOKUP(Table410[[#This Row],[RATE CONCAT]],Tables!I:N,5,0)),0) | CT18: =IFERROR(Table410[[#This Row],[Aug_2026_Days_Actual]]*Table410[[#This Row],[Cost Boolean]]*(VLOOKUP(Table410[[#This Row],[RATE CONCAT]],Tables!I:N,5,0)),0) | CU18: =Table410[[#This Row],[Aug_2026_F]]-Table410[[#This Row],[Aug_2026_A]] | CW18: =IFERROR(Table410[[#This Row],[Sep_2026_Days_Forecast]]*Table410[[#This Row],[Cost Boolean]]*(VLOOKUP(Table410[[#This Row],[RATE CONCAT]],Tables!I:N,5,0)),0) | CX18: =IFERROR(Table410[[#This Row],[Sep_2026_Days_Actual]]*Table410[[#This Row],[Cost Boolean]]*(VLOOKUP(Table410[[#This Row],[RATE CONCAT]],Tables!I:N,5,0)),0) | CY18: =Table410[[#This Row],[Sep_2026_F]]-Table410[[#This Row],[Sep_2026_A]] | DA18: =IFERROR(Table410[[#This Row],[Oct_2026_Days_Forecast]]*Table410[[#This Row],[Cost Boolean]]*(VLOOKUP(Table410[[#This Row],[RATE CONCAT]],Tables!I:N,5,0)),0) | DB18: =IFERROR(Table410[[#This Row],[Oct_2026_Days_Actual]]*Table410[[#This Row],[Cost Boolean]]*(VLOOKUP(Table410[[#This Row],[RATE CONCAT]],Tables!I:N,5,0)),0) | DC18: =Table410[[#This Row],[Oct_2026_F]]-Table410[[#This Row],[Oct_2026_A]] | DE18: =IFERROR(Table410[[#This Row],[Nov_2026_Days_Forecast]]*Table410[[#This Row],[Cost Boolean]]*(VLOOKUP(Table410[[#This Row],[RATE CONCAT]],Tables!I:N,5,0)),0) | DF18: =IFERROR(Table410[[#This Row],[Nov_2026_Days_Actual]]*Table410[[#This Row],[Cost Boolean]]*(VLOOKUP(Table410[[#This Row],[RATE CONCAT]],Tables!I:N,5,0)),0) | DG18: =Table410[[#This Row],[Nov_2026_F]]-Table410[[#This Row],[Nov_2026_A]] | DI18: =IFERROR(Table410[[#This Row],[Dec_2026_Days_Forecast]]*Table410[[#This Row],[Cost Boolean]]*(VLOOKUP(Table410[[#This Row],[RATE CONCAT]],Tables!I:N,5,0)),0) | DJ18: =IFERROR(Table410[[#This Row],[Dec_2026_Days_Actual]]*Table410[[#This Row],[Cost Boolean]]*(VLOOKUP(Table410[[#This Row],[RATE CONCAT]],Tables!I:N,5,0)),0) | DK18: =Table410[[#This Row],[Dec_2026_F]]-Table410[[#This Row],[Dec_2026_A]] | DN18: =IFERROR(Table410[[#This Row],[Jan_2027_Days_Forecast]]*Table410[[#This Row],[Cost Boolean]]*(VLOOKUP(Table410[[#This Row],[RATE CONCAT]],Tables!I:N,6,0)),0) | DO18: 0 | DP18: =Table410[[#This Row],[Jan_2027_F]]-Table410[[#This Row],[Jan_2027_A]] | DQ18: =IFERROR(Table410[[#This Row],[Feb_2027_Days_Forecast]]*Table410[[#This Row],[Cost Boolean]]*(VLOOKUP(Table410[[#This Row],[RATE CONCAT]],Tables!I:N,6,0)),0) | DR18: 0 | DS18: =Table410[[#This Row],[Feb_2027_F]]-Table410[[#This Row],[Feb_2027_A]] | DT18: =IFERROR(Table410[[#This Row],[Mar_2027_Days_Forecast]]*Table410[[#This Row],[Cost Boolean]]*(VLOOKUP(Table410[[#This Row],[RATE CONCAT]],Tables!I:N,6,0)),0) | DU18: 0 | DV18: =Table410[[#This Row],[Mar_2027_F]]-Table410[[#This Row],[Mar_2027_A]] | DW18: =IFERROR(Table410[[#This Row],[Apr_2027_Days_Forecast]]*Table410[[#This Row],[Cost Boolean]]*(VLOOKUP(Table410[[#This Row],[RATE CONCAT]],Tables!I:N,6,0)),0) | DX18: 0 | DY18: =Table410[[#This Row],[Apr_2027_F]]-Table410[[#This Row],[Apr_2027_A]] | DZ18: =IFERROR(Table410[[#This Row],[May_2027_Days_Forecast]]*Table410[[#This Row],[Cost Boolean]]*(VLOOKUP(Table410[[#This Row],[RATE CONCAT]],Tables!I:N,6,0)),0) | EA18: 0 | EB18: =Table410[[#This Row],[May_2027_F]]-Table410[[#This Row],[May_2027_A]] | EC18: =IFERROR(Table410[[#This Row],[Jun_2027_Days_Forecast]]*Table410[[#This Row],[Cost Boolean]]*(VLOOKUP(Table410[[#This Row],[RATE CONCAT]],Tables!I:N,6,0)),0) | ED18: 0 | EE18: =Table410[[#This Row],[Jun_2027_F]]-Table410[[#This Row],[Jun_2027_A]] | EF18: =IFERROR(Table410[[#This Row],[Jul_2027_Days_Forecast]]*Table410[[#This Row],[Cost Boolean]]*(VLOOKUP(Table410[[#This Row],[RATE CONCAT]],Tables!I:N,6,0)),0) | EG18: 0 | EH18: =Table410[[#This Row],[Jul_2027_F]]-Table410[[#This Row],[Jul_2027_A]] | EI18: =IFERROR(Table410[[#This Row],[Aug_2027_Days_Forecast]]*Table410[[#This Row],[Cost Boolean]]*(VLOOKUP(Table410[[#This Row],[RATE CONCAT]],Tables!I:N,6,0)),0) | EJ18: 0 | EK18: =Table410[[#This Row],[Aug_2027_F]]-Table410[[#This Row],[Aug_2027_A]] | EL18: =IFERROR(Table410[[#This Row],[Sep_2027_Days_Forecast]]*Table410[[#This Row],[Cost Boolean]]*(VLOOKUP(Table410[[#This Row],[RATE CONCAT]],Tables!I:N,6,0)),0) | EM18: 0 | EN18: =Table410[[#This Row],[Sep_2027_F]]-Table410[[#This Row],[Sep_2027_A]] | EO18: =IFERROR(Table410[[#This Row],[Oct_2027_Days_Forecast]]*Table410[[#This Row],[Cost Boolean]]*(VLOOKUP(Table410[[#This Row],[RATE CONCAT]],Tables!I:N,6,0)),0) | EP18: 0 | EQ18: =Table410[[#This Row],[Oct_2027_F]]-Table410[[#This Row],[Oct_2027_A]] | ER18: =IFERROR(Table410[[#This Row],[Nov_2027_Days_Forecast]]*Table410[[#This Row],[Cost Boolean]]*(VLOOKUP(Table410[[#This Row],[RATE CONCAT]],Tables!I:N,6,0)),0) | ES18: 0 | ET18: =Table410[[#This Row],[Nov_2027_F]]-Table410[[#This Row],[Nov_2027_A]] | EU18: =IFERROR(Table410[[#This Row],[Dec_2027_Days_Forecast]]*Table410[[#This Row],[Cost Boolean]]*(VLOOKUP(Table410[[#This Row],[RATE CONCAT]],Tables!I:N,6,0)),0) | EV18: 0 | EW18: =Table410[[#This Row],[Dec_2027_F]]-Table410[[#This Row],[Dec_2027_A]]
